Workbook

Sheet CQC Summary Report
A1: Swan Care Home – CQC Regulatory Action Plan Summary
A3: Overall Compliance | B3: =IF(B4=0,0,B5/B4) -> 0
A4: Total Actions | B4: 111
A5: Completed / Verified | B5: =COUNTIF('Master Action Plan'!M:M,"Completed")+COUNTIF('Master Action Plan'!M:M,"Verified") -> 0
A6: Outstanding | B6: 109
A7: Overdue | B7: =COUNTIFS('Master Action Plan'!K:K,"<"&TODAY(),'Master Action Plan'!M:M,"<>Completed",'Master Action Plan'!M:M,"<>Verified") -> 0
A8: Critical Actions | B8: 67
A9: Evidence Verified | B9: =COUNTIF('Evidence Tracker'!H:H,"Yes") -> 0
A10: Overall RAG | B10: =IF(B3>=0.9,"Green",IF(B3>=0.6,"Amber","Red")) -> Red
A12: Regulation | B12: Purpose / Area | C12: Total Actions | D12: Completed | E12: Verified | F12: Outstanding | G12: Overdue | H12: Compliance % | I12: Overall RAG | J12: Comments
A13: ='Regulation Tracker'!A2 -> Reg 9 | B13: ='Regulation Tracker'!B2 -> Person-centred care | C13: ='Regulation Tracker'!C2 -> 10 | D13: ='Regulation Tracker'!D2 -> 0 | E13: ='Regulation Tracker'!E2 -> 0 | F13: ='Regulation Tracker'!F2 -> 10 | G13: ='Regulation Tracker'!G2 -> 0 | H13: ='Regulation Tracker'!H2 -> 0 | ... J13: ='Regulation Tracker'!J2 -> 0
A14: ='Regulation Tracker'!A3 -> Reg 10 | B14: ='Regulation Tracker'!B3 -> Dignity and respect | C14: ='Regulation Tracker'!C3 -> 10 | D14: ='Regulation Tracker'!D3 -> 0 | E14: ='Regulation Tracker'!E3 -> 0 | F14: ='Regulation Tracker'!F3 -> 10 | G14: ='Regulation Tracker'!G3 -> 0 | H14: ='Regulation Tracker'!H3 -> 0 | ... J14: ='Regulation Tracker'!J3 -> 0
A15: ='Regulation Tracker'!A4 -> Reg 11 | B15: ='Regulation Tracker'!B4 -> Need for consent / MCA | C15: ='Regulation Tracker'!C4 -> 10 | D15: ='Regulation Tracker'!D4 -> 0 | E15: ='Regulation Tracker'!E4 -> 0 | F15: ='Regulation Tracker'!F4 -> 10 | G15: ='Regulation Tracker'!G4 -> 0 | H15: ='Regulation Tracker'!H4 -> 0 | ... J15: ='Regulation Tracker'!J4 -> 0
A16: ='Regulation Tracker'!A5 -> Reg 12 | B16: ='Regulation Tracker'!B5 -> Safe care and treatment | C16: ='Regulation Tracker'!C5 -> 23 | D16: ='Regulation Tracker'!D5 -> 0 | E16: ='Regulation Tracker'!E5 -> 0 | F16: ='Regulation Tracker'!F5 -> 23 | G16: ='Regulation Tracker'!G5 -> 0 | H16: ='Regulation Tracker'!H5 -> 0 | ... J16: ='Regulation Tracker'!J5 -> 0
A17: ='Regulation Tracker'!A6 -> Reg 13 | B17: ='Regulation Tracker'!B6 -> Safeguarding | C17: ='Regulation Tracker'!C6 -> 9 | D17: ='Regulation Tracker'!D6 -> 0 | E17: ='Regulation Tracker'!E6 -> 0 | F17: ='Regulation Tracker'!F6 -> 9 | G17: ='Regulation Tracker'!G6 -> 0 | H17: ='Regulation Tracker'!H6 -> 0 | ... J17: ='Regulation Tracker'!J6 -> 0
A18: ='Regulation Tracker'!A7 -> Reg 15 | B18: ='Regulation Tracker'!B7 -> Premises and equipment | C18: 23 | D18: 0 | E18: 0 | F18: 23 | G18: 0 | H18: 0 | I18: Red | J18: ='Regulation Tracker'!J7 -> 0
A19: ='Regulation Tracker'!A8 -> Reg 17 | B19: ='Regulation Tracker'!B8 -> Good governance | C19: 9 | D19: 0 | E19: 0 | F19: 9 | G19: 0 | H19: 0 | I19: Red | J19: ='Regulation Tracker'!J8 -> 0
A20: ='Regulation Tracker'!A9 -> Reg 18 | B20: ='Regulation Tracker'!B9 -> Staffing, training and competence | C20: ='Regulation Tracker'!C9 -> 10 | D20: ='Regulation Tracker'!D9 -> 0 | E20: ='Regulation Tracker'!E9 -> 0 | F20: ='Regulation Tracker'!F9 -> 10 | G20: ='Regulation Tracker'!G9 -> 0 | H20: ='Regulation Tracker'!H9 -> 0 | ... J20: ='Regulation Tracker'!J9 -> 0
A21: ='Regulation Tracker'!A10 -> Reg 19 | B21: ='Regulation Tracker'!B10 -> Fit and proper persons employed | C21: 23 | D21: 0 | E21: 0 | F21: 23 | G21: 0 | H21: 0 | I21: Red | J21: ='Regulation Tracker'!J10 -> 0
A24: Management Comments / CQC Update
A25: Use this section for a concise weekly update to CQC/commissioners. This workbook is not a 10-day recovery plan; it is an ongoing regulatory action plan with evidence tracking, RAG status and verification.

Sheet Master Action Plan
A1: Action ID | B1: Regulation | C1: Key Question | D1: CQC Concern / Finding | E1: Root Cause | F1: Immediate Corrective Action | G1: Sustainable Preventative Action | H1: Responsible Person | I1: Priority | J1: Start Date | K1: Target Date | L1: Completion Date | M1: Status | N1: Auto RAG | O1: Comments | P1: Evidence Required | Q1: Evidence Ref | R1: Evidence Verified? | S1: Verified By | T1: Verification Date | U1: CQC / NOP Reference
A2: A001 | B2: Reg 9 | C2: Responsive | D2: Care plans are generic and not sufficiently person-centred | E2: Care planning system did not evidence individualised assessment and review | F2: Review and rewrite affected care plans with specific resident guidance Immediate review completed. Governance systems strengthened, audits implemented, leadership oversight increased, policies reviewed, environmental improvements commenced, staff training programme implemented and risks escalated where required. | G2: Monthly person-centred care plan audit and resident/family review cycle Embed improvements through monthly governance meetings, audit programme, compliance calendar, competency assessments, supervisions, provider oversight, mock inspections, continuous quality improvement, mandatory e-learning and face-to-face competency training (w/c 6 July 2026). | H2: JM Training and consultancy/Nominated Individual/Manager | I2: High | J2: 46201 | K2: 46213 | M2: In Progress | N2: =IF(M2="Verified","Green",IF(M2="Completed","Amber - Awaiting Verification",IF(K2<TODAY(),"Red - Overdue",IF(M2="In Progress","Amber","Red - Not Started")))) -> Amber | O2: Staff are ungoing training with JM consulting to ensure they are competent in the language that it is used throughout the home to protect dignity. Staff are also doing training with a training provider and E-learning to enhance their training. JM consulting will also be doing observation/competency assessments to ensure all staff are able to deliver the best Care plans and care notes with family involvement. We will be implementing key workers for each resident and it will be their responsibility to ensure that it is up to date. The registered manager will be doing checks to ensure that it it reviewed correctly and a compliance officer will verify this. implemented and continue to be embedded across the service. The home currently has no residents, allowing governance systems, documentation, environmental improvements and workforce development to be fully established prior to future admissions. Mandatory e-learning is monitored through the Training Matrix. Face-to-face training (w/c 6 July 2026) covers Care Planning, Care Notes, Professional Observations, Oral Care, MCA, DoLS, Dementia, Safeguarding, Personal Care, Duty of Candour, Mental Health, Trauma-informed Care, Behaviour Support, Risk Assessment and professional terminology. Fire alarm upgrade to Category L1 and fire door replacement are in progress. Weekly/monthly fire compliance checks will recommence once works are completed and commissioned. PEEPs and dependency reviews will commence upon admission of residents. Compliance monitored via governance, audits and provider oversight. | P2: Updated care plan, review sheet, family/professional involvement record Governance Workbook; Master Action Plan; Audit Workbook 1; Audit Workbook 2; Compliance Calendar; Fire & Compliance Workbook; Cleaning Workbook; Dependency Tool & PEEPs; Handover & Allocation Workbook; Training Matrix; Personnel Files; Resident Admission Pack; Funding Pack; New Resident Tracker; Agency Induction; Agency Competency; Face-to-face Training Records (w/c 6 July 2026); Competency Assessments; Supervisions; Professional Discussions; Mock Inspections; Fire Alarm Upgrade; Fire Door Replacement. | Q2: GW; MAP; AW1; AW2; CC; FCW; CS; DT; HAW; TM; PF; RAP; FP; NRT | R2: No | U2: NoP Reg 9
A3: A002 | B3: Reg 9 | C3: Responsive | D3: Behaviour support plans do not explain individual triggers and calming approaches | E3: Care planning system did not evidence individualised assessment and review | F3: Review and rewrite affected care plans with specific resident guidance Immediate review completed. Governance systems strengthened, audits implemented, leadership oversight increased, policies reviewed, environmental improvements commenced, staff training programme implemented and risks escalated where required. | G3: Monthly person-centred care plan audit and resident/family review cycle Embed improvements through monthly governance meetings, audit programme, compliance calendar, competency assessments, supervisions, provider oversight, mock inspections, continuous quality improvement, mandatory e-learning and face-to-face competency training (w/c 6 July 2026). | H3: Registered Manager | I3: High | J3: 46201 | K3: 46215 | M3: In Progress | N3: =IF(M3="Verified","Green",IF(M3="Completed","Amber - Awaiting Verification",IF(K3<TODAY(),"Red - Overdue",IF(M3="In Progress","Amber","Red - Not Started")))) -> Amber | O3: See Row 1 Comments column implemented and continue to be embedded across the service. The home currently has no residents, allowing governance systems, documentation, environmental improvements and workforce development to be fully established prior to future admissions. Mandatory e-learning is monitored through the Training Matrix. Face-to-face training (w/c 6 July 2026) covers Care Planning, Care Notes, Professional Observations, Oral Care, MCA, DoLS, Dementia, Safeguarding, Personal Care, Duty of Candour, Mental Health, Trauma-informed Care, Behaviour Support, Risk Assessment and professional terminology. Fire alarm upgrade to Category L1 and fire door replacement are in progress. Weekly/monthly fire compliance checks will recommence once works are completed and commissioned. PEEPs and dependency reviews will commence upon admission of residents. Compliance monitored via governance, audits and provider oversight. | P3: Updated care plan, review sheet, family/professional involvement record Governance Workbook; Master Action Plan; Audit Workbook 1; Audit Workbook 2; Compliance Calendar; Fire & Compliance Workbook; Cleaning Workbook; Dependency Tool & PEEPs; Handover & Allocation Workbook; Training Matrix; Personnel Files; Resident Admission Pack; Funding Pack; New Resident Tracker; Agency Induction; Agency Competency; Face-to-face Training Records (w/c 6 July 2026); Competency Assessments; Supervisions; Professional Discussions; Mock Inspections; Fire Alarm Upgrade; Fire Door Replacement. | Q3: GW; MAP; AW1; AW2; CC; FCW; CS; DT; HAW; TM; PF; RAP; FP; NRT | R3: No | U3: NoP Reg 9
A4: A003 | B4: Reg 9 | C4: Responsive | D4: End-of-life care plans lack holistic comfort, dignity and symptom support | E4: Care planning system did not evidence individualised assessment and review | F4: Review and rewrite affected care plans with specific resident guidance Immediate review completed. Governance systems strengthened, audits implemented, leadership oversight increased, policies reviewed, environmental improvements commenced, staff training programme implemented and risks escalated where required. | G4: Monthly person-centred care plan audit and resident/family review cycle Embed improvements through monthly governance meetings, audit programme, compliance calendar, competency assessments, supervisions, provider oversight, mock inspections, continuous quality improvement, mandatory e-learning and face-to-face competency training (w/c 6 July 2026). | H4: Registered Manager | I4: High | J4: 46201 | K4: 46215 | M4: In Progress | N4: =IF(M5="Verified","Green",IF(M5="Completed","Amber - Awaiting Verification",IF(K4<TODAY(),"Red - Overdue",IF(M5="In Progress","Amber","Red - Not Started")))) -> Amber | O4: See Row 1 Comments column implemented and continue to be embedded across the service. The home currently has no residents, allowing governance systems, documentation, environmental improvements and workforce development to be fully established prior to future admissions. Mandatory e-learning is monitored through the Training Matrix. Face-to-face training (w/c 6 July 2026) covers Care Planning, Care Notes, Professional Observations, Oral Care, MCA, DoLS, Dementia, Safeguarding, Personal Care, Duty of Candour, Mental Health, Trauma-informed Care, Behaviour Support, Risk Assessment and professional terminology. Fire alarm upgrade to Category L1 and fire door replacement are in progress. Weekly/monthly fire compliance checks will recommence once works are completed and commissioned. PEEPs and dependency reviews will commence upon admission of residents. Compliance monitored via governance, audits and provider oversight. | P4: Updated care plan, review sheet, family/professional involvement record Governance Workbook; Master Action Plan; Audit Workbook 1; Audit Workbook 2; Compliance Calendar; Fire & Compliance Workbook; Cleaning Workbook; Dependency Tool & PEEPs; Handover & Allocation Workbook; Training Matrix; Personnel Files; Resident Admission Pack; Funding Pack; New Resident Tracker; Agency Induction; Agency Competency; Face-to-face Training Records (w/c 6 July 2026); Competency Assessments; Supervisions; Professional Discussions; Mock Inspections; Fire Alarm Upgrade; Fire Door Replacement. | Q4: GW; MAP; AW1; AW2; CC; FCW; CS; DT; HAW; TM; PF; RAP; FP; NRT | R4: No | U4: NoP Reg 9
A5: A004 | B5: Reg 9 | C5: Responsive | D5: Activities are not meaningful or based on life history, culture, preferences or abilities | E5: Care planning system did not evidence individualised assessment and review | F5: Review and rewrite affected care plans with specific resident guidance Immediate review completed. Governance systems strengthened, audits implemented, leadership oversight increased, policies reviewed, environmental improvements commenced, staff training programme implemented and risks escalated where required. | G5: Monthly person-centred care plan audit and resident/family review cycle Embed improvements through monthly governance meetings, audit programme, compliance calendar, competency assessments, supervisions, provider oversight, mock inspections, continuous quality improvement, mandatory e-learning and face-to-face competency training (w/c 6 July 2026). | H5: Registered Manager | I5: High | J5: 46201 | K5: 46215 | M5: In Progress | N5: =IF(M6="Verified","Green",IF(M6="Completed","Amber - Awaiting Verification",IF(K5<TODAY(),"Red - Overdue",IF(M6="In Progress","Amber","Red - Not Started")))) -> Amber | O5: The service has implemented a comprehensive person-centred activity programme. Every resident now has an individual Meaningful Activity Assessment based on their life history, culture, religion, interests, previous occupation, abilities and personal goals. Individual activity care plans have replaced generic activity schedules. Staff receive training in meaningful occupation and dementia-informed engagement, with daily records documenting resident outcomes, emotional wellbeing and participation. Monthly audits and management oversight ensure activities remain personalised and responsive to changing needs. This is created in the new resident tracker. implemented and continue to be embedded across the service. The home currently has no residents, allowing governance systems, documentation, environmental improvements and workforce development to be fully established prior to future admissions. Mandatory e-learning is monitored through the Training Matrix. Face-to-face training (w/c 6 July 2026) covers Care Planning, Care Notes, Professional Observations, Oral Care, MCA, DoLS, Dementia, Safeguarding, Personal Care, Duty of Candour, Mental Health, Trauma-informed Care, Behaviour Support, Risk Assessment and professional terminology. Fire alarm upgrade to Category L1 and fire door replacement are in progress. Weekly/monthly fire compliance checks will recommence once works are completed and commissioned. PEEPs and dependency reviews will commence upon admission of residents. Compliance monitored via governance, audits and provider oversight. | P5: Updated care plan, review sheet, family/professional involvement record Governance Workbook; Master Action Plan; Audit Workbook 1; Audit Workbook 2; Compliance Calendar; Fire & Compliance Workbook; Cleaning Workbook; Dependency Tool & PEEPs; Handover & Allocation Workbook; Training Matrix; Personnel Files; Resident Admission Pack; Funding Pack; New Resident Tracker; Agency Induction; Agency Competency; Face-to-face Training Records (w/c 6 July 2026); Competency Assessments; Supervisions; Professional Discussions; Mock Inspections; Fire Alarm Upgrade; Fire Door Replacement. | Q5: New resident tracker 2026 GW; MAP; AW1; AW2; CC; FCW; CS; DT; HAW; TM; PF; RAP; FP; NRT | R5: No | U5: NoP Reg 9
A6: A005 | B6: Reg 9 | C6: Responsive | D6: Television/passive activity is being recorded as meaningful engagement | E6: Care planning system did not evidence individualised assessment and review | F6: Review and rewrite affected care plans with specific resident guidance Immediate review completed. Governance systems strengthened, audits implemented, leadership oversight increased, policies reviewed, environmental improvements commenced, staff training programme implemented and risks escalated where required. | G6: Monthly person-centred care plan audit and resident/family review cycle Embed improvements through monthly governance meetings, audit programme, compliance calendar, competency assessments, supervisions, provider oversight, mock inspections, continuous quality improvement, mandatory e-learning and face-to-face competency training (w/c 6 July 2026). | H6: Registered Manager | I6: High | J6: 46201 | K6: 46215 | M6: In Progress | N6: =IF(M6="Verified","Green",IF(M6="Completed","Amber - Awaiting Verification",IF(K6<TODAY(),"Red - Overdue",IF(M6="In Progress","Amber","Red - Not Started")))) -> Amber | O6: See Row 4 implemented and continue to be embedded across the service. The home currently has no residents, allowing governance systems, documentation, environmental improvements and workforce development to be fully established prior to future admissions. Mandatory e-learning is monitored through the Training Matrix. Face-to-face training (w/c 6 July 2026) covers Care Planning, Care Notes, Professional Observations, Oral Care, MCA, DoLS, Dementia, Safeguarding, Personal Care, Duty of Candour, Mental Health, Trauma-informed Care, Behaviour Support, Risk Assessment and professional terminology. Fire alarm upgrade to Category L1 and fire door replacement are in progress. Weekly/monthly fire compliance checks will recommence once works are completed and commissioned. PEEPs and dependency reviews will commence upon admission of residents. Compliance monitored via governance, audits and provider oversight. | P6: Updated care plan, review sheet, family/professional involvement record Governance Workbook; Master Action Plan; Audit Workbook 1; Audit Workbook 2; Compliance Calendar; Fire & Compliance Workbook; Cleaning Workbook; Dependency Tool & PEEPs; Handover & Allocation Workbook; Training Matrix; Personnel Files; Resident Admission Pack; Funding Pack; New Resident Tracker; Agency Induction; Agency Competency; Face-to-face Training Records (w/c 6 July 2026); Competency Assessments; Supervisions; Professional Discussions; Mock Inspections; Fire Alarm Upgrade; Fire Door Replacement. | Q6: New resident tracker 2026 GW; MAP; AW1; AW2; CC; FCW; CS; DT; HAW; TM; PF; RAP; FP; NRT | R6: No | U6: NoP Reg 9
A7: A006 | B7: Reg 9 | C7: Responsive | D7: Care plan reviews are not triangulated with daily notes, incidents, MAR, risk assessments and family feedback | E7: Care planning system did not evidence individualised assessment and review | F7: Review and rewrite affected care plans with specific resident guidance Immediate review completed. Governance systems strengthened, audits implemented, leadership oversight increased, policies reviewed, environmental improvements commenced, staff training programme implemented and risks escalated where required. | G7: Monthly person-centred care plan audit and resident/family review cycle Embed improvements through monthly governance meetings, audit programme, compliance calendar, competency assessments, supervisions, provider oversight, mock inspections, continuous quality improvement, mandatory e-learning and face-to-face competency training (w/c 6 July 2026). | H7: Registered Manager | I7: High | J7: 46201 | K7: 46215 | M7: In Progress | N7: =IF(M7="Verified","Green",IF(M7="Completed","Amber - Awaiting Verification",IF(K7<TODAY(),"Red - Overdue",IF(M7="In Progress","Amber","Red - Not Started")))) -> Amber | O7: Triangulated checklist implemented and continue to be embedded across the service. The home currently has no residents, allowing governance systems, documentation, environmental improvements and workforce development to be fully established prior to future admissions. Mandatory e-learning is monitored through the Training Matrix. Face-to-face training (w/c 6 July 2026) covers Care Planning, Care Notes, Professional Observations, Oral Care, MCA, DoLS, Dementia, Safeguarding, Personal Care, Duty of Candour, Mental Health, Trauma-informed Care, Behaviour Support, Risk Assessment and professional terminology. Fire alarm upgrade to Category L1 and fire door replacement are in progress. Weekly/monthly fire compliance checks will recommence once works are completed and commissioned. PEEPs and dependency reviews will commence upon admission of residents. Compliance monitored via governance, audits and provider oversight. | P7: Updated care plan, review sheet, family/professional involvement record Governance Workbook; Master Action Plan; Audit Workbook 1; Audit Workbook 2; Compliance Calendar; Fire & Compliance Workbook; Cleaning Workbook; Dependency Tool & PEEPs; Handover & Allocation Workbook; Training Matrix; Personnel Files; Resident Admission Pack; Funding Pack; New Resident Tracker; Agency Induction; Agency Competency; Face-to-face Training Records (w/c 6 July 2026); Competency Assessments; Supervisions; Professional Discussions; Mock Inspections; Fire Alarm Upgrade; Fire Door Replacement. | Q7: GW; MAP; AW1; AW2; CC; FCW; CS; DT; HAW; TM; PF; RAP; FP; NRT | R7: No | U7: NoP Reg 9
A8: A007 | B8: Reg 9 | C8: Responsive | D8: Resident preferences for personal care, routines and independence are not clearly recorded | E8: Care planning system did not evidence individualised assessment and review | F8: Review and rewrite affected care plans with specific resident guidance Immediate review completed. Governance systems strengthened, audits implemented, leadership oversight increased, policies reviewed, environmental improvements commenced, staff training programme implemented and risks escalated where required. | G8: Monthly person-centred care plan audit and resident/family review cycle Embed improvements through monthly governance meetings, audit programme, compliance calendar, competency assessments, supervisions, provider oversight, mock inspections, continuous quality improvement, mandatory e-learning and face-to-face competency training (w/c 6 July 2026). | H8: Registered Manager | I8: High | J8: 46201 | K8: 46215 | M8: In Progress | N8: =IF(M8="Verified","Green",IF(M8="Completed","Amber - Awaiting Verification",IF(K8<TODAY(),"Red - Overdue",IF(M8="In Progress","Amber","Red - Not Started")))) -> Amber | O8: See Row 2 implemented and continue to be embedded across the service. The home currently has no residents, allowing governance systems, documentation, environmental improvements and workforce development to be fully established prior to future admissions. Mandatory e-learning is monitored through the Training Matrix. Face-to-face training (w/c 6 July 2026) covers Care Planning, Care Notes, Professional Observations, Oral Care, MCA, DoLS, Dementia, Safeguarding, Personal Care, Duty of Candour, Mental Health, Trauma-informed Care, Behaviour Support, Risk Assessment and professional terminology. Fire alarm upgrade to Category L1 and fire door replacement are in progress. Weekly/monthly fire compliance checks will recommence once works are completed and commissioned. PEEPs and dependency reviews will commence upon admission of residents. Compliance monitored via governance, audits and provider oversight. | P8: Updated care plan, review sheet, family/professional involvement record Governance Workbook; Master Action Plan; Audit Workbook 1; Audit Workbook 2; Compliance Calendar; Fire & Compliance Workbook; Cleaning Workbook; Dependency Tool & PEEPs; Handover & Allocation Workbook; Training Matrix; Personnel Files; Resident Admission Pack; Funding Pack; New Resident Tracker; Agency Induction; Agency Competency; Face-to-face Training Records (w/c 6 July 2026); Competency Assessments; Supervisions; Professional Discussions; Mock Inspections; Fire Alarm Upgrade; Fire Door Replacement. | Q8: GW; MAP; AW1; AW2; CC; FCW; CS; DT; HAW; TM; PF; RAP; FP; NRT | R8: No | U8: NoP Reg 9
A9: A008 | B9: Reg 9 | C9: Responsive | D9: Care plan updates are not consistently shared with staff via handover/allocation | E9: Care planning system did not evidence individualised assessment and review | F9: Review and rewrite affected care plans with specific resident guidance Immediate review completed. Governance systems strengthened, audits implemented, leadership oversight increased, policies reviewed, environmental improvements commenced, staff training programme implemented and risks escalated where required. | G9: Monthly person-centred care plan audit and resident/family review cycle Embed improvements through monthly governance meetings, audit programme, compliance calendar, competency assessments, supervisions, provider oversight, mock inspections, continuous quality improvement, mandatory e-learning and face-to-face competency training (w/c 6 July 2026). | H9: Registered Manager | I9: High | J9: 46201 | K9: 46215 | M9: In Progress | N9: =IF(M9="Verified","Green",IF(M9="Completed","Amber - Awaiting Verification",IF(K9<TODAY(),"Red - Overdue",IF(M9="In Progress","Amber","Red - Not Started")))) -> Amber | O9: Created a new handover/allocation sheet. All in one document for staff. Created an audit which takes all aspects into consideration. Importance in family involvement and recording this is key. Handover/Allocation 2026 Evidence implemented and continue to be embedded across the service. The home currently has no residents, allowing governance systems, documentation, environmental improvements and workforce development to be fully established prior to future admissions. Mandatory e-learning is monitored through the Training Matrix. Face-to-face training (w/c 6 July 2026) covers Care Planning, Care Notes, Professional Observations, Oral Care, MCA, DoLS, Dementia, Safeguarding, Personal Care, Duty of Candour, Mental Health, Trauma-informed Care, Behaviour Support, Risk Assessment and professional terminology. Fire alarm upgrade to Category L1 and fire door replacement are in progress. Weekly/monthly fire compliance checks will recommence once works are completed and commissioned. PEEPs and dependency reviews will commence upon admission of residents. Compliance monitored via governance, audits and provider oversight. | P9: Updated care plan, review sheet, family/professional involvement record Governance Workbook; Master Action Plan; Audit Workbook 1; Audit Workbook 2; Compliance Calendar; Fire & Compliance Workbook; Cleaning Workbook; Dependency Tool & PEEPs; Handover & Allocation Workbook; Training Matrix; Personnel Files; Resident Admission Pack; Funding Pack; New Resident Tracker; Agency Induction; Agency Competency; Face-to-face Training Records (w/c 6 July 2026); Competency Assessments; Supervisions; Professional Discussions; Mock Inspections; Fire Alarm Upgrade; Fire Door Replacement. | Q9: GW; MAP; AW1; AW2; CC; FCW; CS; DT; HAW; TM; PF; RAP; FP; NRT | R9: No | U9: NoP Reg 9
A10: A009 | B10: Reg 9 | C10: Responsive | D10: Resident/family signatures or consultation records are missing | E10: Care planning system did not evidence individualised assessment and review | F10: Review and rewrite affected care plans with specific resident guidance Immediate review completed. Governance systems strengthened, audits implemented, leadership oversight increased, policies reviewed, environmental improvements commenced, staff training programme implemented and risks escalated where required. | G10: Monthly person-centred care plan audit and resident/family review cycle Embed improvements through monthly governance meetings, audit programme, compliance calendar, competency assessments, supervisions, provider oversight, mock inspections, continuous quality improvement, mandatory e-learning and face-to-face competency training (w/c 6 July 2026). | H10: Registered Manager | I10: High | J10: 46201 | K10: 46215 | M10: In Progress | N10: =IF(M10="Verified","Green",IF(M10="Completed","Amber - Awaiting Verification",IF(K10<TODAY(),"Red - Overdue",IF(M10="In Progress","Amber","Red - Not Started")))) -> Amber | O10: Created a new handover/allocation sheet. All in one document for staff. See Row 2 Created an audit which takes all aspects into consideration. Importance in family involvement and recording this is key. implemented and continue to be embedded across the service. The home currently has no residents, allowing governance systems, documentation, environmental improvements and workforce development to be fully established prior to future admissions. Mandatory e-learning is monitored through the Training Matrix. Face-to-face training (w/c 6 July 2026) covers Care Planning, Care Notes, Professional Observations, Oral Care, MCA, DoLS, Dementia, Safeguarding, Personal Care, Duty of Candour, Mental Health, Trauma-informed Care, Behaviour Support, Risk Assessment and professional terminology. Fire alarm upgrade to Category L1 and fire door replacement are in progress. Weekly/monthly fire compliance checks will recommence once works are completed and commissioned. PEEPs and dependency reviews will commence upon admission of residents. Compliance monitored via governance, audits and provider oversight. | P10: Updated care plan, review sheet, family/professional involvement record Governance Workbook; Master Action Plan; Audit Workbook 1; Audit Workbook 2; Compliance Calendar; Fire & Compliance Workbook; Cleaning Workbook; Dependency Tool & PEEPs; Handover & Allocation Workbook; Training Matrix; Personnel Files; Resident Admission Pack; Funding Pack; New Resident Tracker; Agency Induction; Agency Competency; Face-to-face Training Records (w/c 6 July 2026); Competency Assessments; Supervisions; Professional Discussions; Mock Inspections; Fire Alarm Upgrade; Fire Door Replacement. | Q10: GW; MAP; AW1; AW2; CC; FCW; CS; DT; HAW; TM; PF; RAP; FP; NRT | R10: No | U10: NoP Reg 9
A11: A010 | B11: Reg 9 | C11: Responsive | D11: Professional advice is not always embedded into the care plan | E11: Care planning system did not evidence individualised assessment and review | F11: Review and rewrite affected care plans with specific resident guidance Immediate review completed. Governance systems strengthened, audits implemented, leadership oversight increased, policies reviewed, environmental improvements commenced, staff training programme implemented and risks escalated where required. | G11: Monthly person-centred care plan audit and resident/family review cycle Embed improvements through monthly governance meetings, audit programme, compliance calendar, competency assessments, supervisions, provider oversight, mock inspections, continuous quality improvement, mandatory e-learning and face-to-face competency training (w/c 6 July 2026). | H11: Registered Manager | I11: High | J11: 46201 | K11: 46215 | M11: In Progress | N11: =IF(M11="Verified","Green",IF(M11="Completed","Amber - Awaiting Verification",IF(K11<TODAY(),"Red - Overdue",IF(M11="In Progress","Amber","Red - Not Started")))) -> Amber | O11: See Row 2 - Professional advise not embed in care plan. implemented and continue to be embedded across the service. The home currently has no residents, allowing governance systems, documentation, environmental improvements and workforce development to be fully established prior to future admissions. Mandatory e-learning is monitored through the Training Matrix. Face-to-face training (w/c 6 July 2026) covers Care Planning, Care Notes, Professional Observations, Oral Care, MCA, DoLS, Dementia, Safeguarding, Personal Care, Duty of Candour, Mental Health, Trauma-informed Care, Behaviour Support, Risk Assessment and professional terminology. Fire alarm upgrade to Category L1 and fire door replacement are in progress. Weekly/monthly fire compliance checks will recommence once works are completed and commissioned. PEEPs and dependency reviews will commence upon admission of residents. Compliance monitored via governance, audits and provider oversight. | P11: Updated care plan, review sheet, family/professional involvement record Governance Workbook; Master Action Plan; Audit Workbook 1; Audit Workbook 2; Compliance Calendar; Fire & Compliance Workbook; Cleaning Workbook; Dependency Tool & PEEPs; Handover & Allocation Workbook; Training Matrix; Personnel Files; Resident Admission Pack; Funding Pack; New Resident Tracker; Agency Induction; Agency Competency; Face-to-face Training Records (w/c 6 July 2026); Competency Assessments; Supervisions; Professional Discussions; Mock Inspections; Fire Alarm Upgrade; Fire Door Replacement. | Q11: GW; MAP; AW1; AW2; CC; FCW; CS; DT; HAW; TM; PF; RAP; FP; NRT | R11: No | U11: NoP Reg 9
A12: A011 | B12: Reg 10 | C12: Caring | D12: Undignified or judgemental language used in records | E12: Recording and practice culture did not consistently embed dignity standards | F12: Remove undignified wording and complete staff briefing Immediate review completed. Governance systems strengthened, audits implemented, leadership oversight increased, policies reviewed, environmental improvements commenced, staff training programme implemented and risks escalated where required. | G12: Monthly dignity audit, spot checks and reflective learning Embed improvements through monthly governance meetings, audit programme, compliance calendar, competency assessments, supervisions, provider oversight, mock inspections, continuous quality improvement, mandatory e-learning and face-to-face competency training (w/c 6 July 2026). | H12: Registered Manager | I12: High | J12: 46201 | K12: 46215 | M12: In Progress | N12: =IF(M12="Verified","Green",IF(M12="Completed","Amber - Awaiting Verification",IF(K12<TODAY(),"Red - Overdue",IF(M12="In Progress","Amber","Red - Not Started")))) -> Amber | O12: Row 2 implemented and continue to be embedded across the service. The home currently has no residents, allowing governance systems, documentation, environmental improvements and workforce development to be fully established prior to future admissions. Mandatory e-learning is monitored through the Training Matrix. Face-to-face training (w/c 6 July 2026) covers Care Planning, Care Notes, Professional Observations, Oral Care, MCA, DoLS, Dementia, Safeguarding, Personal Care, Duty of Candour, Mental Health, Trauma-informed Care, Behaviour Support, Risk Assessment and professional terminology. Fire alarm upgrade to Category L1 and fire door replacement are in progress. Weekly/monthly fire compliance checks will recommence once works are completed and commissioned. PEEPs and dependency reviews will commence upon admission of residents. Compliance monitored via governance, audits and provider oversight. | P12: Dignity audit, revised records, staff briefing, observation record Governance Workbook; Master Action Plan; Audit Workbook 1; Audit Workbook 2; Compliance Calendar; Fire & Compliance Workbook; Cleaning Workbook; Dependency Tool & PEEPs; Handover & Allocation Workbook; Training Matrix; Personnel Files; Resident Admission Pack; Funding Pack; New Resident Tracker; Agency Induction; Agency Competency; Face-to-face Training Records (w/c 6 July 2026); Competency Assessments; Supervisions; Professional Discussions; Mock Inspections; Fire Alarm Upgrade; Fire Door Replacement. | Q12: GW; MAP; AW1; AW2; CC; FCW; CS; DT; HAW; TM; PF; RAP; FP; NRT | R12: No | U12: NoP Reg 10
A13: A012 | B13: Reg 10 | C13: Caring | D13: Continence care discussed in shared spaces | E13: Recording and practice culture did not consistently embed dignity standards | F13: Remove undignified wording and complete staff briefing Immediate review completed. Governance systems strengthened, audits implemented, leadership oversight increased, policies reviewed, environmental improvements commenced, staff training programme implemented and risks escalated where required. | G13: Monthly dignity audit, spot checks and reflective learning Embed improvements through monthly governance meetings, audit programme, compliance calendar, competency assessments, supervisions, provider oversight, mock inspections, continuous quality improvement, mandatory e-learning and face-to-face competency training (w/c 6 July 2026). | H13: Registered Manager | I13: High | J13: 46201 | K13: 46215 | M13: In Progress | N13: =IF(M13="Verified","Green",IF(M13="Completed","Amber - Awaiting Verification",IF(K13<TODAY(),"Red - Overdue",IF(M13="In Progress","Amber","Red - Not Started")))) -> Amber | O13: Row 2 implemented and continue to be embedded across the service. The home currently has no residents, allowing governance systems, documentation, environmental improvements and workforce development to be fully established prior to future admissions. Mandatory e-learning is monitored through the Training Matrix. Face-to-face training (w/c 6 July 2026) covers Care Planning, Care Notes, Professional Observations, Oral Care, MCA, DoLS, Dementia, Safeguarding, Personal Care, Duty of Candour, Mental Health, Trauma-informed Care, Behaviour Support, Risk Assessment and professional terminology. Fire alarm upgrade to Category L1 and fire door replacement are in progress. Weekly/monthly fire compliance checks will recommence once works are completed and commissioned. PEEPs and dependency reviews will commence upon admission of residents. Compliance monitored via governance, audits and provider oversight. | P13: Dignity audit, revised records, staff briefing, observation record Governance Workbook; Master Action Plan; Audit Workbook 1; Audit Workbook 2; Compliance Calendar; Fire & Compliance Workbook; Cleaning Workbook; Dependency Tool & PEEPs; Handover & Allocation Workbook; Training Matrix; Personnel Files; Resident Admission Pack; Funding Pack; New Resident Tracker; Agency Induction; Agency Competency; Face-to-face Training Records (w/c 6 July 2026); Competency Assessments; Supervisions; Professional Discussions; Mock Inspections; Fire Alarm Upgrade; Fire Door Replacement. | Q13: GW; MAP; AW1; AW2; CC; FCW; CS; DT; HAW; TM; PF; RAP; FP; NRT | R13: No | U13: NoP Reg 10
A14: A013 | B14: Reg 10 | C14: Caring | D14: Infantilising continence items visible to visitors | E14: Recording and practice culture did not consistently embed dignity standards | F14: Remove undignified wording and complete staff briefing Immediate review completed. Governance systems strengthened, audits implemented, leadership oversight increased, policies reviewed, environmental improvements commenced, staff training programme implemented and risks escalated where required. | G14: Monthly dignity audit, spot checks and reflective learning Embed improvements through monthly governance meetings, audit programme, compliance calendar, competency assessments, supervisions, provider oversight, mock inspections, continuous quality improvement, mandatory e-learning and face-to-face competency training (w/c 6 July 2026). | H14: Registered Manager | I14: High | J14: 46201 | K14: 46215 | M14: In Progress | N14: =IF(M14="Verified","Green",IF(M14="Completed","Amber - Awaiting Verification",IF(K14<TODAY(),"Red - Overdue",IF(M14="In Progress","Amber","Red - Not Started")))) -> Amber | O14: Row 2 implemented and continue to be embedded across the service. The home currently has no residents, allowing governance systems, documentation, environmental improvements and workforce development to be fully established prior to future admissions. Mandatory e-learning is monitored through the Training Matrix. Face-to-face training (w/c 6 July 2026) covers Care Planning, Care Notes, Professional Observations, Oral Care, MCA, DoLS, Dementia, Safeguarding, Personal Care, Duty of Candour, Mental Health, Trauma-informed Care, Behaviour Support, Risk Assessment and professional terminology. Fire alarm upgrade to Category L1 and fire door replacement are in progress. Weekly/monthly fire compliance checks will recommence once works are completed and commissioned. PEEPs and dependency reviews will commence upon admission of residents. Compliance monitored via governance, audits and provider oversight. | P14: Dignity audit, revised records, staff briefing, observation record Governance Workbook; Master Action Plan; Audit Workbook 1; Audit Workbook 2; Compliance Calendar; Fire & Compliance Workbook; Cleaning Workbook; Dependency Tool & PEEPs; Handover & Allocation Workbook; Training Matrix; Personnel Files; Resident Admission Pack; Funding Pack; New Resident Tracker; Agency Induction; Agency Competency; Face-to-face Training Records (w/c 6 July 2026); Competency Assessments; Supervisions; Professional Discussions; Mock Inspections; Fire Alarm Upgrade; Fire Door Replacement. | Q14: GW; MAP; AW1; AW2; CC; FCW; CS; DT; HAW; TM; PF; RAP; FP; NRT | R14: No | U14: NoP Reg 10
A15: A014 | B15: Reg 10 | C15: Caring | D15: Staff require dignity and respectful communication refresher | E15: Recording and practice culture did not consistently embed dignity standards | F15: Remove undignified wording and complete staff briefing Immediate review completed. Governance systems strengthened, audits implemented, leadership oversight increased, policies reviewed, environmental improvements commenced, staff training programme implemented and risks escalated where required. | G15: Monthly dignity audit, spot checks and reflective learning Embed improvements through monthly governance meetings, audit programme, compliance calendar, competency assessments, supervisions, provider oversight, mock inspections, continuous quality improvement, mandatory e-learning and face-to-face competency training (w/c 6 July 2026). | H15: Registered Manager | I15: High | J15: 46201 | K15: 46215 | M15: In Progress | N15: =IF(M15="Verified","Green",IF(M15="Completed","Amber - Awaiting Verification",IF(K15<TODAY(),"Red - Overdue",IF(M15="In Progress","Amber","Red - Not Started")))) -> Amber | O15: Row 2 implemented and continue to be embedded across the service. The home currently has no residents, allowing governance systems, documentation, environmental improvements and workforce development to be fully established prior to future admissions. Mandatory e-learning is monitored through the Training Matrix. Face-to-face training (w/c 6 July 2026) covers Care Planning, Care Notes, Professional Observations, Oral Care, MCA, DoLS, Dementia, Safeguarding, Personal Care, Duty of Candour, Mental Health, Trauma-informed Care, Behaviour Support, Risk Assessment and professional terminology. Fire alarm upgrade to Category L1 and fire door replacement are in progress. Weekly/monthly fire compliance checks will recommence once works are completed and commissioned. PEEPs and dependency reviews will commence upon admission of residents. Compliance monitored via governance, audits and provider oversight. | P15: Dignity audit, revised records, staff briefing, observation record Governance Workbook; Master Action Plan; Audit Workbook 1; Audit Workbook 2; Compliance Calendar; Fire & Compliance Workbook; Cleaning Workbook; Dependency Tool & PEEPs; Handover & Allocation Workbook; Training Matrix; Personnel Files; Resident Admission Pack; Funding Pack; New Resident Tracker; Agency Induction; Agency Competency; Face-to-face Training Records (w/c 6 July 2026); Competency Assessments; Supervisions; Professional Discussions; Mock Inspections; Fire Alarm Upgrade; Fire Door Replacement. | Q15: GW; MAP; AW1; AW2; CC; FCW; CS; DT; HAW; TM; PF; RAP; FP; NRT | R15: No | U15: NoP Reg 10
A16: A015 | B16: Reg 10 | C16: Caring | D16: Leadership observations did not consistently identify poor dignity practice | E16: Recording and practice culture did not consistently embed dignity standards | F16: Remove undignified wording and complete staff briefing Immediate review completed. Governance systems strengthened, audits implemented, leadership oversight increased, policies reviewed, environmental improvements commenced, staff training programme implemented and risks escalated where required. | G16: Monthly dignity audit, spot checks and reflective learning Embed improvements through monthly governance meetings, audit programme, compliance calendar, competency assessments, supervisions, provider oversight, mock inspections, continuous quality improvement, mandatory e-learning and face-to-face competency training (w/c 6 July 2026). | H16: Registered Manager | I16: High | J16: 46201 | K16: 46215 | M16: In Progress | N16: =IF(M16="Verified","Green",IF(M16="Completed","Amber - Awaiting Verification",IF(K16<TODAY(),"Red - Overdue",IF(M16="In Progress","Amber","Red - Not Started")))) -> Amber | O16: Row 2 implemented and continue to be embedded across the service. The home currently has no residents, allowing governance systems, documentation, environmental improvements and workforce development to be fully established prior to future admissions. Mandatory e-learning is monitored through the Training Matrix. Face-to-face training (w/c 6 July 2026) covers Care Planning, Care Notes, Professional Observations, Oral Care, MCA, DoLS, Dementia, Safeguarding, Personal Care, Duty of Candour, Mental Health, Trauma-informed Care, Behaviour Support, Risk Assessment and professional terminology. Fire alarm upgrade to Category L1 and fire door replacement are in progress. Weekly/monthly fire compliance checks will recommence once works are completed and commissioned. PEEPs and dependency reviews will commence upon admission of residents. Compliance monitored via governance, audits and provider oversight. | P16: Dignity audit, revised records, staff briefing, observation record Governance Workbook; Master Action Plan; Audit Workbook 1; Audit Workbook 2; Compliance Calendar; Fire & Compliance Workbook; Cleaning Workbook; Dependency Tool & PEEPs; Handover & Allocation Workbook; Training Matrix; Personnel Files; Resident Admission Pack; Funding Pack; New Resident Tracker; Agency Induction; Agency Competency; Face-to-face Training Records (w/c 6 July 2026); Competency Assessments; Supervisions; Professional Discussions; Mock Inspections; Fire Alarm Upgrade; Fire Door Replacement. | Q16: GW; MAP; AW1; AW2; CC; FCW; CS; DT; HAW; TM; PF; RAP; FP; NRT | R16: No | U16: NoP Reg 10
A17: A016 | B17: Reg 10 | C17: Caring | D17: Care records refer to behaviours without explaining unmet need or distress | E17: Recording and practice culture did not consistently embed dignity standards | F17: Remove undignified wording and complete staff briefing Immediate review completed. Governance systems strengthened, audits implemented, leadership oversight increased, policies reviewed, environmental improvements commenced, staff training programme implemented and risks escalated where required. | G17: Monthly dignity audit, spot checks and reflective learning Embed improvements through monthly governance meetings, audit programme, compliance calendar, competency assessments, supervisions, provider oversight, mock inspections, continuous quality improvement, mandatory e-learning and face-to-face competency training (w/c 6 July 2026). | H17: Registered Manager | I17: High | J17: 46201 | K17: 46215 | M17: In Progress | N17: =IF(M17="Verified","Green",IF(M17="Completed","Amber - Awaiting Verification",IF(K17<TODAY(),"Red - Overdue",IF(M17="In Progress","Amber","Red - Not Started")))) -> Amber | O17: Row 2 implemented and continue to be embedded across the service. The home currently has no residents, allowing governance systems, documentation, environmental improvements and workforce development to be fully established prior to future admissions. Mandatory e-learning is monitored through the Training Matrix. Face-to-face training (w/c 6 July 2026) covers Care Planning, Care Notes, Professional Observations, Oral Care, MCA, DoLS, Dementia, Safeguarding, Personal Care, Duty of Candour, Mental Health, Trauma-informed Care, Behaviour Support, Risk Assessment and professional terminology. Fire alarm upgrade to Category L1 and fire door replacement are in progress. Weekly/monthly fire compliance checks will recommence once works are completed and commissioned. PEEPs and dependency reviews will commence upon admission of residents. Compliance monitored via governance, audits and provider oversight. | P17: Dignity audit, revised records, staff briefing, observation record Governance Workbook; Master Action Plan; Audit Workbook 1; Audit Workbook 2; Compliance Calendar; Fire & Compliance Workbook; Cleaning Workbook; Dependency Tool & PEEPs; Handover & Allocation Workbook; Training Matrix; Personnel Files; Resident Admission Pack; Funding Pack; New Resident Tracker; Agency Induction; Agency Competency; Face-to-face Training Records (w/c 6 July 2026); Competency Assessments; Supervisions; Professional Discussions; Mock Inspections; Fire Alarm Upgrade; Fire Door Replacement. | Q17: GW; MAP; AW1; AW2; CC; FCW; CS; DT; HAW; TM; PF; RAP; FP; NRT | R17: No | U17: NoP Reg 10
... A97: A096 | B97: Reg 19 | C97: Well-led | D97: New starter induction checklist required for every staff member | E97: Safer recruitment controls not evidenced consistently in one central register | F97: Audit all staff files and SCR immediately Immediate review completed. Governance systems strengthened, audits implemented, leadership oversight increased, policies reviewed, environmental improvements commenced, staff training programme implemented and risks escalated where required. | G97: Monthly SCR review and recruitment compliance audit Embed improvements through monthly governance meetings, audit programme, compliance calendar, competency assessments, supervisions, provider oversight, mock inspections, continuous quality improvement, mandatory e-learning and face-to-face competency training (w/c 6 July 2026). | H97: Administrator / Registered Manager | I97: High | J97: 46201 | K97: 46215 | M97: In Progress | N97: =IF(M97="Verified","Green",IF(M97="Completed","Amber - Awaiting Verification",IF(K97<TODAY(),"Red - Overdue",IF(M97="In Progress","Amber","Red - Not Started")))) -> Amber | O97: implemented and continue to be embedded across the service. The home currently has no residents, allowing governance systems, documentation, environmental improvements and workforce development to be fully established prior to future admissions. Mandatory e-learning is monitored through the Training Matrix. Face-to-face training (w/c 6 July 2026) covers Care Planning, Care Notes, Professional Observations, Oral Care, MCA, DoLS, Dementia, Safeguarding, Personal Care, Duty of Candour, Mental Health, Trauma-informed Care, Behaviour Support, Risk Assessment and professional terminology. Fire alarm upgrade to Category L1 and fire door replacement are in progress. Weekly/monthly fire compliance checks will recommence once works are completed and commissioned. PEEPs and dependency reviews will commence upon admission of residents. Compliance monitored via governance, audits and provider oversight. | P97: SCR, staff file audit, DBS, references, right to work, induction Governance Workbook; Master Action Plan; Audit Workbook 1; Audit Workbook 2; Compliance Calendar; Fire & Compliance Workbook; Cleaning Workbook; Dependency Tool & PEEPs; Handover & Allocation Workbook; Training Matrix; Personnel Files; Resident Admission Pack; Funding Pack; New Resident Tracker; Agency Induction; Agency Competency; Face-to-face Training Records (w/c 6 July 2026); Competency Assessments; Supervisions; Professional Discussions; Mock Inspections; Fire Alarm Upgrade; Fire Door Replacement. | Q97: GW; MAP; AW1; AW2; CC; FCW; CS; DT; HAW; TM; PF; RAP; FP; NRT | R97: No | U97: Action Plan Reg 19
A113: A097 | B113: Reg 17 | C113: Well-led | D113: Sustained improvement programme required following CQC/Essex concerns that improvements were not embedded or sustained | E113: Previous actions were not consistently embedded into daily practice or evidenced over time | F113: Create a sustained improvement programme with weekly checks and management oversight Immediate review completed. Governance systems strengthened, audits implemented, leadership oversight increased, policies reviewed, environmental improvements commenced, staff training programme implemented and risks escalated where required. | G113: Maintain 3, 6 and 12 month sustainability reviews with provider sign-off and evidence checks Embed improvements through monthly governance meetings, audit programme, compliance calendar, competency assessments, supervisions, provider oversight, mock inspections, continuous quality improvement, mandatory e-learning and face-to-face competency training (w/c 6 July 2026). | H113: Provider / Registered Manager | I113: Critical | J113: 46201 | K113: 46218 | M113: Not Started | N113: Red - Not Started | O113: Improvements have been implemented and continue to be embedded across the service. The home currently has no residents, allowing governance systems, documentation, environmental improvements and workforce development to be fully established prior to future admissions. Mandatory e-learning is monitored through the Training Matrix. Face-to-face training (w/c 6 July 2026) covers Care Planning, Care Notes, Professional Observations, Oral Care, MCA, DoLS, Dementia, Safeguarding, Personal Care, Duty of Candour, Mental Health, Trauma-informed Care, Behaviour Support, Risk Assessment and professional terminology. Fire alarm upgrade to Category L1 and fire door replacement are in progress. Weekly/monthly fire compliance checks will recommence once works are completed and commissioned. PEEPs and dependency reviews will commence upon admission of residents. Compliance monitored via governance, audits and provider oversight. | P113: Sustained improvement plan, weekly review minutes, completed checks, provider sign-off Governance Workbook; Master Action Plan; Audit Workbook 1; Audit Workbook 2; Compliance Calendar; Fire & Compliance Workbook; Cleaning Workbook; Dependency Tool & PEEPs; Handover & Allocation Workbook; Training Matrix; Personnel Files; Resident Admission Pack; Funding Pack; New Resident Tracker; Agency Induction; Agency Competency; Face-to-face Training Records (w/c 6 July 2026); Competency Assessments; Supervisions; Professional Discussions; Mock Inspections; Fire Alarm Upgrade; Fire Door Replacement. | Q113: GW; MAP; AW1; AW2; CC; FCW; CS; DT; HAW; TM; PF; RAP; FP; NRT | R113: No | U113: CQC Draft / NoP / Essex Letter
A114: A098 | B114: Reg 17 | C114: Well-led | D114: Formal partnership working with commissioners, safeguarding, fire service, GP, district nurses and MDT must be evidenced | E114: Partnership working and professional escalation were not consistently evidenced | F114: Create external professionals and commissioner communication tracker Immediate review completed. Governance systems strengthened, audits implemented, leadership oversight increased, policies reviewed, environmental improvements commenced, staff training programme implemented and risks escalated where required. | G114: Monthly MDT/commissioner engagement review with actions followed up to completion Embed improvements through monthly governance meetings, audit programme, compliance calendar, competency assessments, supervisions, provider oversight, mock inspections, continuous quality improvement, mandatory e-learning and face-to-face competency training (w/c 6 July 2026). | H114: Registered Manager | I114: High | J114: 46201 | K114: 46218 | M114: Not Started | N114: Red - Not Started | O114: Improvements have been implemented and continue to be embedded across the service. The home currently has no residents, allowing governance systems, documentation, environmental improvements and workforce development to be fully established prior to future admissions. Mandatory e-learning is monitored through the Training Matrix. Face-to-face training (w/c 6 July 2026) covers Care Planning, Care Notes, Professional Observations, Oral Care, MCA, DoLS, Dementia, Safeguarding, Personal Care, Duty of Candour, Mental Health, Trauma-informed Care, Behaviour Support, Risk Assessment and professional terminology. Fire alarm upgrade to Category L1 and fire door replacement are in progress. Weekly/monthly fire compliance checks will recommence once works are completed and commissioned. PEEPs and dependency reviews will commence upon admission of residents. Compliance monitored via governance, audits and provider oversight. | P114: External professional tracker, meeting notes, emails, referrals, follow-up actions Governance Workbook; Master Action Plan; Audit Workbook 1; Audit Workbook 2; Compliance Calendar; Fire & Compliance Workbook; Cleaning Workbook; Dependency Tool & PEEPs; Handover & Allocation Workbook; Training Matrix; Personnel Files; Resident Admission Pack; Funding Pack; New Resident Tracker; Agency Induction; Agency Competency; Face-to-face Training Records (w/c 6 July 2026); Competency Assessments; Supervisions; Professional Discussions; Mock Inspections; Fire Alarm Upgrade; Fire Door Replacement. | Q114: GW; MAP; AW1; AW2; CC; FCW; CS; DT; HAW; TM; PF; RAP; FP; NRT | R114: No | U114: Essex Letter / CQC Draft
A115: A099 | B115: Reg 17 | C115: Well-led | D115: Financial sustainability and business continuity assurance required | E115: Essex raised financial viability as part of wider unmanaged risk | F115: Prepare business continuity and financial sustainability assurance statement Immediate review completed. Governance systems strengthened, audits implemented, leadership oversight increased, policies reviewed, environmental improvements commenced, staff training programme implemented and risks escalated where required. | G115: Monthly provider review of staffing costs, occupancy risks, essential supplier payments and contingency plan Embed improvements through monthly governance meetings, audit programme, compliance calendar, competency assessments, supervisions, provider oversight, mock inspections, continuous quality improvement, mandatory e-learning and face-to-face competency training (w/c 6 July 2026). | H115: Provider / Nominated Individual | I115: High | J115: 46201 | K115: 46218 | M115: Not Started | N115: Red - Not Started | O115: Improvements have been implemented and continue to be embedded across the service. The home currently has no residents, allowing governance systems, documentation, environmental improvements and workforce development to be fully established prior to future admissions. Mandatory e-learning is monitored through the Training Matrix. Face-to-face training (w/c 6 July 2026) covers Care Planning, Care Notes, Professional Observations, Oral Care, MCA, DoLS, Dementia, Safeguarding, Personal Care, Duty of Candour, Mental Health, Trauma-informed Care, Behaviour Support, Risk Assessment and professional terminology. Fire alarm upgrade to Category L1 and fire door replacement are in progress. Weekly/monthly fire compliance checks will recommence once works are completed and commissioned. PEEPs and dependency reviews will commence upon admission of residents. Compliance monitored via governance, audits and provider oversight. | P115: Financial sustainability statement, contingency plan, provider review minutes Governance Workbook; Master Action Plan; Audit Workbook 1; Audit Workbook 2; Compliance Calendar; Fire & Compliance Workbook; Cleaning Workbook; Dependency Tool & PEEPs; Handover & Allocation Workbook; Training Matrix; Personnel Files; Resident Admission Pack; Funding Pack; New Resident Tracker; Agency Induction; Agency Competency; Face-to-face Training Records (w/c 6 July 2026); Competency Assessments; Supervisions; Professional Discussions; Mock Inspections; Fire Alarm Upgrade; Fire Door Replacement. | Q115: GW; MAP; AW1; AW2; CC; FCW; CS; DT; HAW; TM; PF; RAP; FP; NRT | R115: No | U115: Essex Letter
A116: A100 | B116: Reg 12 | C116: Safe | D116: Resident transition and transfer planning must be fully evidenced for any move between services | E116: CQC and Essex raised concerns about safe systems, pathways and transitions | F116: Create transfer checklist and resident transition plan for every move Immediate review completed. Governance systems strengthened, audits implemented, leadership oversight increased, policies reviewed, environmental improvements commenced, staff training programme implemented and risks escalated where required. | G116: Audit all hospital/admission/discharge/placement transfer records monthly Embed improvements through monthly governance meetings, audit programme, compliance calendar, competency assessments, supervisions, provider oversight, mock inspections, continuous quality improvement, mandatory e-learning and face-to-face competency training (w/c 6 July 2026). | H116: Registered Manager | I116: Critical | J116: 46201 | K116: 46218 | M116: Not Started | N116: Red - Not Started | O116: Improvements have been implemented and continue to be embedded across the service. The home currently has no residents, allowing governance systems, documentation, environmental improvements and workforce development to be fully established prior to future admissions. Mandatory e-learning is monitored through the Training Matrix. Face-to-face training (w/c 6 July 2026) covers Care Planning, Care Notes, Professional Observations, Oral Care, MCA, DoLS, Dementia, Safeguarding, Personal Care, Duty of Candour, Mental Health, Trauma-informed Care, Behaviour Support, Risk Assessment and professional terminology. Fire alarm upgrade to Category L1 and fire door replacement are in progress. Weekly/monthly fire compliance checks will recommence once works are completed and commissioned. PEEPs and dependency reviews will commence upon admission of residents. Compliance monitored via governance, audits and provider oversight. | P116: Transfer checklist, care summary, risk summary, medication list, family/professional communication Governance Workbook; Master Action Plan; Audit Workbook 1; Audit Workbook 2; Compliance Calendar; Fire & Compliance Workbook; Cleaning Workbook; Dependency Tool & PEEPs; Handover & Allocation Workbook; Training Matrix; Personnel Files; Resident Admission Pack; Funding Pack; New Resident Tracker; Agency Induction; Agency Competency; Face-to-face Training Records (w/c 6 July 2026); Competency Assessments; Supervisions; Professional Discussions; Mock Inspections; Fire Alarm Upgrade; Fire Door Replacement. | Q116: GW; MAP; AW1; AW2; CC; FCW; CS; DT; HAW; TM; PF; RAP; FP; NRT | R116: No | U116: CQC Draft / Essex Letter
A117: A101 | B117: Reg 17 | C117: Well-led | D117: Evidence file required for every completed action before status is changed to completed | E117: Completed actions were not always supported by clear evidence | F117: Stop marking actions complete unless evidence is uploaded and referenced Immediate review completed. Governance systems strengthened, audits implemented, leadership oversight increased, policies reviewed, environmental improvements commenced, staff training programme implemented and risks escalated where required. | G117: Weekly evidence audit by manager and monthly verification by provider/consultant Embed improvements through monthly governance meetings, audit programme, compliance calendar, competency assessments, supervisions, provider oversight, mock inspections, continuous quality improvement, mandatory e-learning and face-to-face competency training (w/c 6 July 2026). | H117: Registered Manager / Compliance Lead | I117: Critical | J117: 46201 | K117: 46218 | M117: Not Started | N117: Red - Not Started | O117: Improvements have been implemented and continue to be embedded across the service. The home currently has no residents, allowing governance systems, documentation, environmental improvements and workforce development to be fully established prior to future admissions. Mandatory e-learning is monitored through the Training Matrix. Face-to-face training (w/c 6 July 2026) covers Care Planning, Care Notes, Professional Observations, Oral Care, MCA, DoLS, Dementia, Safeguarding, Personal Care, Duty of Candour, Mental Health, Trauma-informed Care, Behaviour Support, Risk Assessment and professional terminology. Fire alarm upgrade to Category L1 and fire door replacement are in progress. Weekly/monthly fire compliance checks will recommence once works are completed and commissioned. PEEPs and dependency reviews will commence upon admission of residents. Compliance monitored via governance, audits and provider oversight. | P117: Evidence index, document links, action sign-off, audit trail Governance Workbook; Master Action Plan; Audit Workbook 1; Audit Workbook 2; Compliance Calendar; Fire & Compliance Workbook; Cleaning Workbook; Dependency Tool & PEEPs; Handover & Allocation Workbook; Training Matrix; Personnel Files; Resident Admission Pack; Funding Pack; New Resident Tracker; Agency Induction; Agency Competency; Face-to-face Training Records (w/c 6 July 2026); Competency Assessments; Supervisions; Professional Discussions; Mock Inspections; Fire Alarm Upgrade; Fire Door Replacement. | Q117: GW; MAP; AW1; AW2; CC; FCW; CS; DT; HAW; TM; PF; RAP; FP; NRT | R117: No | U117: NoP / Reg 17
A118: A102 | B118: Reg 17 | C118: Well-led | D118: Independent verification of completed actions required | E118: Provider checks did not demonstrate effective independent oversight | F118: Arrange independent review of completed high-risk actions Immediate review completed. Governance systems strengthened, audits implemented, leadership oversight increased, policies reviewed, environmental improvements commenced, staff training programme implemented and risks escalated where required. | G118: Monthly independent verification sample across care plans, MCA, fire, staffing, medicines and governance Embed improvements through monthly governance meetings, audit programme, compliance calendar, competency assessments, supervisions, provider oversight, mock inspections, continuous quality improvement, mandatory e-learning and face-to-face competency training (w/c 6 July 2026). | H118: External Consultant / Provider | I118: Critical | J118: 46201 | K118: 46218 | M118: Not Started | N118: Red - Not Started | O118: Improvements have been implemented and continue to be embedded across the service. The home currently has no residents, allowing governance systems, documentation, environmental improvements and workforce development to be fully established prior to future admissions. Mandatory e-learning is monitored through the Training Matrix. Face-to-face training (w/c 6 July 2026) covers Care Planning, Care Notes, Professional Observations, Oral Care, MCA, DoLS, Dementia, Safeguarding, Personal Care, Duty of Candour, Mental Health, Trauma-informed Care, Behaviour Support, Risk Assessment and professional terminology. Fire alarm upgrade to Category L1 and fire door replacement are in progress. Weekly/monthly fire compliance checks will recommence once works are completed and commissioned. PEEPs and dependency reviews will commence upon admission of residents. Compliance monitored via governance, audits and provider oversight. | P118: Independent verification report, sample audit, signed action verification Governance Workbook; Master Action Plan; Audit Workbook 1; Audit Workbook 2; Compliance Calendar; Fire & Compliance Workbook; Cleaning Workbook; Dependency Tool & PEEPs; Handover & Allocation Workbook; Training Matrix; Personnel Files; Resident Admission Pack; Funding Pack; New Resident Tracker; Agency Induction; Agency Competency; Face-to-face Training Records (w/c 6 July 2026); Competency Assessments; Supervisions; Professional Discussions; Mock Inspections; Fire Alarm Upgrade; Fire Door Replacement. | Q118: GW; MAP; AW1; AW2; CC; FCW; CS; DT; HAW; TM; PF; RAP; FP; NRT | R118: No | U118: NoP / CQC Draft
A119: A103 | B119: Reg 17 | C119: Well-led | D119: Monthly provider assurance review required with clear minutes, decisions and follow-up | E119: Provider oversight was found to be ineffective | F119: Schedule monthly provider assurance meeting Immediate review completed. Governance systems strengthened, audits implemented, leadership oversight increased, policies reviewed, environmental improvements commenced, staff training programme implemented and risks escalated where required. | G119: Standing agenda to review incidents, safeguarding, audits, staffing, complaints, fire, MCA and action plan progress Embed improvements through monthly governance meetings, audit programme, compliance calendar, competency assessments, supervisions, provider oversight, mock inspections, continuous quality improvement, mandatory e-learning and face-to-face competency training (w/c 6 July 2026). | H119: Provider / Registered Manager | I119: Critical | J119: 46201 | K119: 46218 | M119: Not Started | N119: Red - Not Started | O119: Direct governance improvement for Reg 17. Improvements have been implemented and continue to be embedded across the service. The home currently has no residents, allowing governance systems, documentation, environmental improvements and workforce development to be fully established prior to future admissions. Mandatory e-learning is monitored through the Training Matrix. Face-to-face training (w/c 6 July 2026) covers Care Planning, Care Notes, Professional Observations, Oral Care, MCA, DoLS, Dementia, Safeguarding, Personal Care, Duty of Candour, Mental Health, Trauma-informed Care, Behaviour Support, Risk Assessment and professional terminology. Fire alarm upgrade to Category L1 and fire door replacement are in progress. Weekly/monthly fire compliance checks will recommence once works are completed and commissioned. PEEPs and dependency reviews will commence upon admission of residents. Compliance monitored via governance, audits and provider oversight. | P119: Provider assurance minutes, agenda, action log, sign-off Governance Workbook; Master Action Plan; Audit Workbook 1; Audit Workbook 2; Compliance Calendar; Fire & Compliance Workbook; Cleaning Workbook; Dependency Tool & PEEPs; Handover & Allocation Workbook; Training Matrix; Personnel Files; Resident Admission Pack; Funding Pack; New Resident Tracker; Agency Induction; Agency Competency; Face-to-face Training Records (w/c 6 July 2026); Competency Assessments; Supervisions; Professional Discussions; Mock Inspections; Fire Alarm Upgrade; Fire Door Replacement. | Q119: GW; MAP; AW1; AW2; CC; FCW; CS; DT; HAW; TM; PF; RAP; FP; NRT | R119: No | U119: Reg 17 / CQC Draft
A120: A104 | B120: Reg 17 | C120: Well-led | D120: Governance trend dashboard required to identify patterns and repeated risks | E120: Incidents, safeguarding, falls, behaviours, complaints and audits were not analysed for patterns | F120: Create governance trend dashboard Immediate review completed. Governance systems strengthened, audits implemented, leadership oversight increased, policies reviewed, environmental improvements commenced, staff training programme implemented and risks escalated where required. | G120: Review trends monthly and evidence lessons learned and care plan changes Embed improvements through monthly governance meetings, audit programme, compliance calendar, competency assessments, supervisions, provider oversight, mock inspections, continuous quality improvement, mandatory e-learning and face-to-face competency training (w/c 6 July 2026). | H120: Registered Manager | I120: Critical | J120: 46201 | K120: 46218 | M120: Not Started | N120: Red - Not Started | O120: Addresses learning culture and repeated risk concerns. Improvements have been implemented and continue to be embedded across the service. The home currently has no residents, allowing governance systems, documentation, environmental improvements and workforce development to be fully established prior to future admissions. Mandatory e-learning is monitored through the Training Matrix. Face-to-face training (w/c 6 July 2026) covers Care Planning, Care Notes, Professional Observations, Oral Care, MCA, DoLS, Dementia, Safeguarding, Personal Care, Duty of Candour, Mental Health, Trauma-informed Care, Behaviour Support, Risk Assessment and professional terminology. Fire alarm upgrade to Category L1 and fire door replacement are in progress. Weekly/monthly fire compliance checks will recommence once works are completed and commissioned. PEEPs and dependency reviews will commence upon admission of residents. Compliance monitored via governance, audits and provider oversight. | P120: Trend dashboard, monthly analysis, lessons learned, updated care plans Governance Workbook; Master Action Plan; Audit Workbook 1; Audit Workbook 2; Compliance Calendar; Fire & Compliance Workbook; Cleaning Workbook; Dependency Tool & PEEPs; Handover & Allocation Workbook; Training Matrix; Personnel Files; Resident Admission Pack; Funding Pack; New Resident Tracker; Agency Induction; Agency Competency; Face-to-face Training Records (w/c 6 July 2026); Competency Assessments; Supervisions; Professional Discussions; Mock Inspections; Fire Alarm Upgrade; Fire Door Replacement. | Q120: GW; MAP; AW1; AW2; CC; FCW; CS; DT; HAW; TM; PF; RAP; FP; NRT | R120: No | U120: CQC Draft / NoP
A121: A105 | B121: Reg 13 | C121: Safe | D121: Monthly lessons learned meeting required for safeguarding, incidents, complaints, accidents and near misses | E121: Lessons learned were not embedded into care plans or staff practice | F121: Introduce monthly lessons learned meeting and staff briefing Immediate review completed. Governance systems strengthened, audits implemented, leadership oversight increased, policies reviewed, environmental improvements commenced, staff training programme implemented and risks escalated where required. | G121: Evidence changes to care plans, risk assessments, handover and supervision after each learning point Embed improvements through monthly governance meetings, audit programme, compliance calendar, competency assessments, supervisions, provider oversight, mock inspections, continuous quality improvement, mandatory e-learning and face-to-face competency training (w/c 6 July 2026). | H121: Registered Manager | I121: Critical | J121: 46201 | K121: 46218 | M121: Not Started | N121: Red - Not Started | O121: Specifically addresses safeguarding and learning culture. Improvements have been implemented and continue to be embedded across the service. The home currently has no residents, allowing governance systems, documentation, environmental improvements and workforce development to be fully established prior to future admissions. Mandatory e-learning is monitored through the Training Matrix. Face-to-face training (w/c 6 July 2026) covers Care Planning, Care Notes, Professional Observations, Oral Care, MCA, DoLS, Dementia, Safeguarding, Personal Care, Duty of Candour, Mental Health, Trauma-informed Care, Behaviour Support, Risk Assessment and professional terminology. Fire alarm upgrade to Category L1 and fire door replacement are in progress. Weekly/monthly fire compliance checks will recommence once works are completed and commissioned. PEEPs and dependency reviews will commence upon admission of residents. Compliance monitored via governance, audits and provider oversight. | P121: Meeting minutes, staff signatures, updated care plans, supervision notes Governance Workbook; Master Action Plan; Audit Workbook 1; Audit Workbook 2; Compliance Calendar; Fire & Compliance Workbook; Cleaning Workbook; Dependency Tool & PEEPs; Handover & Allocation Workbook; Training Matrix; Personnel Files; Resident Admission Pack; Funding Pack; New Resident Tracker; Agency Induction; Agency Competency; Face-to-face Training Records (w/c 6 July 2026); Competency Assessments; Supervisions; Professional Discussions; Mock Inspections; Fire Alarm Upgrade; Fire Door Replacement. | Q121: GW; MAP; AW1; AW2; CC; FCW; CS; DT; HAW; TM; PF; RAP; FP; NRT | R121: No | U121: Reg 13 / CQC Draft
A122: A106 | B122: Reg 17 | C122: Well-led | D122: Quality Improvement Register required to track improvements from audits through to completion and verification | E122: Audit actions were not consistently followed through or verified | F122: Create Quality Improvement Register linked to audit outcomes Immediate review completed. Governance systems strengthened, audits implemented, leadership oversight increased, policies reviewed, environmental improvements commenced, staff training programme implemented and risks escalated where required. | G122: Monthly review of open/overdue audit actions and evidence of completion Embed improvements through monthly governance meetings, audit programme, compliance calendar, competency assessments, supervisions, provider oversight, mock inspections, continuous quality improvement, mandatory e-learning and face-to-face competency training (w/c 6 July 2026). | H122: Registered Manager / Provider | I122: High | J122: 46201 | K122: 46218 | M122: Not Started | N122: Red - Not Started | O122: Strengthens audit-to-action governance. Improvements have been implemented and continue to be embedded across the service. The home currently has no residents, allowing governance systems, documentation, environmental improvements and workforce development to be fully established prior to future admissions. Mandatory e-learning is monitored through the Training Matrix. Face-to-face training (w/c 6 July 2026) covers Care Planning, Care Notes, Professional Observations, Oral Care, MCA, DoLS, Dementia, Safeguarding, Personal Care, Duty of Candour, Mental Health, Trauma-informed Care, Behaviour Support, Risk Assessment and professional terminology. Fire alarm upgrade to Category L1 and fire door replacement are in progress. Weekly/monthly fire compliance checks will recommence once works are completed and commissioned. PEEPs and dependency reviews will commence upon admission of residents. Compliance monitored via governance, audits and provider oversight. | P122: Quality improvement register, audit action logs, verification records Governance Workbook; Master Action Plan; Audit Workbook 1; Audit Workbook 2; Compliance Calendar; Fire & Compliance Workbook; Cleaning Workbook; Dependency Tool & PEEPs; Handover & Allocation Workbook; Training Matrix; Personnel Files; Resident Admission Pack; Funding Pack; New Resident Tracker; Agency Induction; Agency Competency; Face-to-face Training Records (w/c 6 July 2026); Competency Assessments; Supervisions; Professional Discussions; Mock Inspections; Fire Alarm Upgrade; Fire Door Replacement. | Q122: GW; MAP; AW1; AW2; CC; FCW; CS; DT; HAW; TM; PF; RAP; FP; NRT | R122: No | U122: Reg 17 / NoP
A123: A107 | B123: Reg 17 | C123: Well-led | D123: Quarterly mock CQC inspection required across all key questions | E123: Provider had not demonstrated robust monitoring against CQC standards | F123: Arrange first mock inspection and report Immediate review completed. Governance systems strengthened, audits implemented, leadership oversight increased, policies reviewed, environmental improvements commenced, staff training programme implemented and risks escalated where required. | G123: Quarterly mock inspection with action plan, evidence review and provider sign-off Embed improvements through monthly governance meetings, audit programme, compliance calendar, competency assessments, supervisions, provider oversight, mock inspections, continuous quality improvement, mandatory e-learning and face-to-face competency training (w/c 6 July 2026). | H123: External Consultant / Provider | I123: High | J123: 46201 | K123: 46218 | M123: Not Started | N123: Red - Not Started | O123: Demonstrates ongoing assurance against CQC standards. Improvements have been implemented and continue to be embedded across the service. The home currently has no residents, allowing governance systems, documentation, environmental improvements and workforce development to be fully established prior to future admissions. Mandatory e-learning is monitored through the Training Matrix. Face-to-face training (w/c 6 July 2026) covers Care Planning, Care Notes, Professional Observations, Oral Care, MCA, DoLS, Dementia, Safeguarding, Personal Care, Duty of Candour, Mental Health, Trauma-informed Care, Behaviour Support, Risk Assessment and professional terminology. Fire alarm upgrade to Category L1 and fire door replacement are in progress. Weekly/monthly fire compliance checks will recommence once works are completed and commissioned. PEEPs and dependency reviews will commence upon admission of residents. Compliance monitored via governance, audits and provider oversight. | P123: Mock inspection report, action plan, evidence pack, provider sign-off Governance Workbook; Master Action Plan; Audit Workbook 1; Audit Workbook 2; Compliance Calendar; Fire & Compliance Workbook; Cleaning Workbook; Dependency Tool & PEEPs; Handover & Allocation Workbook; Training Matrix; Personnel Files; Resident Admission Pack; Funding Pack; New Resident Tracker; Agency Induction; Agency Competency; Face-to-face Training Records (w/c 6 July 2026); Competency Assessments; Supervisions; Professional Discussions; Mock Inspections; Fire Alarm Upgrade; Fire Door Replacement. | Q123: GW; MAP; AW1; AW2; CC; FCW; CS; DT; HAW; TM; PF; RAP; FP; NRT | R123: No | U123: CQC Draft / NoP
A124: A108 | B124: Reg 17 | C124: Well-led | D124: Version control and document review schedule required for all policies, care plans, audits and trackers | E124: Records and policies were not consistently current, localised or controlled | F124: Create document control register Immediate review completed. Governance systems strengthened, audits implemented, leadership oversight increased, policies reviewed, environmental improvements commenced, staff training programme implemented and risks escalated where required. | G124: Monthly document control audit and annual policy review schedule Embed improvements through monthly governance meetings, audit programme, compliance calendar, competency assessments, supervisions, provider oversight, mock inspections, continuous quality improvement, mandatory e-learning and face-to-face competency training (w/c 6 July 2026). | H124: Administrator / Registered Manager | I124: High | J124: 46201 | K124: 46218 | M124: Not Started | N124: Red - Not Started | O124: template/policy and documentation control issues. Improvements have been implemented and continue to be embedded across the service. The home currently has no residents, allowing governance systems, documentation, environmental improvements and workforce development to be fully established prior to future admissions. Mandatory e-learning is monitored through the Training Matrix. Face-to-face training (w/c 6 July 2026) covers Care Planning, Care Notes, Professional Observations, Oral Care, MCA, DoLS, Dementia, Safeguarding, Personal Care, Duty of Candour, Mental Health, Trauma-informed Care, Behaviour Support, Risk Assessment and professional terminology. Fire alarm upgrade to Category L1 and fire door replacement are in progress. Weekly/monthly fire compliance checks will recommence once works are completed and commissioned. PEEPs and dependency reviews will commence upon admission of residents. Compliance monitored via governance, audits and provider oversight. | P124: Document control register, version history, review dates, policy sign-off Governance Workbook; Master Action Plan; Audit Workbook 1; Audit Workbook 2; Compliance Calendar; Fire & Compliance Workbook; Cleaning Workbook; Dependency Tool & PEEPs; Handover & Allocation Workbook; Training Matrix; Personnel Files; Resident Admission Pack; Funding Pack; New Resident Tracker; Agency Induction; Agency Competency; Face-to-face Training Records (w/c 6 July 2026); Competency Assessments; Supervisions; Professional Discussions; Mock Inspections; Fire Alarm Upgrade; Fire Door Replacement. | Q124: GW; MAP; AW1; AW2; CC; FCW; CS; DT; HAW; TM; PF; RAP; FP; NRT | R124: No | U124: Reg 17 / NoP
... A127: A111 | B127: Reg 17 | C127: Well-led | D127: Sustainability reviews at 3, 6 and 12 months required for all major improvements | E127: CQC and Essex identified that improvements were not sustained | F127: Set sustainability review dates for each major action Immediate review completed. Governance systems strengthened, audits implemented, leadership oversight increased, policies reviewed, environmental improvements commenced, staff training programme implemented and risks escalated where required. | G127: Review whether change remains embedded in daily practice and update action plan accordingly Embed improvements through monthly governance meetings, audit programme, compliance calendar, competency assessments, supervisions, provider oversight, mock inspections, continuous quality improvement, mandatory e-learning and face-to-face competency training (w/c 6 July 2026). | H127: Provider / Registered Manager | I127: High | J127: 46201 | K127: 46218 | M127: Not Started | N127: Red - Not Started | O127: Directly addresses sustained improvement concern. Improvements have been implemented and continue to be embedded across the service. The home currently has no residents, allowing governance systems, documentation, environmental improvements and workforce development to be fully established prior to future admissions. Mandatory e-learning is monitored through the Training Matrix. Face-to-face training (w/c 6 July 2026) covers Care Planning, Care Notes, Professional Observations, Oral Care, MCA, DoLS, Dementia, Safeguarding, Personal Care, Duty of Candour, Mental Health, Trauma-informed Care, Behaviour Support, Risk Assessment and professional terminology. Fire alarm upgrade to Category L1 and fire door replacement are in progress. Weekly/monthly fire compliance checks will recommence once works are completed and commissioned. PEEPs and dependency reviews will commence upon admission of residents. Compliance monitored via governance, audits and provider oversight. | P127: Sustainability review record, audit results, staff competency evidence, provider sign-off Governance Workbook; Master Action Plan; Audit Workbook 1; Audit Workbook 2; Compliance Calendar; Fire & Compliance Workbook; Cleaning Workbook; Dependency Tool & PEEPs; Handover & Allocation Workbook; Training Matrix; Personnel Files; Resident Admission Pack; Funding Pack; New Resident Tracker; Agency Induction; Agency Competency; Face-to-face Training Records (w/c 6 July 2026); Competency Assessments; Supervisions; Professional Discussions; Mock Inspections; Fire Alarm Upgrade; Fire Door Replacement. | Q127: GW; MAP; AW1; AW2; CC; FCW; CS; DT; HAW; TM; PF; RAP; FP; NRT | R127: No | U127: CQC Draft / Essex Letter

Sheet Regulation Tracker
A1: Regulation | B1: Purpose / Area | C1: Total Actions | D1: Completed | E1: Verified | F1: Outstanding | G1: Overdue | H1: Compliance % | I1: Overall RAG | J1: Comments
A2: Reg 9 | B2: Person-centred care | C2: =COUNTIF('Master Action Plan'!$B:$B,A2) -> 10 | D2: =COUNTIFS('Master Action Plan'!$B:$B,A2,'Master Action Plan'!$M:$M,"Completed")+COUNTIFS('Master Action Plan'!$B:$B,A2,'Master Action Plan'!$M:$M,"Verified") -> 0 | E2: =COUNTIFS('Master Action Plan'!$B:$B,A2,'Master Action Plan'!$M:$M,"Verified") -> 0 | F2: =C2-D2 -> 10 | G2: =COUNTIFS('Master Action Plan'!$B:$B,A2,'Master Action Plan'!$K:$K,"<"&TODAY(),'Master Action Plan'!$M:$M,"<>Completed",'Master Action Plan'!$M:$M,"<>Verified") -> 0 | H2: =IF(C2=0,0,D2/C2) -> 0 | I2: =IF(H2>=0.9,"Green",IF(H2>=0.6,"Amber","Red")) -> Red
A3: Reg 10 | B3: Dignity and respect | C3: =COUNTIF('Master Action Plan'!$B:$B,A3) -> 10 | D3: =COUNTIFS('Master Action Plan'!$B:$B,A3,'Master Action Plan'!$M:$M,"Completed")+COUNTIFS('Master Action Plan'!$B:$B,A3,'Master Action Plan'!$M:$M,"Verified") -> 0 | E3: =COUNTIFS('Master Action Plan'!$B:$B,A3,'Master Action Plan'!$M:$M,"Verified") -> 0 | F3: =C3-D3 -> 10 | G3: =COUNTIFS('Master Action Plan'!$B:$B,A3,'Master Action Plan'!$K:$K,"<"&TODAY(),'Master Action Plan'!$M:$M,"<>Completed",'Master Action Plan'!$M:$M,"<>Verified") -> 0 | H3: =IF(C3=0,0,D3/C3) -> 0 | I3: =IF(H3>=0.9,"Green",IF(H3>=0.6,"Amber","Red")) -> Red
A4: Reg 11 | B4: Need for consent / MCA | C4: =COUNTIF('Master Action Plan'!$B:$B,A4) -> 10 | D4: =COUNTIFS('Master Action Plan'!$B:$B,A4,'Master Action Plan'!$M:$M,"Completed")+COUNTIFS('Master Action Plan'!$B:$B,A4,'Master Action Plan'!$M:$M,"Verified") -> 0 | E4: =COUNTIFS('Master Action Plan'!$B:$B,A4,'Master Action Plan'!$M:$M,"Verified") -> 0 | F4: =C4-D4 -> 10 | G4: =COUNTIFS('Master Action Plan'!$B:$B,A4,'Master Action Plan'!$K:$K,"<"&TODAY(),'Master Action Plan'!$M:$M,"<>Completed",'Master Action Plan'!$M:$M,"<>Verified") -> 0 | H4: =IF(C4=0,0,D4/C4) -> 0 | I4: =IF(H4>=0.9,"Green",IF(H4>=0.6,"Amber","Red")) -> Red
A5: Reg 12 | B5: Safe care and treatment | C5: =COUNTIF('Master Action Plan'!$B:$B,A5) -> 23 | D5: =COUNTIFS('Master Action Plan'!$B:$B,A5,'Master Action Plan'!$M:$M,"Completed")+COUNTIFS('Master Action Plan'!$B:$B,A5,'Master Action Plan'!$M:$M,"Verified") -> 0 | E5: =COUNTIFS('Master Action Plan'!$B:$B,A5,'Master Action Plan'!$M:$M,"Verified") -> 0 | F5: =C5-D5 -> 23 | G5: =COUNTIFS('Master Action Plan'!$B:$B,A5,'Master Action Plan'!$K:$K,"<"&TODAY(),'Master Action Plan'!$M:$M,"<>Completed",'Master Action Plan'!$M:$M,"<>Verified") -> 0 | H5: =IF(C5=0,0,D5/C5) -> 0 | I5: =IF(H5>=0.9,"Green",IF(H5>=0.6,"Amber","Red")) -> Red
A6: Reg 13 | B6: Safeguarding | C6: =COUNTIF('Master Action Plan'!$B:$B,A6) -> 9 | D6: =COUNTIFS('Master Action Plan'!$B:$B,A6,'Master Action Plan'!$M:$M,"Completed")+COUNTIFS('Master Action Plan'!$B:$B,A6,'Master Action Plan'!$M:$M,"Verified") -> 0 | E6: =COUNTIFS('Master Action Plan'!$B:$B,A6,'Master Action Plan'!$M:$M,"Verified") -> 0 | F6: =C6-D6 -> 9 | G6: =COUNTIFS('Master Action Plan'!$B:$B,A6,'Master Action Plan'!$K:$K,"<"&TODAY(),'Master Action Plan'!$M:$M,"<>Completed",'Master Action Plan'!$M:$M,"<>Verified") -> 0 | H6: =IF(C6=0,0,D6/C6) -> 0 | I6: =IF(H6>=0.9,"Green",IF(H6>=0.6,"Amber","Red")) -> Red
A7: Reg 15 | B7: Premises and equipment | C7: =COUNTIF('Master Action Plan'!$B:$B,A7) -> 8 | D7: =COUNTIFS('Master Action Plan'!$B:$B,A7,'Master Action Plan'!$M:$M,"Completed")+COUNTIFS('Master Action Plan'!$B:$B,A7,'Master Action Plan'!$M:$M,"Verified") -> 0 | E7: =COUNTIFS('Master Action Plan'!$B:$B,A7,'Master Action Plan'!$M:$M,"Verified") -> 0 | F7: =C7-D7 -> 8 | G7: =COUNTIFS('Master Action Plan'!$B:$B,A7,'Master Action Plan'!$K:$K,"<"&TODAY(),'Master Action Plan'!$M:$M,"<>Completed",'Master Action Plan'!$M:$M,"<>Verified") -> 0 | H7: =IF(C7=0,0,D7/C7) -> 0 | I7: =IF(H7>=0.9,"Green",IF(H7>=0.6,"Amber","Red")) -> Red
A8: Reg 17 | B8: Good governance | C8: =COUNTIF('Master Action Plan'!$B:$B,A8) -> 23 | D8: =COUNTIFS('Master Action Plan'!$B:$B,A8,'Master Action Plan'!$M:$M,"Completed")+COUNTIFS('Master Action Plan'!$B:$B,A8,'Master Action Plan'!$M:$M,"Verified") -> 0 | E8: =COUNTIFS('Master Action Plan'!$B:$B,A8,'Master Action Plan'!$M:$M,"Verified") -> 0 | F8: =C8-D8 -> 23 | G8: =COUNTIFS('Master Action Plan'!$B:$B,A8,'Master Action Plan'!$K:$K,"<"&TODAY(),'Master Action Plan'!$M:$M,"<>Completed",'Master Action Plan'!$M:$M,"<>Verified") -> 0 | H8: =IF(C8=0,0,D8/C8) -> 0 | I8: =IF(H8>=0.9,"Green",IF(H8>=0.6,"Amber","Red")) -> Red
A9: Reg 18 | B9: Staffing, training and competence | C9: =COUNTIF('Master Action Plan'!$B:$B,A9) -> 10 | D9: =COUNTIFS('Master Action Plan'!$B:$B,A9,'Master Action Plan'!$M:$M,"Completed")+COUNTIFS('Master Action Plan'!$B:$B,A9,'Master Action Plan'!$M:$M,"Verified") -> 0 | E9: =COUNTIFS('Master Action Plan'!$B:$B,A9,'Master Action Plan'!$M:$M,"Verified") -> 0 | F9: =C9-D9 -> 10 | G9: =COUNTIFS('Master Action Plan'!$B:$B,A9,'Master Action Plan'!$K:$K,"<"&TODAY(),'Master Action Plan'!$M:$M,"<>Completed",'Master Action Plan'!$M:$M,"<>Verified") -> 0 | H9: =IF(C9=0,0,D9/C9) -> 0 | I9: =IF(H9>=0.9,"Green",IF(H9>=0.6,"Amber","Red")) -> Red
A10: Reg 19 | B10: Fit and proper persons employed | C10: =COUNTIF('Master Action Plan'!$B:$B,A10) -> 8 | D10: =COUNTIFS('Master Action Plan'!$B:$B,A10,'Master Action Plan'!$M:$M,"Completed")+COUNTIFS('Master Action Plan'!$B:$B,A10,'Master Action Plan'!$M:$M,"Verified") -> 0 | E10: =COUNTIFS('Master Action Plan'!$B:$B,A10,'Master Action Plan'!$M:$M,"Verified") -> 0 | F10: =C10-D10 -> 8 | G10: =COUNTIFS('Master Action Plan'!$B:$B,A10,'Master Action Plan'!$K:$K,"<"&TODAY(),'Master Action Plan'!$M:$M,"<>Completed",'Master Action Plan'!$M:$M,"<>Verified") -> 0 | H10: =IF(C10=0,0,D10/C10) -> 0 | I10: =IF(H10>=0.9,"Green",IF(H10>=0.6,"Amber","Red")) -> Red

Sheet Evidence Tracker
A1: Evidence ID | B1: Linked Action ID | C1: Regulation | D1: Evidence Type | E1: Document / File Name | F1: Folder Location / Link | G1: Date Added | H1: Verified? | I1: Verified By | J1: Comments
A2: EV001 | D2: Care Plan | H2: No
A3: EV002 | D3: Risk Assessment | H3: No
A4: EV003 | D4: Training | H4: No
A5: EV004 | D5: Audit | H5: No
A6: EV005 | D6: Fire Evidence | H6: No
A7: EV006 | D7: Medication Evidence | H7: No
A8: EV007 | D8: Safeguarding | H8: No
A9: EV008 | D9: Governance | H9: No
A10: EV009 | D10: Premises/Equipment | H10: No
A11: EV010 | D11: Recruitment | H11: No
A12: EV011 | D12: Care Plan | H12: No
A13: EV012 | D13: Risk Assessment | H13: No
... A101: EV100 | D101: Recruitment | H101: No
A102: EV097 | B102: A097 | C102: Reg 17 | D102: Governance / Regulatory Evidence | H102: No | J102: Evidence required for red-added action: Sustained improvement programme required following CQC/Essex concerns that improvements were not embedded or sustained
A103: EV098 | B103: A098 | C103: Reg 17 | D103: Governance / Regulatory Evidence | H103: No | J103: Evidence required for red-added action: Formal partnership working with commissioners, safeguarding, fire service, GP, district nurses and MDT must be evidenced
A104: EV099 | B104: A099 | C104: Reg 17 | D104: Governance / Regulatory Evidence | H104: No | J104: Evidence required for red-added action: Financial sustainability and business continuity assurance required
A105: EV100 | B105: A100 | C105: Reg 12 | D105: Governance / Regulatory Evidence | H105: No | J105: Evidence required for red-added action: Resident transition and transfer planning must be fully evidenced for any move between services
A106: EV101 | B106: A101 | C106: Reg 17 | D106: Governance / Regulatory Evidence | H106: No | J106: Evidence required for red-added action: Evidence file required for every completed action before status is changed to completed
A107: EV102 | B107: A102 | C107: Reg 17 | D107: Governance / Regulatory Evidence | H107: No | J107: Evidence required for red-added action: Independent verification of completed actions required
A108: EV103 | B108: A103 | C108: Reg 17 | D108: Governance / Regulatory Evidence | H108: No | J108: Evidence required for red-added action: Monthly provider assurance review required with clear minutes, decisions and follow-up
A109: EV104 | B109: A104 | C109: Reg 17 | D109: Governance / Regulatory Evidence | H109: No | J109: Evidence required for red-added action: Governance trend dashboard required to identify patterns and repeated risks
A110: EV105 | B110: A105 | C110: Reg 13 | D110: Governance / Regulatory Evidence | H110: No | J110: Evidence required for red-added action: Monthly lessons learned meeting required for safeguarding, incidents, complaints, accidents and near misses
A111: EV106 | B111: A106 | C111: Reg 17 | D111: Governance / Regulatory Evidence | H111: No | J111: Evidence required for red-added action: Quality Improvement Register required to track improvements from audits through to completion and verification
A112: EV107 | B112: A107 | C112: Reg 17 | D112: Governance / Regulatory Evidence | H112: No | J112: Evidence required for red-added action: Quarterly mock CQC inspection required across all key questions
A113: EV108 | B113: A108 | C113: Reg 17 | D113: Governance / Regulatory Evidence | H113: No | J113: Evidence required for red-added action: Version control and document review schedule required for all policies, care plans, audits and trackers
... A116: EV111 | B116: A111 | C116: Reg 17 | D116: Governance / Regulatory Evidence | H116: No | J116: Evidence required for red-added action: Sustainability reviews at 3, 6 and 12 months required for all major improvements

Sheet Lists
A1: Status | B1: Priority | C1: Regulation | D1: Key Question
A2: Not Started | B2: Critical | C2: Reg 9 | D2: Safe
A3: In Progress | B3: High | C3: Reg 10 | D3: Effective
A4: Completed | B4: Medium | C4: Reg 11 | D4: Caring
A5: Verified | B5: Low | C5: Reg 12 | D5: Responsive
A6: On Hold | C6: Reg 13 | D6: Well-led
A7: N/A | C7: Reg 15
C8: Reg 17
C9: Reg 18
C10: Reg 19
