Workbook

Sheet How to Use
A1: How to Use - Resident Wellbeing & Meaningful Activity Pack
A2: This guide explains how staff should complete the new embedded workbook tabs.
A4: Section | B4: What staff must do | C4: CQC evidence produced
A5: Meaningful Activity Assessment | B5: Complete within 72 hours of admission. Record life history, culture, preferences, abilities and individual activity plan. | C5: Shows activities are planned around identity, preferences and abilities.
A6: Life Story Book | B6: Complete with resident and/or family. Include childhood, occupation, family, achievements, memories and important places. | C6: Shows the home understands the person beyond care tasks.
A7: This Is Me | B7: Create a quick profile for all staff to use daily. Include communication, routine, likes/dislikes, reassurance and triggers. | C7: Shows consistent person-centred care across the staff team.
A8: Weekly Activity Planner | B8: Plan each week using the assessment. Include one-to-one, group, spiritual, physical, sensory and community activities. | C8: Shows activities are planned, not ad hoc.
A9: Daily Activity Outcomes | B9: Record what happened, mood before/after and outcome. Avoid generic notes like 'joined in well'. | C9: Shows impact on wellbeing and emotional outcomes.
A10: Monthly Activity Audit | B10: Manager to audit completion, quality and actions monthly with RAG status. | C10: Shows management oversight and governance.
A11: Activity Evidence Tracker | B11: Record where evidence is stored, including photos, family feedback, planners and audit evidence. | C11: Shows clear evidence trail for inspectors.
A13: Worked Example
A14: Resident | B14: Mrs Teresa Edmunds
A15: Life History | B15: Retired primary school teacher for 38 years. Enjoyed gardening, reading, flowers and church.
A16: Meaningful Activities | B16: Reading children's books, watering plants, flower arranging, hymn singing, organising books.
A17: Good outcome note | B17: Resident engaged for 45 minutes, smiled, reminisced about teaching children and appeared calmer afterwards. She requested to repeat the activity next week.
A18: Poor outcome note | B18: Resident did bingo.

Sheet Front Dashboard
A1: Resident Governance Dashboard - MCA, DoLS & Best Interests | T1: Family Involvement Governance
A3: Resident Name | N3: Administration RAG Summary | T3: KPI | U3: Formula / Source | V3: Target | W3: RAG
A4: NHS Number | N4: Red | O4: =COUNTIF(G48:G58,"Red") -> 11 | T4: Family decision records | U4: Complete from Family Decision Register | V4: 100%
A5: Admission Date | N5: Amber | O5: =COUNTIF(G48:G58,"Amber") -> 0 | T5: Communication logs | U5: Complete after each decision/event | V5: 100%
A6: Room Number | N6: Green | O6: =COUNTIF(G48:G58,"Green") -> 0 | T6: Best Interest family views | U6: Included where required | V6: 100%
A7: Responsible Person | N7: Total Registers | O7: =COUNTA(A48:A58) -> 11 | T7: Significant event notifications | U7: Recorded promptly | V7: 100%
A8: Dashboard Date | B8: =TODAY() -> 46201 | T8: Monthly audit | U8: Completed monthly | V8: 100%
A10: Area | B10: Open Tab | C10: Total Applicable | D10: Red Overdue | E10: Amber Due 30 Days | F10: Green In Date | G10: Grey N/A | H10: Overall RAG | I10: Last Reviewed | J10: Next Review Due | K10: Responsible Person | L10: CQC Review Notes | N10: Resident Expenses Log Summary
A11: MCA | B11: =HYPERLINK("#'MCA'!A1","See MCA Tab") -> See MCA Tab | C11: =COUNTIF(MCA!C5:C75,"Yes") -> 0 | D11: =COUNTIF(MCA!Y5:Y75,"Red") -> 0 | E11: =COUNTIF(MCA!Y5:Y75,"Amber") -> 0 | F11: =COUNTIF(MCA!Y5:Y75,"Green") -> 0 | G11: =COUNTIF(MCA!Y5:Y75,"Grey") -> 71 | H11: =IF(C11=0,"Grey",IF(D11>0,"Red",IF(E11>0,"Amber","Green"))) -> Grey | I11: =IF(COUNT(MCA!V5:V75)=0,"",MAX(MCA!V5:V75)) | J11: =IF(COUNT(MCA!W5:W75)=0,"",MIN(MCA!W5:W75)) | N11: Total Money In | O11: ='Resident Expenses Log'!$O$2 -> 0
A12: Best Interests | B12: =HYPERLINK("#'Best Interests'!A1","See Best Interests Tab") -> See Best Interests Tab | C12: =COUNTIF('Best Interests'!C5:C40,"Yes") -> 0 | D12: =COUNTIF('Best Interests'!Y5:Y40,"Red") -> 0 | E12: =COUNTIF('Best Interests'!Y5:Y40,"Amber") -> 0 | F12: =COUNTIF('Best Interests'!Y5:Y40,"Green") -> 0 | G12: =COUNTIF('Best Interests'!Y5:Y40,"Grey") -> 36 | H12: =IF(C12=0,"Grey",IF(D12>0,"Red",IF(E12>0,"Amber","Green"))) -> Grey | I12: =IF(COUNT('Best Interests'!V5:V40)=0,"",MAX('Best Interests'!V5:V40)) | J12: =IF(COUNT('Best Interests'!W5:W40)=0,"",MIN('Best Interests'!W5:W40)) | N12: Total Money Out | O12: ='Resident Expenses Log'!$O$3 -> 0
A13: DoLS | B13: =HYPERLINK("#'DoLS'!A1","See DoLS Tab") -> See DoLS Tab | C13: =COUNTIF(DoLS!C5:C35,"Yes") -> 0 | D13: =COUNTIF(DoLS!Y5:Y35,"Red") -> 0 | E13: =COUNTIF(DoLS!Y5:Y35,"Amber") -> 0 | F13: =COUNTIF(DoLS!Y5:Y35,"Green") -> 0 | G13: =COUNTIF(DoLS!Y5:Y35,"Grey") -> 31 | H13: =IF(C13=0,"Grey",IF(D13>0,"Red",IF(E13>0,"Amber","Green"))) -> Grey | I13: =IF(COUNT(DoLS!V5:V35)=0,"",MAX(DoLS!V5:V35)) | J13: =IF(COUNT(DoLS!W5:W35)=0,"",MIN(DoLS!W5:W35)) | N13: Current Balance | O13: ='Resident Expenses Log'!$O$4 -> 0
N14: Last Entry Date | O14: =MAX('Resident Expenses Log'!$A$2:$A$41) -> 0
A15: Overall Dashboard Alert | N15: Open Expenses Tab | O15: Resident Expenses Log
A16: Overall RAG | B16: =IF(COUNTIF(H11:H13,"Red")>0,"Red",IF(COUNTIF(H11:H13,"Amber")>0,"Amber",IF(COUNTIF(H11:H13,"Green")>0,"Green","Grey"))) -> Grey
A17: MCA Assessment Due/Overdue Flag | B17: =IF(OR(D11>0,E11>0),"ACTION REQUIRED","OK") -> OK
A18: DoLS Due/Overdue Flag | B18: =IF(OR(D13>0,E13>0),"ACTION REQUIRED","OK") -> OK
A19: Best Interest Due/Overdue Flag | B19: =IF(OR(D12>0,E12>0),"ACTION REQUIRED","OK") -> OK
A22: Resident Record Area | B22: Jan | C22: Feb | D22: Mar | E22: Apr | F22: May | G22: Jun | H22: Jul | I22: Aug | J22: Sep | K22: Oct | L22: Nov | M22: Dec | N22: Date Last Reviewed | O22: Next Review Due | P22: Responsible Person | Q22: RAG | R22: Comments
A23: Resident Details | O23: =IF(N23="","",EDATE(N23,1)) | Q23: =IF(O23="","Red",IF(O23<TODAY(),"Red",IF(O23<=TODAY()+30,"Amber","Green"))) -> Red
A24: Next of Kin Details | O24: =IF(N24="","",EDATE(N24,1)) | Q24: =IF(O24="","Red",IF(O24<TODAY(),"Red",IF(O24<=TODAY()+30,"Amber","Green"))) -> Red
A25: GP Registration | O25: =IF(N25="","",EDATE(N25,1)) | Q25: =IF(O25="","Red",IF(O25<TODAY(),"Red",IF(O25<=TODAY()+30,"Amber","Green"))) -> Red
A26: DNACPR | O26: =IF(N26="","",EDATE(N26,1)) | Q26: =IF(O26="","Red",IF(O26<TODAY(),"Red",IF(O26<=TODAY()+30,"Amber","Green"))) -> Red
A27: Advance Care Plan | O27: =IF(N27="","",EDATE(N27,1)) | Q27: =IF(O27="","Red",IF(O27<TODAY(),"Red",IF(O27<=TODAY()+30,"Amber","Green"))) -> Red
A28: End of Life Plan | O28: =IF(N28="","",EDATE(N28,1)) | Q28: =IF(O28="","Red",IF(O28<TODAY(),"Red",IF(O28<=TODAY()+30,"Amber","Green"))) -> Red
A29: Consent Forms | O29: =IF(N29="","",EDATE(N29,1)) | Q29: =IF(O29="","Red",IF(O29<TODAY(),"Red",IF(O29<=TODAY()+30,"Amber","Green"))) -> Red
A30: Photograph Consent | O30: =IF(N30="","",EDATE(N30,1)) | Q30: =IF(O30="","Red",IF(O30<TODAY(),"Red",IF(O30<=TODAY()+30,"Amber","Green"))) -> Red
A31: CCTV Consent | O31: =IF(N31="","",EDATE(N31,1)) | Q31: =IF(O31="","Red",IF(O31<TODAY(),"Red",IF(O31<=TODAY()+30,"Amber","Green"))) -> Red
A32: Data Sharing Consent | O32: =IF(N32="","",EDATE(N32,1)) | Q32: =IF(O32="","Red",IF(O32<TODAY(),"Red",IF(O32<=TODAY()+30,"Amber","Green"))) -> Red
A33: Resident Agreement | O33: =IF(N33="","",EDATE(N33,1)) | Q33: =IF(O33="","Red",IF(O33<TODAY(),"Red",IF(O33<=TODAY()+30,"Amber","Green"))) -> Red
A34: Fees Agreement | O34: =IF(N34="","",EDATE(N34,1)) | Q34: =IF(O34="","Red",IF(O34<TODAY(),"Red",IF(O34<=TODAY()+30,"Amber","Green"))) -> Red
... A39: Petty Cash Log | O39: =IF(N39="","",EDATE(N39,1)) | Q39: =IF(O39="","Red",IF(O39<TODAY(),"Red",IF(O39<=TODAY()+30,"Amber","Green"))) -> Red
A40: Personal Expenses Log | O40: =IF(N40="","",EDATE(N40,1)) | Q40: =IF(O40="","Red",IF(O40<TODAY(),"Red",IF(O40<=TODAY()+30,"Amber","Green"))) -> Red | R40: Linked to Resident Expenses Log tab
A41: MCA Register | O41: =IF(N41="","",EDATE(N41,1)) | Q41: =IF(O41="","Red",IF(O41<TODAY(),"Red",IF(O41<=TODAY()+30,"Amber","Green"))) -> Red
A42: Best Interest Decisions | O42: =IF(N42="","",EDATE(N42,1)) | Q42: =IF(O42="","Red",IF(O42<TODAY(),"Red",IF(O42<=TODAY()+30,"Amber","Green"))) -> Red
A43: DoLS Tracker | O43: =IF(N43="","",EDATE(N43,1)) | Q43: =IF(O43="","Red",IF(O43<TODAY(),"Red",IF(O43<=TODAY()+30,"Amber","Green"))) -> Red
A45: Administration Registers - Linked Dashboard
A47: Register | B47: Open Tab | C47: Review Frequency | D47: Last Reviewed | E47: Next Review Due | F47: Responsible Person | G47: RAG | H47: Notes
A48: Resident Agreement | B48: =HYPERLINK("#'Resident Agreement'!A1","Open") -> Open | C48: ='Resident Agreement'!B5 -> Monthly | D48: ='Resident Agreement'!B4 -> 0 | E48: ='Resident Agreement'!B6 | F48: ='Resident Agreement'!B7 -> Registered Manager | G48: ='Resident Agreement'!B8 -> Red
A49: Fees Agreement | B49: =HYPERLINK("#'Fees Agreement'!A1","Open") -> Open | C49: ='Fees Agreement'!B5 -> 12 months | D49: ='Fees Agreement'!B4 -> 0 | E49: ='Fees Agreement'!B6 | F49: ='Fees Agreement'!B7 -> Registered Manager | G49: ='Fees Agreement'!B8 -> Red
A50: Inventory | B50: =HYPERLINK("#'Inventory'!A1","Open") -> Open | C50: =Inventory!B5 -> Monthly | D50: =Inventory!B4 -> 0 | E50: =Inventory!B6 | F50: =Inventory!B7 -> Registered Manager | G50: =Inventory!B8 -> Red
A51: Jewellery Register | B51: =HYPERLINK("#'Jewellery Register'!A1","Open") -> Open | C51: ='Jewellery Register'!B5 -> Monthly | D51: ='Jewellery Register'!B4 -> 0 | E51: ='Jewellery Register'!B6 | F51: ='Jewellery Register'!B7 -> Registered Manager | G51: ='Jewellery Register'!B8 -> Red
A52: Safe Contents | B52: =HYPERLINK("#'Safe Contents'!A1","Open") -> Open | C52: ='Safe Contents'!B5 -> Monthly | D52: ='Safe Contents'!B4 -> 0 | E52: ='Safe Contents'!B6 | F52: ='Safe Contents'!B7 -> Registered Manager | G52: ='Safe Contents'!B8 -> Red
A53: Property Returned | B53: =HYPERLINK("#'Property Returned'!A1","Open") -> Open | C53: ='Property Returned'!B5 -> Monthly | D53: ='Property Returned'!B4 -> 0 | E53: ='Property Returned'!B6 | F53: ='Property Returned'!B7 -> Registered Manager | G53: ='Property Returned'!B8 -> Red
A54: Resident Finance | B54: =HYPERLINK("#'Resident Finance'!A1","Open") -> Open | C54: ='Resident Finance'!B5 -> Monthly | D54: ='Resident Finance'!B4 -> 0 | E54: ='Resident Finance'!B6 | F54: ='Resident Finance'!B7 -> Registered Manager | G54: ='Resident Finance'!B8 -> Red
A55: CCTV Consent | B55: =HYPERLINK("#'CCTV Consent'!A1","Open") -> Open | C55: ='CCTV Consent'!B5 -> Monthly | D55: ='CCTV Consent'!B4 -> 0 | E55: ='CCTV Consent'!B6 | F55: ='CCTV Consent'!B7 -> Registered Manager | G55: ='CCTV Consent'!B8 -> Red
A56: Data Sharing Consent | B56: =HYPERLINK("#'Data Sharing Consent'!A1","Open") -> Open | C56: ='Data Sharing Consent'!B5 -> Monthly | D56: ='Data Sharing Consent'!B4 -> 0 | E56: ='Data Sharing Consent'!B6 | F56: ='Data Sharing Consent'!B7 -> Registered Manager | G56: ='Data Sharing Consent'!B8 -> Red
A57: Social Media Consent | B57: =HYPERLINK("#'Social Media Consent'!A1","Open") -> Open | C57: ='Social Media Consent'!B5 -> Monthly | D57: ='Social Media Consent'!B4 -> 0 | E57: ='Social Media Consent'!B6 | F57: ='Social Media Consent'!B7 -> Registered Manager | G57: ='Social Media Consent'!B8 -> Red
A58: Telephone Consent | B58: =HYPERLINK("#'Telephone Consent'!A1","Open") -> Open | C58: ='Telephone Consent'!B5 -> 12 | D58: ='Telephone Consent'!B4 -> 0 | E58: ='Telephone Consent'!B6 | F58: ='Telephone Consent'!B7 -> Registered Manager | G58: ='Telephone Consent'!B8 -> Red
A59: Resident Expenses Log | B59: Resident Expenses Log | C59: Monthly | H59: Track money in/out and balance for each resident
A62: Meaningful Activity & Wellbeing Dashboard
A64: KPI | B64: Formula / Count | C64: Target | D64: RAG
A65: Activity assessments started | B65: =COUNTIF('Meaningful Activity Assessment'!A4:A123,"?*") -> 0 | C65: 100% | D65: =IF(B65=0,"Amber","Green") -> Amber
A66: Activity assessments overdue | B66: =COUNTIF('Meaningful Activity Assessment'!L4:L123,"Red*") -> 0 | C66: 0 | D66: =IF(B66>0,"Red","Green") -> Green
A67: Activity assessments due soon | B67: =COUNTIF('Meaningful Activity Assessment'!L4:L123,"Amber*") -> 0 | C67: 0 | D67: =IF(B67>0,"Amber","Green") -> Green
A68: Life Story records started | B68: =COUNTIF('Life Story Book'!A4:A123,"?*") -> 0 | C68: 100% | D68: =IF(B68=0,"Amber","Green") -> Amber
A69: "This Is Me" profiles started | B69: =COUNTIF('This Is Me'!A4:A123,"?*") -> 0 | C69: 100% | D69: =IF(B69=0,"Amber","Green") -> Amber
A70: Daily activity outcomes recorded | B70: =COUNTIF('Daily Activity Outcomes'!A4:A123,"?*") -> 0 | C70: Daily | D70: =IF(B70=0,"Amber","Green") -> Amber
A71: Monthly audits recorded | B71: =COUNTIF('Monthly Activity Audit'!A4:A123,"?*") -> 0 | C71: Monthly | D71: =IF(B71=0,"Amber","Green") -> Amber

Sheet MCA
A1: MCA - Resident Monthly Review Tracker
A2: Resident Name | C2: NHS No. | E2: Admission Date | G2: Room No. | I2: Key Worker
A4: No. | B4: Decision / Item | C4: Applicable? | D4: Jan | E4: Feb | F4: Mar | G4: Apr | H4: May | I4: Jun | J4: Jul | K4: Aug | L4: Sep | M4: Oct | N4: Nov | O4: Dec | P4: Meeting Held | Q4: Family Consulted | R4: LPA Consulted | S4: IMCA Required | T4: Outcome | U4: Review Frequency Months | V4: Last Reviewed | W4: Next Review Due | X4: Responsible Person | Y4: RAG | Z4: Comments
A5: 1 | B5: Admission to care home | U5: 1 | W5: =IF(V5="","",EDATE(V5,U5)) | Y5: =IF(C5<>"Yes","Grey",IF(W5="","Red",IF(W5<TODAY(),"Red",IF(W5<=TODAY()+30,"Amber","Green")))) -> Grey
A6: 2 | B6: Remaining in care home | U6: 1 | W6: =IF(V6="","",EDATE(V6,U6)) | Y6: =IF(C6<>"Yes","Grey",IF(W6="","Red",IF(W6<TODAY(),"Red",IF(W6<=TODAY()+30,"Amber","Green")))) -> Grey
A7: 3 | B7: Transfer to another care home | U7: 1 | W7: =IF(V7="","",EDATE(V7,U7)) | Y7: =IF(C7<>"Yes","Grey",IF(W7="","Red",IF(W7<TODAY(),"Red",IF(W7<=TODAY()+30,"Amber","Green")))) -> Grey
A8: 4 | B8: Hospital admission | U8: 1 | W8: =IF(V8="","",EDATE(V8,U8)) | Y8: =IF(C8<>"Yes","Grey",IF(W8="","Red",IF(W8<TODAY(),"Red",IF(W8<=TODAY()+30,"Amber","Green")))) -> Grey
A9: 5 | B9: Hospital discharge | U9: 1 | W9: =IF(V9="","",EDATE(V9,U9)) | Y9: =IF(C9<>"Yes","Grey",IF(W9="","Red",IF(W9<TODAY(),"Red",IF(W9<=TODAY()+30,"Amber","Green")))) -> Grey
A10: 6 | B10: Consent to personal care | U10: 1 | W10: =IF(V10="","",EDATE(V10,U10)) | Y10: =IF(C10<>"Yes","Grey",IF(W10="","Red",IF(W10<TODAY(),"Red",IF(W10<=TODAY()+30,"Amber","Green")))) -> Grey
A11: 7 | B11: Washing | U11: 1 | W11: =IF(V11="","",EDATE(V11,U11)) | Y11: =IF(C11<>"Yes","Grey",IF(W11="","Red",IF(W11<TODAY(),"Red",IF(W11<=TODAY()+30,"Amber","Green")))) -> Grey
A12: 8 | B12: Bathing or showering | U12: 1 | W12: =IF(V12="","",EDATE(V12,U12)) | Y12: =IF(C12<>"Yes","Grey",IF(W12="","Red",IF(W12<TODAY(),"Red",IF(W12<=TODAY()+30,"Amber","Green")))) -> Grey
A13: 9 | B13: Dressing | U13: 1 | W13: =IF(V13="","",EDATE(V13,U13)) | Y13: =IF(C13<>"Yes","Grey",IF(W13="","Red",IF(W13<TODAY(),"Red",IF(W13<=TODAY()+30,"Amber","Green")))) -> Grey
A14: 10 | B14: Oral care | U14: 1 | W14: =IF(V14="","",EDATE(V14,U14)) | Y14: =IF(C14<>"Yes","Grey",IF(W14="","Red",IF(W14<TODAY(),"Red",IF(W14<=TODAY()+30,"Amber","Green")))) -> Grey
A15: 11 | B15: Continence care | U15: 1 | W15: =IF(V15="","",EDATE(V15,U15)) | Y15: =IF(C15<>"Yes","Grey",IF(W15="","Red",IF(W15<TODAY(),"Red",IF(W15<=TODAY()+30,"Amber","Green")))) -> Grey
A16: 12 | B16: Medication | U16: 1 | W16: =IF(V16="","",EDATE(V16,U16)) | Y16: =IF(C16<>"Yes","Grey",IF(W16="","Red",IF(W16<TODAY(),"Red",IF(W16<=TODAY()+30,"Amber","Green")))) -> Grey
... A75: 71 | B75: Other decision - free text | U75: 1 | W75: =IF(V75="","",EDATE(V75,U75)) | Y75: =IF(C75<>"Yes","Grey",IF(W75="","Red",IF(W75<TODAY(),"Red",IF(W75<=TODAY()+30,"Amber","Green")))) -> Grey

Sheet Best Interests
A1: Best Interests - Resident Monthly Review Tracker
A2: Resident Name | C2: NHS No. | E2: Admission Date | G2: Room No. | I2: Key Worker
A4: No. | B4: Decision / Item | C4: Applicable? | D4: Jan | E4: Feb | F4: Mar | G4: Apr | H4: May | I4: Jun | J4: Jul | K4: Aug | L4: Sep | M4: Oct | N4: Nov | O4: Dec | P4: Meeting Held | Q4: Family Consulted | R4: LPA Consulted | S4: IMCA Required | T4: Outcome | U4: Review Frequency Months | V4: Last Reviewed | W4: Next Review Due | X4: Responsible Person | Y4: RAG | Z4: Comments
A5: 1 | B5: Admission to care home | U5: 1 | W5: =IF(V5="","",EDATE(V5,U5)) | Y5: =IF(C5<>"Yes","Grey",IF(W5="","Red",IF(W5<TODAY(),"Red",IF(W5<=TODAY()+30,"Amber","Green")))) -> Grey
A6: 2 | B6: Remaining in care home | U6: 1 | W6: =IF(V6="","",EDATE(V6,U6)) | Y6: =IF(C6<>"Yes","Grey",IF(W6="","Red",IF(W6<TODAY(),"Red",IF(W6<=TODAY()+30,"Amber","Green")))) -> Grey
A7: 3 | B7: Hospital admission | U7: 1 | W7: =IF(V7="","",EDATE(V7,U7)) | Y7: =IF(C7<>"Yes","Grey",IF(W7="","Red",IF(W7<TODAY(),"Red",IF(W7<=TODAY()+30,"Amber","Green")))) -> Grey
A8: 4 | B8: Hospital discharge | U8: 1 | W8: =IF(V8="","",EDATE(V8,U8)) | Y8: =IF(C8<>"Yes","Grey",IF(W8="","Red",IF(W8<TODAY(),"Red",IF(W8<=TODAY()+30,"Amber","Green")))) -> Grey
A9: 5 | B9: Transfer of placement | U9: 1 | W9: =IF(V9="","",EDATE(V9,U9)) | Y9: =IF(C9<>"Yes","Grey",IF(W9="","Red",IF(W9<TODAY(),"Red",IF(W9<=TODAY()+30,"Amber","Green")))) -> Grey
A10: 6 | B10: Medical treatment | U10: 1 | W10: =IF(V10="","",EDATE(V10,U10)) | Y10: =IF(C10<>"Yes","Grey",IF(W10="","Red",IF(W10<TODAY(),"Red",IF(W10<=TODAY()+30,"Amber","Green")))) -> Grey
A11: 7 | B11: Surgery | U11: 1 | W11: =IF(V11="","",EDATE(V11,U11)) | Y11: =IF(C11<>"Yes","Grey",IF(W11="","Red",IF(W11<TODAY(),"Red",IF(W11<=TODAY()+30,"Amber","Green")))) -> Grey
A12: 8 | B12: Vaccinations | U12: 1 | W12: =IF(V12="","",EDATE(V12,U12)) | Y12: =IF(C12<>"Yes","Grey",IF(W12="","Red",IF(W12<TODAY(),"Red",IF(W12<=TODAY()+30,"Amber","Green")))) -> Grey
A13: 9 | B13: Medication | U13: 1 | W13: =IF(V13="","",EDATE(V13,U13)) | Y13: =IF(C13<>"Yes","Grey",IF(W13="","Red",IF(W13<TODAY(),"Red",IF(W13<=TODAY()+30,"Amber","Green")))) -> Grey
A14: 10 | B14: Covert medication | U14: 1 | W14: =IF(V14="","",EDATE(V14,U14)) | Y14: =IF(C14<>"Yes","Grey",IF(W14="","Red",IF(W14<TODAY(),"Red",IF(W14<=TODAY()+30,"Amber","Green")))) -> Grey
A15: 11 | B15: Nutrition plan | U15: 1 | W15: =IF(V15="","",EDATE(V15,U15)) | Y15: =IF(C15<>"Yes","Grey",IF(W15="","Red",IF(W15<TODAY(),"Red",IF(W15<=TODAY()+30,"Amber","Green")))) -> Grey
A16: 12 | B16: PEG feeding | U16: 1 | W16: =IF(V16="","",EDATE(V16,U16)) | Y16: =IF(C16<>"Yes","Grey",IF(W16="","Red",IF(W16<TODAY(),"Red",IF(W16<=TODAY()+30,"Amber","Green")))) -> Grey
... A40: 36 | B40: Other best interest decision - free text | U40: 1 | W40: =IF(V40="","",EDATE(V40,U40)) | Y40: =IF(C40<>"Yes","Grey",IF(W40="","Red",IF(W40<TODAY(),"Red",IF(W40<=TODAY()+30,"Amber","Green")))) -> Grey

Sheet DoLS
A1: DoLS - Resident Monthly Review Tracker
A2: Resident Name | C2: NHS No. | E2: Admission Date | G2: Room No. | I2: Key Worker
A4: No. | B4: Decision / Item | C4: Applicable? | D4: Jan | E4: Feb | F4: Mar | G4: Apr | H4: May | I4: Jun | J4: Jul | K4: Aug | L4: Sep | M4: Oct | N4: Nov | O4: Dec | P4: Meeting Held | Q4: Family Consulted | R4: LPA Consulted | S4: IMCA Required | T4: Outcome | U4: Review Frequency Months | V4: Last Reviewed | W4: Next Review Due | X4: Responsible Person | Y4: RAG | Z4: Comments
A5: 1 | B5: Capacity assessment completed | U5: 1 | W5: =IF(V5="","",EDATE(V5,U5)) | Y5: =IF(C5<>"Yes","Grey",IF(W5="","Red",IF(W5<TODAY(),"Red",IF(W5<=TODAY()+30,"Amber","Green")))) -> Grey
A6: 2 | B6: Continuous supervision considered | U6: 1 | W6: =IF(V6="","",EDATE(V6,U6)) | Y6: =IF(C6<>"Yes","Grey",IF(W6="","Red",IF(W6<TODAY(),"Red",IF(W6<=TODAY()+30,"Amber","Green")))) -> Grey
A7: 3 | B7: Not free to leave considered | U7: 1 | W7: =IF(V7="","",EDATE(V7,U7)) | Y7: =IF(C7<>"Yes","Grey",IF(W7="","Red",IF(W7<TODAY(),"Red",IF(W7<=TODAY()+30,"Amber","Green")))) -> Grey
A8: 4 | B8: Less restrictive options considered | U8: 1 | W8: =IF(V8="","",EDATE(V8,U8)) | Y8: =IF(C8<>"Yes","Grey",IF(W8="","Red",IF(W8<TODAY(),"Red",IF(W8<=TODAY()+30,"Amber","Green")))) -> Grey
A9: 5 | B9: Best interests assessment completed | U9: 1 | W9: =IF(V9="","",EDATE(V9,U9)) | Y9: =IF(C9<>"Yes","Grey",IF(W9="","Red",IF(W9<TODAY(),"Red",IF(W9<=TODAY()+30,"Amber","Green")))) -> Grey
A10: 6 | B10: Mental health assessment | U10: 1 | W10: =IF(V10="","",EDATE(V10,U10)) | Y10: =IF(C10<>"Yes","Grey",IF(W10="","Red",IF(W10<TODAY(),"Red",IF(W10<=TODAY()+30,"Amber","Green")))) -> Grey
A11: 7 | B11: Eligibility assessment | U11: 1 | W11: =IF(V11="","",EDATE(V11,U11)) | Y11: =IF(C11<>"Yes","Grey",IF(W11="","Red",IF(W11<TODAY(),"Red",IF(W11<=TODAY()+30,"Amber","Green")))) -> Grey
A12: 8 | B12: No refusals assessment | U12: 1 | W12: =IF(V12="","",EDATE(V12,U12)) | Y12: =IF(C12<>"Yes","Grey",IF(W12="","Red",IF(W12<TODAY(),"Red",IF(W12<=TODAY()+30,"Amber","Green")))) -> Grey
A13: 9 | B13: Urgent authorisation considered | U13: 1 | W13: =IF(V13="","",EDATE(V13,U13)) | Y13: =IF(C13<>"Yes","Grey",IF(W13="","Red",IF(W13<TODAY(),"Red",IF(W13<=TODAY()+30,"Amber","Green")))) -> Grey
A14: 10 | B14: Urgent authorisation completed | U14: 1 | W14: =IF(V14="","",EDATE(V14,U14)) | Y14: =IF(C14<>"Yes","Grey",IF(W14="","Red",IF(W14<TODAY(),"Red",IF(W14<=TODAY()+30,"Amber","Green")))) -> Grey
A15: 11 | B15: Standard authorisation submitted | U15: 1 | W15: =IF(V15="","",EDATE(V15,U15)) | Y15: =IF(C15<>"Yes","Grey",IF(W15="","Red",IF(W15<TODAY(),"Red",IF(W15<=TODAY()+30,"Amber","Green")))) -> Grey
A16: 12 | B16: Application acknowledged | U16: 1 | W16: =IF(V16="","",EDATE(V16,U16)) | Y16: =IF(C16<>"Yes","Grey",IF(W16="","Red",IF(W16<TODAY(),"Red",IF(W16<=TODAY()+30,"Amber","Green")))) -> Grey
... A35: 31 | B35: Other DoLS item - free text | U35: 1 | W35: =IF(V35="","",EDATE(V35,U35)) | Y35: =IF(C35<>"Yes","Grey",IF(W35="","Red",IF(W35<TODAY(),"Red",IF(W35<=TODAY()+30,"Amber","Green")))) -> Grey

Sheet Resident Agreement
A1: AS Care - Resident Agreement
A3: Resident Name
A4: Last Reviewed
A5: Review Frequency (months) | B5: Monthly
A6: Next Review Due | B6: =IF(B4="","",EDATE(B4,B5))
A7: Responsible Person | B7: Registered Manager
A8: RAG | B8: =IF(B6="","Red",IF(B6<TODAY(),"Red",IF(B6<=TODAY()+30,"Amber","Green"))) -> Red
A9: Evidence Location | B9: Resident file / this register
A12: Checklist Item | B12: Applicable | C12: Jan | D12: Feb | E12: Mar | F12: Apr | G12: May | H12: Jun | I12: Jul | J12: Aug | K12: Sep | L12: Oct | M12: Nov | N12: Dec | O12: Completed | P12: Last Reviewed | Q12: Next Review Due | R12: Responsible Person | S12: RAG | T12: Evidence / Notes
A13: Resident details completed | B13: ☐ | C13: ☐ | D13: ☐ | E13: ☐ | F13: ☐ | G13: ☐ | H13: ☐ | I13: ☐ | J13: ☐ | K13: ☐ | L13: ☐ | M13: ☐ | N13: ☐ | O13: ☐ | Q13: =IF(P13="","",EDATE(P13,$B$5)) | R13: Registered Manager | S13: =IF(B13="☐","N/A",IF(Q13="","Red",IF(Q13<TODAY(),"Red",IF(Q13<=TODAY()+30,"Amber","Green")))) -> N/A
A14: Agreement issued to resident/representative | B14: ☐ | C14: ☐ | D14: ☐ | E14: ☐ | F14: ☐ | G14: ☐ | H14: ☐ | I14: ☐ | J14: ☐ | K14: ☐ | L14: ☐ | M14: ☐ | N14: ☐ | O14: ☐ | Q14: =IF(P14="","",EDATE(P14,$B$5)) | R14: Registered Manager | S14: =IF(B14="☐","N/A",IF(Q14="","Red",IF(Q14<TODAY(),"Red",IF(Q14<=TODAY()+30,"Amber","Green")))) -> N/A
A15: Terms explained | B15: ☐ | C15: ☐ | D15: ☐ | E15: ☐ | F15: ☐ | G15: ☐ | H15: ☐ | I15: ☐ | J15: ☐ | K15: ☐ | L15: ☐ | M15: ☐ | N15: ☐ | O15: ☐ | Q15: =IF(P15="","",EDATE(P15,$B$5)) | R15: Registered Manager | S15: =IF(B15="☐","N/A",IF(Q15="","Red",IF(Q15<TODAY(),"Red",IF(Q15<=TODAY()+30,"Amber","Green")))) -> N/A
A16: Room and service information completed | B16: ☐ | C16: ☐ | D16: ☐ | E16: ☐ | F16: ☐ | G16: ☐ | H16: ☐ | I16: ☐ | J16: ☐ | K16: ☐ | L16: ☐ | M16: ☐ | N16: ☐ | O16: ☐ | Q16: =IF(P16="","",EDATE(P16,$B$5)) | R16: Registered Manager | S16: =IF(B16="☐","N/A",IF(Q16="","Red",IF(Q16<TODAY(),"Red",IF(Q16<=TODAY()+30,"Amber","Green")))) -> N/A
A17: Resident rights and responsibilities included | B17: ☐ | C17: ☐ | D17: ☐ | E17: ☐ | F17: ☐ | G17: ☐ | H17: ☐ | I17: ☐ | J17: ☐ | K17: ☐ | L17: ☐ | M17: ☐ | N17: ☐ | O17: ☐ | Q17: =IF(P17="","",EDATE(P17,$B$5)) | R17: Registered Manager | S17: =IF(B17="☐","N/A",IF(Q17="","Red",IF(Q17<TODAY(),"Red",IF(Q17<=TODAY()+30,"Amber","Green")))) -> N/A
A18: Complaints information included | B18: ☐ | C18: ☐ | D18: ☐ | E18: ☐ | F18: ☐ | G18: ☐ | H18: ☐ | I18: ☐ | J18: ☐ | K18: ☐ | L18: ☐ | M18: ☐ | N18: ☐ | O18: ☐ | Q18: =IF(P18="","",EDATE(P18,$B$5)) | R18: Registered Manager | S18: =IF(B18="☐","N/A",IF(Q18="","Red",IF(Q18<TODAY(),"Red",IF(Q18<=TODAY()+30,"Amber","Green")))) -> N/A
A19: Signatures completed | B19: ☐ | C19: ☐ | D19: ☐ | E19: ☐ | F19: ☐ | G19: ☐ | H19: ☐ | I19: ☐ | J19: ☐ | K19: ☐ | L19: ☐ | M19: ☐ | N19: ☐ | O19: ☐ | Q19: =IF(P19="","",EDATE(P19,$B$5)) | R19: Registered Manager | S19: =IF(B19="☐","N/A",IF(Q19="","Red",IF(Q19<TODAY(),"Red",IF(Q19<=TODAY()+30,"Amber","Green")))) -> N/A
A20: Copy provided | B20: ☐ | C20: ☐ | D20: ☐ | E20: ☐ | F20: ☐ | G20: ☐ | H20: ☐ | I20: ☐ | J20: ☐ | K20: ☐ | L20: ☐ | M20: ☐ | N20: ☐ | O20: ☐ | Q20: =IF(P20="","",EDATE(P20,$B$5)) | R20: Registered Manager | S20: =IF(B20="☐","N/A",IF(Q20="","Red",IF(Q20<TODAY(),"Red",IF(Q20<=TODAY()+30,"Amber","Green")))) -> N/A
A21: Annual review completed | B21: ☐ | C21: ☐ | D21: ☐ | E21: ☐ | F21: ☐ | G21: ☐ | H21: ☐ | I21: ☐ | J21: ☐ | K21: ☐ | L21: ☐ | M21: ☐ | N21: ☐ | O21: ☐ | Q21: =IF(P21="","",EDATE(P21,$B$5)) | R21: Registered Manager | S21: =IF(B21="☐","N/A",IF(Q21="","Red",IF(Q21<TODAY(),"Red",IF(Q21<=TODAY()+30,"Amber","Green")))) -> N/A

Sheet Fees Agreement
A1: AS Care - Fees Agreement
A3: Resident Name
A4: Last Reviewed
A5: Review Frequency (months) | B5: 12 months
A6: Next Review Due | B6: =IF(B4="","",EDATE(B4,B5))
A7: Responsible Person | B7: Registered Manager
A8: RAG | B8: =IF(B6="","Red",IF(B6<TODAY(),"Red",IF(B6<=TODAY()+30,"Amber","Green"))) -> Red
A9: Evidence Location | B9: Resident file / this register
A12: Checklist Item | B12: Applicable | C12: Jan | D12: Feb | E12: Mar | F12: Apr | G12: May | H12: Jun | I12: Jul | J12: Aug | K12: Sep | L12: Oct | M12: Nov | N12: Dec | O12: Completed | P12: Last Reviewed | Q12: Next Review Due | R12: Responsible Person | S12: RAG | T12: Evidence / Notes
A13: Funding type recorded | B13: ☐ | C13: ☐ | D13: ☐ | E13: ☐ | F13: ☐ | G13: ☐ | H13: ☐ | I13: ☐ | J13: ☐ | K13: ☐ | L13: ☐ | M13: ☐ | N13: ☐ | O13: ☐ | Q13: =IF(P13="","",EDATE(P13,$B$5)) | R13: Registered Manager | S13: =IF(B13="☐","N/A",IF(Q13="","Red",IF(Q13<TODAY(),"Red",IF(Q13<=TODAY()+30,"Amber","Green")))) -> N/A
A14: Weekly fee recorded | B14: ☐ | C14: ☐ | D14: ☐ | E14: ☐ | F14: ☐ | G14: ☐ | H14: ☐ | I14: ☐ | J14: ☐ | K14: ☐ | L14: ☐ | M14: ☐ | N14: ☐ | O14: ☐ | Q14: =IF(P14="","",EDATE(P14,$B$5)) | R14: Registered Manager | S14: =IF(B14="☐","N/A",IF(Q14="","Red",IF(Q14<TODAY(),"Red",IF(Q14<=TODAY()+30,"Amber","Green")))) -> N/A
A15: Top-up/third party agreement recorded | B15: ☐ | C15: ☐ | D15: ☐ | E15: ☐ | F15: ☐ | G15: ☐ | H15: ☐ | I15: ☐ | J15: ☐ | K15: ☐ | L15: ☐ | M15: ☐ | N15: ☐ | O15: ☐ | Q15: =IF(P15="","",EDATE(P15,$B$5)) | R15: Registered Manager | S15: =IF(B15="☐","N/A",IF(Q15="","Red",IF(Q15<TODAY(),"Red",IF(Q15<=TODAY()+30,"Amber","Green")))) -> N/A
A16: Payment method recorded | B16: ☐ | C16: ☐ | D16: ☐ | E16: ☐ | F16: ☐ | G16: ☐ | H16: ☐ | I16: ☐ | J16: ☐ | K16: ☐ | L16: ☐ | M16: ☐ | N16: ☐ | O16: ☐ | Q16: =IF(P16="","",EDATE(P16,$B$5)) | R16: Registered Manager | S16: =IF(B16="☐","N/A",IF(Q16="","Red",IF(Q16<TODAY(),"Red",IF(Q16<=TODAY()+30,"Amber","Green")))) -> N/A
A17: Billing contact confirmed | B17: ☐ | C17: ☐ | D17: ☐ | E17: ☐ | F17: ☐ | G17: ☐ | H17: ☐ | I17: ☐ | J17: ☐ | K17: ☐ | L17: ☐ | M17: ☐ | N17: ☐ | O17: ☐ | Q17: =IF(P17="","",EDATE(P17,$B$5)) | R17: Registered Manager | S17: =IF(B17="☐","N/A",IF(Q17="","Red",IF(Q17<TODAY(),"Red",IF(Q17<=TODAY()+30,"Amber","Green")))) -> N/A
A18: Fee review clause explained | B18: ☐ | C18: ☐ | D18: ☐ | E18: ☐ | F18: ☐ | G18: ☐ | H18: ☐ | I18: ☐ | J18: ☐ | K18: ☐ | L18: ☐ | M18: ☐ | N18: ☐ | O18: ☐ | Q18: =IF(P18="","",EDATE(P18,$B$5)) | R18: Registered Manager | S18: =IF(B18="☐","N/A",IF(Q18="","Red",IF(Q18<TODAY(),"Red",IF(Q18<=TODAY()+30,"Amber","Green")))) -> N/A
A19: Outstanding balance process explained | B19: ☐ | C19: ☐ | D19: ☐ | E19: ☐ | F19: ☐ | G19: ☐ | H19: ☐ | I19: ☐ | J19: ☐ | K19: ☐ | L19: ☐ | M19: ☐ | N19: ☐ | O19: ☐ | Q19: =IF(P19="","",EDATE(P19,$B$5)) | R19: Registered Manager | S19: =IF(B19="☐","N/A",IF(Q19="","Red",IF(Q19<TODAY(),"Red",IF(Q19<=TODAY()+30,"Amber","Green")))) -> N/A
A20: Signatures completed | B20: ☐ | C20: ☐ | D20: ☐ | E20: ☐ | F20: ☐ | G20: ☐ | H20: ☐ | I20: ☐ | J20: ☐ | K20: ☐ | L20: ☐ | M20: ☐ | N20: ☐ | O20: ☐ | Q20: =IF(P20="","",EDATE(P20,$B$5)) | R20: Registered Manager | S20: =IF(B20="☐","N/A",IF(Q20="","Red",IF(Q20<TODAY(),"Red",IF(Q20<=TODAY()+30,"Amber","Green")))) -> N/A
A21: Annual review completed | B21: ☐ | C21: ☐ | D21: ☐ | E21: ☐ | F21: ☐ | G21: ☐ | H21: ☐ | I21: ☐ | J21: ☐ | K21: ☐ | L21: ☐ | M21: ☐ | N21: ☐ | O21: ☐ | Q21: =IF(P21="","",EDATE(P21,$B$5)) | R21: Registered Manager | S21: =IF(B21="☐","N/A",IF(Q21="","Red",IF(Q21<TODAY(),"Red",IF(Q21<=TODAY()+30,"Amber","Green")))) -> N/A

Sheet Inventory
A1: AS Care - Inventory
A3: Resident Name
A4: Last Reviewed
A5: Review Frequency (months) | B5: Monthly
A6: Next Review Due | B6: =IF(B4="","",EDATE(B4,B5))
A7: Responsible Person | B7: Registered Manager
A8: RAG | B8: =IF(B6="","Red",IF(B6<TODAY(),"Red",IF(B6<=TODAY()+30,"Amber","Green"))) -> Red
A9: Evidence Location | B9: Resident file / this register
A12: Checklist Item | B12: Applicable | C12: Jan | D12: Feb | E12: Mar | F12: Apr | G12: May | H12: Jun | I12: Jul | J12: Aug | K12: Sep | L12: Oct | M12: Nov | N12: Dec | O12: Completed | P12: Last Reviewed | Q12: Next Review Due | R12: Responsible Person | S12: RAG | T12: Evidence / Notes
A13: Clothing recorded | B13: ☐ | C13: ☐ | D13: ☐ | E13: ☐ | F13: ☐ | G13: ☐ | H13: ☐ | I13: ☐ | J13: ☐ | K13: ☐ | L13: ☐ | M13: ☐ | N13: ☐ | O13: ☐ | Q13: =IF(P13="","",EDATE(P13,$B$5)) | R13: Registered Manager | S13: =IF(B13="☐","N/A",IF(Q13="","Red",IF(Q13<TODAY(),"Red",IF(Q13<=TODAY()+30,"Amber","Green")))) -> N/A
A14: Footwear recorded | B14: ☐ | C14: ☐ | D14: ☐ | E14: ☐ | F14: ☐ | G14: ☐ | H14: ☐ | I14: ☐ | J14: ☐ | K14: ☐ | L14: ☐ | M14: ☐ | N14: ☐ | O14: ☐ | Q14: =IF(P14="","",EDATE(P14,$B$5)) | R14: Registered Manager | S14: =IF(B14="☐","N/A",IF(Q14="","Red",IF(Q14<TODAY(),"Red",IF(Q14<=TODAY()+30,"Amber","Green")))) -> N/A
A15: Toiletries recorded | B15: ☐ | C15: ☐ | D15: ☐ | E15: ☐ | F15: ☐ | G15: ☐ | H15: ☐ | I15: ☐ | J15: ☐ | K15: ☐ | L15: ☐ | M15: ☐ | N15: ☐ | O15: ☐ | Q15: =IF(P15="","",EDATE(P15,$B$5)) | R15: Registered Manager | S15: =IF(B15="☐","N/A",IF(Q15="","Red",IF(Q15<TODAY(),"Red",IF(Q15<=TODAY()+30,"Amber","Green")))) -> N/A
A16: Mobility aids recorded | B16: ☐ | C16: ☐ | D16: ☐ | E16: ☐ | F16: ☐ | G16: ☐ | H16: ☐ | I16: ☐ | J16: ☐ | K16: ☐ | L16: ☐ | M16: ☐ | N16: ☐ | O16: ☐ | Q16: =IF(P16="","",EDATE(P16,$B$5)) | R16: Registered Manager | S16: =IF(B16="☐","N/A",IF(Q16="","Red",IF(Q16<TODAY(),"Red",IF(Q16<=TODAY()+30,"Amber","Green")))) -> N/A
A17: Electrical items recorded | B17: ☐ | C17: ☐ | D17: ☐ | E17: ☐ | F17: ☐ | G17: ☐ | H17: ☐ | I17: ☐ | J17: ☐ | K17: ☐ | L17: ☐ | M17: ☐ | N17: ☐ | O17: ☐ | Q17: =IF(P17="","",EDATE(P17,$B$5)) | R17: Registered Manager | S17: =IF(B17="☐","N/A",IF(Q17="","Red",IF(Q17<TODAY(),"Red",IF(Q17<=TODAY()+30,"Amber","Green")))) -> N/A
A18: Furniture/items from home recorded | B18: ☐ | C18: ☐ | D18: ☐ | E18: ☐ | F18: ☐ | G18: ☐ | H18: ☐ | I18: ☐ | J18: ☐ | K18: ☐ | L18: ☐ | M18: ☐ | N18: ☐ | O18: ☐ | Q18: =IF(P18="","",EDATE(P18,$B$5)) | R18: Registered Manager | S18: =IF(B18="☐","N/A",IF(Q18="","Red",IF(Q18<TODAY(),"Red",IF(Q18<=TODAY()+30,"Amber","Green")))) -> N/A
A19: Items labelled | B19: ☐ | C19: ☐ | D19: ☐ | E19: ☐ | F19: ☐ | G19: ☐ | H19: ☐ | I19: ☐ | J19: ☐ | K19: ☐ | L19: ☐ | M19: ☐ | N19: ☐ | O19: ☐ | Q19: =IF(P19="","",EDATE(P19,$B$5)) | R19: Registered Manager | S19: =IF(B19="☐","N/A",IF(Q19="","Red",IF(Q19<TODAY(),"Red",IF(Q19<=TODAY()+30,"Amber","Green")))) -> N/A
A20: Condition recorded | B20: ☐ | C20: ☐ | D20: ☐ | E20: ☐ | F20: ☐ | G20: ☐ | H20: ☐ | I20: ☐ | J20: ☐ | K20: ☐ | L20: ☐ | M20: ☐ | N20: ☐ | O20: ☐ | Q20: =IF(P20="","",EDATE(P20,$B$5)) | R20: Registered Manager | S20: =IF(B20="☐","N/A",IF(Q20="","Red",IF(Q20<TODAY(),"Red",IF(Q20<=TODAY()+30,"Amber","Green")))) -> N/A
A21: Resident/representative signature | B21: ☐ | C21: ☐ | D21: ☐ | E21: ☐ | F21: ☐ | G21: ☐ | H21: ☐ | I21: ☐ | J21: ☐ | K21: ☐ | L21: ☐ | M21: ☐ | N21: ☐ | O21: ☐ | Q21: =IF(P21="","",EDATE(P21,$B$5)) | R21: Registered Manager | S21: =IF(B21="☐","N/A",IF(Q21="","Red",IF(Q21<TODAY(),"Red",IF(Q21<=TODAY()+30,"Amber","Green")))) -> N/A

Sheet Jewellery Register
A1: AS Care - Jewellery Register
A3: Resident Name
A4: Last Reviewed
A5: Review Frequency (months) | B5: Monthly
A6: Next Review Due | B6: =IF(B4="","",EDATE(B4,B5))
A7: Responsible Person | B7: Registered Manager
A8: RAG | B8: =IF(B6="","Red",IF(B6<TODAY(),"Red",IF(B6<=TODAY()+30,"Amber","Green"))) -> Red
A9: Evidence Location | B9: Resident file / this register
A12: Checklist Item | B12: Applicable | C12: Jan | D12: Feb | E12: Mar | F12: Apr | G12: May | H12: Jun | I12: Jul | J12: Aug | K12: Sep | L12: Oct | M12: Nov | N12: Dec | O12: Completed | P12: Last Reviewed | Q12: Next Review Due | R12: Responsible Person | S12: RAG | T12: Evidence / Notes
A13: Rings recorded | B13: ☐ | C13: ☐ | D13: ☐ | E13: ☐ | F13: ☐ | G13: ☐ | H13: ☐ | I13: ☐ | J13: ☐ | K13: ☐ | L13: ☐ | M13: ☐ | N13: ☐ | O13: ☐ | Q13: =IF(P13="","",EDATE(P13,$B$5)) | R13: Registered Manager | S13: =IF(B13="☐","N/A",IF(Q13="","Red",IF(Q13<TODAY(),"Red",IF(Q13<=TODAY()+30,"Amber","Green")))) -> N/A
A14: Watches recorded | B14: ☐ | C14: ☐ | D14: ☐ | E14: ☐ | F14: ☐ | G14: ☐ | H14: ☐ | I14: ☐ | J14: ☐ | K14: ☐ | L14: ☐ | M14: ☐ | N14: ☐ | O14: ☐ | Q14: =IF(P14="","",EDATE(P14,$B$5)) | R14: Registered Manager | S14: =IF(B14="☐","N/A",IF(Q14="","Red",IF(Q14<TODAY(),"Red",IF(Q14<=TODAY()+30,"Amber","Green")))) -> N/A
A15: Necklaces recorded | B15: ☐ | C15: ☐ | D15: ☐ | E15: ☐ | F15: ☐ | G15: ☐ | H15: ☐ | I15: ☐ | J15: ☐ | K15: ☐ | L15: ☐ | M15: ☐ | N15: ☐ | O15: ☐ | Q15: =IF(P15="","",EDATE(P15,$B$5)) | R15: Registered Manager | S15: =IF(B15="☐","N/A",IF(Q15="","Red",IF(Q15<TODAY(),"Red",IF(Q15<=TODAY()+30,"Amber","Green")))) -> N/A
A16: Bracelets recorded | B16: ☐ | C16: ☐ | D16: ☐ | E16: ☐ | F16: ☐ | G16: ☐ | H16: ☐ | I16: ☐ | J16: ☐ | K16: ☐ | L16: ☐ | M16: ☐ | N16: ☐ | O16: ☐ | Q16: =IF(P16="","",EDATE(P16,$B$5)) | R16: Registered Manager | S16: =IF(B16="☐","N/A",IF(Q16="","Red",IF(Q16<TODAY(),"Red",IF(Q16<=TODAY()+30,"Amber","Green")))) -> N/A
A17: Earrings recorded | B17: ☐ | C17: ☐ | D17: ☐ | E17: ☐ | F17: ☐ | G17: ☐ | H17: ☐ | I17: ☐ | J17: ☐ | K17: ☐ | L17: ☐ | M17: ☐ | N17: ☐ | O17: ☐ | Q17: =IF(P17="","",EDATE(P17,$B$5)) | R17: Registered Manager | S17: =IF(B17="☐","N/A",IF(Q17="","Red",IF(Q17<TODAY(),"Red",IF(Q17<=TODAY()+30,"Amber","Green")))) -> N/A
A18: Other valuables recorded | B18: ☐ | C18: ☐ | D18: ☐ | E18: ☐ | F18: ☐ | G18: ☐ | H18: ☐ | I18: ☐ | J18: ☐ | K18: ☐ | L18: ☐ | M18: ☐ | N18: ☐ | O18: ☐ | Q18: =IF(P18="","",EDATE(P18,$B$5)) | R18: Registered Manager | S18: =IF(B18="☐","N/A",IF(Q18="","Red",IF(Q18<TODAY(),"Red",IF(Q18<=TODAY()+30,"Amber","Green")))) -> N/A
A19: Photographic description/description recorded | B19: ☐ | C19: ☐ | D19: ☐ | E19: ☐ | F19: ☐ | G19: ☐ | H19: ☐ | I19: ☐ | J19: ☐ | K19: ☐ | L19: ☐ | M19: ☐ | N19: ☐ | O19: ☐ | Q19: =IF(P19="","",EDATE(P19,$B$5)) | R19: Registered Manager | S19: =IF(B19="☐","N/A",IF(Q19="","Red",IF(Q19<TODAY(),"Red",IF(Q19<=TODAY()+30,"Amber","Green")))) -> N/A
A20: Storage decision recorded | B20: ☐ | C20: ☐ | D20: ☐ | E20: ☐ | F20: ☐ | G20: ☐ | H20: ☐ | I20: ☐ | J20: ☐ | K20: ☐ | L20: ☐ | M20: ☐ | N20: ☐ | O20: ☐ | Q20: =IF(P20="","",EDATE(P20,$B$5)) | R20: Registered Manager | S20: =IF(B20="☐","N/A",IF(Q20="","Red",IF(Q20<TODAY(),"Red",IF(Q20<=TODAY()+30,"Amber","Green")))) -> N/A
A21: Return/removal recorded | B21: ☐ | C21: ☐ | D21: ☐ | E21: ☐ | F21: ☐ | G21: ☐ | H21: ☐ | I21: ☐ | J21: ☐ | K21: ☐ | L21: ☐ | M21: ☐ | N21: ☐ | O21: ☐ | Q21: =IF(P21="","",EDATE(P21,$B$5)) | R21: Registered Manager | S21: =IF(B21="☐","N/A",IF(Q21="","Red",IF(Q21<TODAY(),"Red",IF(Q21<=TODAY()+30,"Amber","Green")))) -> N/A

Sheet Safe Contents
A1: AS Care - Safe Contents
A3: Resident Name
A4: Last Reviewed
A5: Review Frequency (months) | B5: Monthly
A6: Next Review Due | B6: =IF(B4="","",EDATE(B4,B5))
A7: Responsible Person | B7: Registered Manager
A8: RAG | B8: =IF(B6="","Red",IF(B6<TODAY(),"Red",IF(B6<=TODAY()+30,"Amber","Green"))) -> Red
A9: Evidence Location | B9: Resident file / this register
A12: Checklist Item | B12: Applicable | C12: Jan | D12: Feb | E12: Mar | F12: Apr | G12: May | H12: Jun | I12: Jul | J12: Aug | K12: Sep | L12: Oct | M12: Nov | N12: Dec | O12: Completed | P12: Last Reviewed | Q12: Next Review Due | R12: Responsible Person | S12: RAG | T12: Evidence / Notes
A13: Cash stored | B13: ☐ | C13: ☐ | D13: ☐ | E13: ☐ | F13: ☐ | G13: ☐ | H13: ☐ | I13: ☐ | J13: ☐ | K13: ☐ | L13: ☐ | M13: ☐ | N13: ☐ | O13: ☐ | Q13: =IF(P13="","",EDATE(P13,$B$5)) | R13: Registered Manager | S13: =IF(B13="☐","N/A",IF(Q13="","Red",IF(Q13<TODAY(),"Red",IF(Q13<=TODAY()+30,"Amber","Green")))) -> N/A
A14: Bank cards stored | B14: ☐ | C14: ☐ | D14: ☐ | E14: ☐ | F14: ☐ | G14: ☐ | H14: ☐ | I14: ☐ | J14: ☐ | K14: ☐ | L14: ☐ | M14: ☐ | N14: ☐ | O14: ☐ | Q14: =IF(P14="","",EDATE(P14,$B$5)) | R14: Registered Manager | S14: =IF(B14="☐","N/A",IF(Q14="","Red",IF(Q14<TODAY(),"Red",IF(Q14<=TODAY()+30,"Amber","Green")))) -> N/A
A15: Passports/ID stored | B15: ☐ | C15: ☐ | D15: ☐ | E15: ☐ | F15: ☐ | G15: ☐ | H15: ☐ | I15: ☐ | J15: ☐ | K15: ☐ | L15: ☐ | M15: ☐ | N15: ☐ | O15: ☐ | Q15: =IF(P15="","",EDATE(P15,$B$5)) | R15: Registered Manager | S15: =IF(B15="☐","N/A",IF(Q15="","Red",IF(Q15<TODAY(),"Red",IF(Q15<=TODAY()+30,"Amber","Green")))) -> N/A
A16: Legal papers stored | B16: ☐ | C16: ☐ | D16: ☐ | E16: ☐ | F16: ☐ | G16: ☐ | H16: ☐ | I16: ☐ | J16: ☐ | K16: ☐ | L16: ☐ | M16: ☐ | N16: ☐ | O16: ☐ | Q16: =IF(P16="","",EDATE(P16,$B$5)) | R16: Registered Manager | S16: =IF(B16="☐","N/A",IF(Q16="","Red",IF(Q16<TODAY(),"Red",IF(Q16<=TODAY()+30,"Amber","Green")))) -> N/A
A17: Jewellery stored | B17: ☐ | C17: ☐ | D17: ☐ | E17: ☐ | F17: ☐ | G17: ☐ | H17: ☐ | I17: ☐ | J17: ☐ | K17: ☐ | L17: ☐ | M17: ☐ | N17: ☐ | O17: ☐ | Q17: =IF(P17="","",EDATE(P17,$B$5)) | R17: Registered Manager | S17: =IF(B17="☐","N/A",IF(Q17="","Red",IF(Q17<TODAY(),"Red",IF(Q17<=TODAY()+30,"Amber","Green")))) -> N/A
A18: Keys stored | B18: ☐ | C18: ☐ | D18: ☐ | E18: ☐ | F18: ☐ | G18: ☐ | H18: ☐ | I18: ☐ | J18: ☐ | K18: ☐ | L18: ☐ | M18: ☐ | N18: ☐ | O18: ☐ | Q18: =IF(P18="","",EDATE(P18,$B$5)) | R18: Registered Manager | S18: =IF(B18="☐","N/A",IF(Q18="","Red",IF(Q18<TODAY(),"Red",IF(Q18<=TODAY()+30,"Amber","Green")))) -> N/A
A19: Other items stored | B19: ☐ | C19: ☐ | D19: ☐ | E19: ☐ | F19: ☐ | G19: ☐ | H19: ☐ | I19: ☐ | J19: ☐ | K19: ☐ | L19: ☐ | M19: ☐ | N19: ☐ | O19: ☐ | Q19: =IF(P19="","",EDATE(P19,$B$5)) | R19: Registered Manager | S19: =IF(B19="☐","N/A",IF(Q19="","Red",IF(Q19<TODAY(),"Red",IF(Q19<=TODAY()+30,"Amber","Green")))) -> N/A
A20: Two staff signatures recorded | B20: ☐ | C20: ☐ | D20: ☐ | E20: ☐ | F20: ☐ | G20: ☐ | H20: ☐ | I20: ☐ | J20: ☐ | K20: ☐ | L20: ☐ | M20: ☐ | N20: ☐ | O20: ☐ | Q20: =IF(P20="","",EDATE(P20,$B$5)) | R20: Registered Manager | S20: =IF(B20="☐","N/A",IF(Q20="","Red",IF(Q20<TODAY(),"Red",IF(Q20<=TODAY()+30,"Amber","Green")))) -> N/A
A21: Monthly safe check completed | B21: ☐ | C21: ☐ | D21: ☐ | E21: ☐ | F21: ☐ | G21: ☐ | H21: ☐ | I21: ☐ | J21: ☐ | K21: ☐ | L21: ☐ | M21: ☐ | N21: ☐ | O21: ☐ | Q21: =IF(P21="","",EDATE(P21,$B$5)) | R21: Registered Manager | S21: =IF(B21="☐","N/A",IF(Q21="","Red",IF(Q21<TODAY(),"Red",IF(Q21<=TODAY()+30,"Amber","Green")))) -> N/A

Sheet Property Returned
A1: AS Care - Property Returned
A3: Resident Name
A4: Last Reviewed
A5: Review Frequency (months) | B5: Monthly
A6: Next Review Due | B6: =IF(B4="","",EDATE(B4,B5))
A7: Responsible Person | B7: Registered Manager
A8: RAG | B8: =IF(B6="","Red",IF(B6<TODAY(),"Red",IF(B6<=TODAY()+30,"Amber","Green"))) -> Red
A9: Evidence Location | B9: Resident file / this register
A12: Checklist Item | B12: Applicable | C12: Jan | D12: Feb | E12: Mar | F12: Apr | G12: May | H12: Jun | I12: Jul | J12: Aug | K12: Sep | L12: Oct | M12: Nov | N12: Dec | O12: Completed | P12: Last Reviewed | Q12: Next Review Due | R12: Responsible Person | S12: RAG | T12: Evidence / Notes
A13: Returned item described | B13: ☐ | C13: ☐ | D13: ☐ | E13: ☐ | F13: ☐ | G13: ☐ | H13: ☐ | I13: ☐ | J13: ☐ | K13: ☐ | L13: ☐ | M13: ☐ | N13: ☐ | O13: ☐ | Q13: =IF(P13="","",EDATE(P13,$B$5)) | R13: Registered Manager | S13: =IF(B13="☐","N/A",IF(Q13="","Red",IF(Q13<TODAY(),"Red",IF(Q13<=TODAY()+30,"Amber","Green")))) -> N/A
A14: Condition at return recorded | B14: ☐ | C14: ☐ | D14: ☐ | E14: ☐ | F14: ☐ | G14: ☐ | H14: ☐ | I14: ☐ | J14: ☐ | K14: ☐ | L14: ☐ | M14: ☐ | N14: ☐ | O14: ☐ | Q14: =IF(P14="","",EDATE(P14,$B$5)) | R14: Registered Manager | S14: =IF(B14="☐","N/A",IF(Q14="","Red",IF(Q14<TODAY(),"Red",IF(Q14<=TODAY()+30,"Amber","Green")))) -> N/A
A15: Returned to named person | B15: ☐ | C15: ☐ | D15: ☐ | E15: ☐ | F15: ☐ | G15: ☐ | H15: ☐ | I15: ☐ | J15: ☐ | K15: ☐ | L15: ☐ | M15: ☐ | N15: ☐ | O15: ☐ | Q15: =IF(P15="","",EDATE(P15,$B$5)) | R15: Registered Manager | S15: =IF(B15="☐","N/A",IF(Q15="","Red",IF(Q15<TODAY(),"Red",IF(Q15<=TODAY()+30,"Amber","Green")))) -> N/A
A16: Relationship recorded | B16: ☐ | C16: ☐ | D16: ☐ | E16: ☐ | F16: ☐ | G16: ☐ | H16: ☐ | I16: ☐ | J16: ☐ | K16: ☐ | L16: ☐ | M16: ☐ | N16: ☐ | O16: ☐ | Q16: =IF(P16="","",EDATE(P16,$B$5)) | R16: Registered Manager | S16: =IF(B16="☐","N/A",IF(Q16="","Red",IF(Q16<TODAY(),"Red",IF(Q16<=TODAY()+30,"Amber","Green")))) -> N/A
A17: Date returned | B17: ☐ | C17: ☐ | D17: ☐ | E17: ☐ | F17: ☐ | G17: ☐ | H17: ☐ | I17: ☐ | J17: ☐ | K17: ☐ | L17: ☐ | M17: ☐ | N17: ☐ | O17: ☐ | Q17: =IF(P17="","",EDATE(P17,$B$5)) | R17: Registered Manager | S17: =IF(B17="☐","N/A",IF(Q17="","Red",IF(Q17<TODAY(),"Red",IF(Q17<=TODAY()+30,"Amber","Green")))) -> N/A
A18: Staff signature | B18: ☐ | C18: ☐ | D18: ☐ | E18: ☐ | F18: ☐ | G18: ☐ | H18: ☐ | I18: ☐ | J18: ☐ | K18: ☐ | L18: ☐ | M18: ☐ | N18: ☐ | O18: ☐ | Q18: =IF(P18="","",EDATE(P18,$B$5)) | R18: Registered Manager | S18: =IF(B18="☐","N/A",IF(Q18="","Red",IF(Q18<TODAY(),"Red",IF(Q18<=TODAY()+30,"Amber","Green")))) -> N/A
A19: Recipient signature | B19: ☐ | C19: ☐ | D19: ☐ | E19: ☐ | F19: ☐ | G19: ☐ | H19: ☐ | I19: ☐ | J19: ☐ | K19: ☐ | L19: ☐ | M19: ☐ | N19: ☐ | O19: ☐ | Q19: =IF(P19="","",EDATE(P19,$B$5)) | R19: Registered Manager | S19: =IF(B19="☐","N/A",IF(Q19="","Red",IF(Q19<TODAY(),"Red",IF(Q19<=TODAY()+30,"Amber","Green")))) -> N/A
A20: Witness signature | B20: ☐ | C20: ☐ | D20: ☐ | E20: ☐ | F20: ☐ | G20: ☐ | H20: ☐ | I20: ☐ | J20: ☐ | K20: ☐ | L20: ☐ | M20: ☐ | N20: ☐ | O20: ☐ | Q20: =IF(P20="","",EDATE(P20,$B$5)) | R20: Registered Manager | S20: =IF(B20="☐","N/A",IF(Q20="","Red",IF(Q20<TODAY(),"Red",IF(Q20<=TODAY()+30,"Amber","Green")))) -> N/A
A21: Copy retained | B21: ☐ | C21: ☐ | D21: ☐ | E21: ☐ | F21: ☐ | G21: ☐ | H21: ☐ | I21: ☐ | J21: ☐ | K21: ☐ | L21: ☐ | M21: ☐ | N21: ☐ | O21: ☐ | Q21: =IF(P21="","",EDATE(P21,$B$5)) | R21: Registered Manager | S21: =IF(B21="☐","N/A",IF(Q21="","Red",IF(Q21<TODAY(),"Red",IF(Q21<=TODAY()+30,"Amber","Green")))) -> N/A

Sheet Resident Finance
A1: AS Care - Resident Finance
A3: Resident Name
A4: Last Reviewed
A5: Review Frequency (months) | B5: Monthly
A6: Next Review Due | B6: =IF(B4="","",EDATE(B4,B5))
A7: Responsible Person | B7: Registered Manager
A8: RAG | B8: =IF(B6="","Red",IF(B6<TODAY(),"Red",IF(B6<=TODAY()+30,"Amber","Green"))) -> Red
A9: Evidence Location | B9: Resident file / this register
A12: Checklist Item | B12: Applicable | C12: Jan | D12: Feb | E12: Mar | F12: Apr | G12: May | H12: Jun | I12: Jul | J12: Aug | K12: Sep | L12: Oct | M12: Nov | N12: Dec | O12: Completed | P12: Last Reviewed | Q12: Next Review Due | R12: Responsible Person | S12: RAG | T12: Evidence / Notes
A13: Opening balance recorded | B13: ☐ | C13: ☐ | D13: ☐ | E13: ☐ | F13: ☐ | G13: ☐ | H13: ☐ | I13: ☐ | J13: ☐ | K13: ☐ | L13: ☐ | M13: ☐ | N13: ☐ | O13: ☐ | Q13: =IF(P13="","",EDATE(P13,$B$5)) | R13: Registered Manager | S13: =IF(B13="☐","N/A",IF(Q13="","Red",IF(Q13<TODAY(),"Red",IF(Q13<=TODAY()+30,"Amber","Green")))) -> N/A
A14: Income recorded | B14: ☐ | C14: ☐ | D14: ☐ | E14: ☐ | F14: ☐ | G14: ☐ | H14: ☐ | I14: ☐ | J14: ☐ | K14: ☐ | L14: ☐ | M14: ☐ | N14: ☐ | O14: ☐ | Q14: =IF(P14="","",EDATE(P14,$B$5)) | R14: Registered Manager | S14: =IF(B14="☐","N/A",IF(Q14="","Red",IF(Q14<TODAY(),"Red",IF(Q14<=TODAY()+30,"Amber","Green")))) -> N/A
A15: Expenditure recorded | B15: ☐ | C15: ☐ | D15: ☐ | E15: ☐ | F15: ☐ | G15: ☐ | H15: ☐ | I15: ☐ | J15: ☐ | K15: ☐ | L15: ☐ | M15: ☐ | N15: ☐ | O15: ☐ | Q15: =IF(P15="","",EDATE(P15,$B$5)) | R15: Registered Manager | S15: =IF(B15="☐","N/A",IF(Q15="","Red",IF(Q15<TODAY(),"Red",IF(Q15<=TODAY()+30,"Amber","Green")))) -> N/A
A16: Receipts attached | B16: ☐ | C16: ☐ | D16: ☐ | E16: ☐ | F16: ☐ | G16: ☐ | H16: ☐ | I16: ☐ | J16: ☐ | K16: ☐ | L16: ☐ | M16: ☐ | N16: ☐ | O16: ☐ | Q16: =IF(P16="","",EDATE(P16,$B$5)) | R16: Registered Manager | S16: =IF(B16="☐","N/A",IF(Q16="","Red",IF(Q16<TODAY(),"Red",IF(Q16<=TODAY()+30,"Amber","Green")))) -> N/A
A17: Balance checked | B17: ☐ | C17: ☐ | D17: ☐ | E17: ☐ | F17: ☐ | G17: ☐ | H17: ☐ | I17: ☐ | J17: ☐ | K17: ☐ | L17: ☐ | M17: ☐ | N17: ☐ | O17: ☐ | Q17: =IF(P17="","",EDATE(P17,$B$5)) | R17: Registered Manager | S17: =IF(B17="☐","N/A",IF(Q17="","Red",IF(Q17<TODAY(),"Red",IF(Q17<=TODAY()+30,"Amber","Green")))) -> N/A
A18: Two-person check completed | B18: ☐ | C18: ☐ | D18: ☐ | E18: ☐ | F18: ☐ | G18: ☐ | H18: ☐ | I18: ☐ | J18: ☐ | K18: ☐ | L18: ☐ | M18: ☐ | N18: ☐ | O18: ☐ | Q18: =IF(P18="","",EDATE(P18,$B$5)) | R18: Registered Manager | S18: =IF(B18="☐","N/A",IF(Q18="","Red",IF(Q18<TODAY(),"Red",IF(Q18<=TODAY()+30,"Amber","Green")))) -> N/A
A19: Family/representative updated where applicable | B19: ☐ | C19: ☐ | D19: ☐ | E19: ☐ | F19: ☐ | G19: ☐ | H19: ☐ | I19: ☐ | J19: ☐ | K19: ☐ | L19: ☐ | M19: ☐ | N19: ☐ | O19: ☐ | Q19: =IF(P19="","",EDATE(P19,$B$5)) | R19: Registered Manager | S19: =IF(B19="☐","N/A",IF(Q19="","Red",IF(Q19<TODAY(),"Red",IF(Q19<=TODAY()+30,"Amber","Green")))) -> N/A
A20: Monthly finance review completed | B20: ☐ | C20: ☐ | D20: ☐ | E20: ☐ | F20: ☐ | G20: ☐ | H20: ☐ | I20: ☐ | J20: ☐ | K20: ☐ | L20: ☐ | M20: ☐ | N20: ☐ | O20: ☐ | Q20: =IF(P20="","",EDATE(P20,$B$5)) | R20: Registered Manager | S20: =IF(B20="☐","N/A",IF(Q20="","Red",IF(Q20<TODAY(),"Red",IF(Q20<=TODAY()+30,"Amber","Green")))) -> N/A
A21: Discrepancies escalated | B21: ☐ | C21: ☐ | D21: ☐ | E21: ☐ | F21: ☐ | G21: ☐ | H21: ☐ | I21: ☐ | J21: ☐ | K21: ☐ | L21: ☐ | M21: ☐ | N21: ☐ | O21: ☐ | Q21: =IF(P21="","",EDATE(P21,$B$5)) | R21: Registered Manager | S21: =IF(B21="☐","N/A",IF(Q21="","Red",IF(Q21<TODAY(),"Red",IF(Q21<=TODAY()+30,"Amber","Green")))) -> N/A

Sheet CCTV Consent
A1: AS Care - CCTV Consent
A3: Resident Name
A4: Last Reviewed
A5: Review Frequency (months) | B5: Monthly
A6: Next Review Due | B6: =IF(B4="","",EDATE(B4,B5))
A7: Responsible Person | B7: Registered Manager
A8: RAG | B8: =IF(B6="","Red",IF(B6<TODAY(),"Red",IF(B6<=TODAY()+30,"Amber","Green"))) -> Red
A9: Evidence Location | B9: Resident file / this register
A12: Checklist Item | B12: Applicable | C12: Jan | D12: Feb | E12: Mar | F12: Apr | G12: May | H12: Jun | I12: Jul | J12: Aug | K12: Sep | L12: Oct | M12: Nov | N12: Dec | O12: Completed | P12: Last Reviewed | Q12: Next Review Due | R12: Responsible Person | S12: RAG | T12: Evidence / Notes
A13: Resident consent considered | B13: ☐ | C13: ☐ | D13: ☐ | E13: ☐ | F13: ☐ | G13: ☐ | H13: ☐ | I13: ☐ | J13: ☐ | K13: ☐ | L13: ☐ | M13: ☐ | N13: ☐ | O13: ☐ | Q13: =IF(P13="","",EDATE(P13,$B$5)) | R13: Registered Manager | S13: =IF(B13="☐","N/A",IF(Q13="","Red",IF(Q13<TODAY(),"Red",IF(Q13<=TODAY()+30,"Amber","Green")))) -> N/A
A14: Capacity considered | B14: ☐ | C14: ☐ | D14: ☐ | E14: ☐ | F14: ☐ | G14: ☐ | H14: ☐ | I14: ☐ | J14: ☐ | K14: ☐ | L14: ☐ | M14: ☐ | N14: ☐ | O14: ☐ | Q14: =IF(P14="","",EDATE(P14,$B$5)) | R14: Registered Manager | S14: =IF(B14="☐","N/A",IF(Q14="","Red",IF(Q14<TODAY(),"Red",IF(Q14<=TODAY()+30,"Amber","Green")))) -> N/A
A15: LPA/representative consulted where applicable | B15: ☐ | C15: ☐ | D15: ☐ | E15: ☐ | F15: ☐ | G15: ☐ | H15: ☐ | I15: ☐ | J15: ☐ | K15: ☐ | L15: ☐ | M15: ☐ | N15: ☐ | O15: ☐ | Q15: =IF(P15="","",EDATE(P15,$B$5)) | R15: Registered Manager | S15: =IF(B15="☐","N/A",IF(Q15="","Red",IF(Q15<TODAY(),"Red",IF(Q15<=TODAY()+30,"Amber","Green")))) -> N/A
A16: Purpose explained | B16: ☐ | C16: ☐ | D16: ☐ | E16: ☐ | F16: ☐ | G16: ☐ | H16: ☐ | I16: ☐ | J16: ☐ | K16: ☐ | L16: ☐ | M16: ☐ | N16: ☐ | O16: ☐ | Q16: =IF(P16="","",EDATE(P16,$B$5)) | R16: Registered Manager | S16: =IF(B16="☐","N/A",IF(Q16="","Red",IF(Q16<TODAY(),"Red",IF(Q16<=TODAY()+30,"Amber","Green")))) -> N/A
A17: Areas covered explained | B17: ☐ | C17: ☐ | D17: ☐ | E17: ☐ | F17: ☐ | G17: ☐ | H17: ☐ | I17: ☐ | J17: ☐ | K17: ☐ | L17: ☐ | M17: ☐ | N17: ☐ | O17: ☐ | Q17: =IF(P17="","",EDATE(P17,$B$5)) | R17: Registered Manager | S17: =IF(B17="☐","N/A",IF(Q17="","Red",IF(Q17<TODAY(),"Red",IF(Q17<=TODAY()+30,"Amber","Green")))) -> N/A
A18: Access controls explained | B18: ☐ | C18: ☐ | D18: ☐ | E18: ☐ | F18: ☐ | G18: ☐ | H18: ☐ | I18: ☐ | J18: ☐ | K18: ☐ | L18: ☐ | M18: ☐ | N18: ☐ | O18: ☐ | Q18: =IF(P18="","",EDATE(P18,$B$5)) | R18: Registered Manager | S18: =IF(B18="☐","N/A",IF(Q18="","Red",IF(Q18<TODAY(),"Red",IF(Q18<=TODAY()+30,"Amber","Green")))) -> N/A
A19: Retention period explained | B19: ☐ | C19: ☐ | D19: ☐ | E19: ☐ | F19: ☐ | G19: ☐ | H19: ☐ | I19: ☐ | J19: ☐ | K19: ☐ | L19: ☐ | M19: ☐ | N19: ☐ | O19: ☐ | Q19: =IF(P19="","",EDATE(P19,$B$5)) | R19: Registered Manager | S19: =IF(B19="☐","N/A",IF(Q19="","Red",IF(Q19<TODAY(),"Red",IF(Q19<=TODAY()+30,"Amber","Green")))) -> N/A
A20: Consent signed | B20: ☐ | C20: ☐ | D20: ☐ | E20: ☐ | F20: ☐ | G20: ☐ | H20: ☐ | I20: ☐ | J20: ☐ | K20: ☐ | L20: ☐ | M20: ☐ | N20: ☐ | O20: ☐ | Q20: =IF(P20="","",EDATE(P20,$B$5)) | R20: Registered Manager | S20: =IF(B20="☐","N/A",IF(Q20="","Red",IF(Q20<TODAY(),"Red",IF(Q20<=TODAY()+30,"Amber","Green")))) -> N/A
A21: Annual review completed | B21: ☐ | C21: ☐ | D21: ☐ | E21: ☐ | F21: ☐ | G21: ☐ | H21: ☐ | I21: ☐ | J21: ☐ | K21: ☐ | L21: ☐ | M21: ☐ | N21: ☐ | O21: ☐ | Q21: =IF(P21="","",EDATE(P21,$B$5)) | R21: Registered Manager | S21: =IF(B21="☐","N/A",IF(Q21="","Red",IF(Q21<TODAY(),"Red",IF(Q21<=TODAY()+30,"Amber","Green")))) -> N/A

Sheet Data Sharing Consent
A1: AS Care - Data Sharing Consent
A3: Resident Name
A4: Last Reviewed
A5: Review Frequency (months) | B5: Monthly
A6: Next Review Due | B6: =IF(B4="","",EDATE(B4,B5))
A7: Responsible Person | B7: Registered Manager
A8: RAG | B8: =IF(B6="","Red",IF(B6<TODAY(),"Red",IF(B6<=TODAY()+30,"Amber","Green"))) -> Red
A9: Evidence Location | B9: Resident file / this register
A12: Checklist Item | B12: Applicable | C12: Jan | D12: Feb | E12: Mar | F12: Apr | G12: May | H12: Jun | I12: Jul | J12: Aug | K12: Sep | L12: Oct | M12: Nov | N12: Dec | O12: Completed | P12: Last Reviewed | Q12: Next Review Due | R12: Responsible Person | S12: RAG | T12: Evidence / Notes
A13: Health professionals | B13: ☐ | C13: ☐ | D13: ☐ | E13: ☐ | F13: ☐ | G13: ☐ | H13: ☐ | I13: ☐ | J13: ☐ | K13: ☐ | L13: ☐ | M13: ☐ | N13: ☐ | O13: ☐ | Q13: =IF(P13="","",EDATE(P13,$B$5)) | R13: Registered Manager | S13: =IF(B13="☐","N/A",IF(Q13="","Red",IF(Q13<TODAY(),"Red",IF(Q13<=TODAY()+30,"Amber","Green")))) -> N/A
A14: Local authority | B14: ☐ | C14: ☐ | D14: ☐ | E14: ☐ | F14: ☐ | G14: ☐ | H14: ☐ | I14: ☐ | J14: ☐ | K14: ☐ | L14: ☐ | M14: ☐ | N14: ☐ | O14: ☐ | Q14: =IF(P14="","",EDATE(P14,$B$5)) | R14: Registered Manager | S14: =IF(B14="☐","N/A",IF(Q14="","Red",IF(Q14<TODAY(),"Red",IF(Q14<=TODAY()+30,"Amber","Green")))) -> N/A
A15: CQC/regulators | B15: ☐ | C15: ☐ | D15: ☐ | E15: ☐ | F15: ☐ | G15: ☐ | H15: ☐ | I15: ☐ | J15: ☐ | K15: ☐ | L15: ☐ | M15: ☐ | N15: ☐ | O15: ☐ | Q15: =IF(P15="","",EDATE(P15,$B$5)) | R15: Registered Manager | S15: =IF(B15="☐","N/A",IF(Q15="","Red",IF(Q15<TODAY(),"Red",IF(Q15<=TODAY()+30,"Amber","Green")))) -> N/A
A16: Emergency services | B16: ☐ | C16: ☐ | D16: ☐ | E16: ☐ | F16: ☐ | G16: ☐ | H16: ☐ | I16: ☐ | J16: ☐ | K16: ☐ | L16: ☐ | M16: ☐ | N16: ☐ | O16: ☐ | Q16: =IF(P16="","",EDATE(P16,$B$5)) | R16: Registered Manager | S16: =IF(B16="☐","N/A",IF(Q16="","Red",IF(Q16<TODAY(),"Red",IF(Q16<=TODAY()+30,"Amber","Green")))) -> N/A
A17: Family/representatives | B17: ☐ | C17: ☐ | D17: ☐ | E17: ☐ | F17: ☐ | G17: ☐ | H17: ☐ | I17: ☐ | J17: ☐ | K17: ☐ | L17: ☐ | M17: ☐ | N17: ☐ | O17: ☐ | Q17: =IF(P17="","",EDATE(P17,$B$5)) | R17: Registered Manager | S17: =IF(B17="☐","N/A",IF(Q17="","Red",IF(Q17<TODAY(),"Red",IF(Q17<=TODAY()+30,"Amber","Green")))) -> N/A
A18: Pharmacy | B18: ☐ | C18: ☐ | D18: ☐ | E18: ☐ | F18: ☐ | G18: ☐ | H18: ☐ | I18: ☐ | J18: ☐ | K18: ☐ | L18: ☐ | M18: ☐ | N18: ☐ | O18: ☐ | Q18: =IF(P18="","",EDATE(P18,$B$5)) | R18: Registered Manager | S18: =IF(B18="☐","N/A",IF(Q18="","Red",IF(Q18<TODAY(),"Red",IF(Q18<=TODAY()+30,"Amber","Green")))) -> N/A
A19: GP | B19: ☐ | C19: ☐ | D19: ☐ | E19: ☐ | F19: ☐ | G19: ☐ | H19: ☐ | I19: ☐ | J19: ☐ | K19: ☐ | L19: ☐ | M19: ☐ | N19: ☐ | O19: ☐ | Q19: =IF(P19="","",EDATE(P19,$B$5)) | R19: Registered Manager | S19: =IF(B19="☐","N/A",IF(Q19="","Red",IF(Q19<TODAY(),"Red",IF(Q19<=TODAY()+30,"Amber","Green")))) -> N/A
A20: Hospital | B20: ☐ | C20: ☐ | D20: ☐ | E20: ☐ | F20: ☐ | G20: ☐ | H20: ☐ | I20: ☐ | J20: ☐ | K20: ☐ | L20: ☐ | M20: ☐ | N20: ☐ | O20: ☐ | Q20: =IF(P20="","",EDATE(P20,$B$5)) | R20: Registered Manager | S20: =IF(B20="☐","N/A",IF(Q20="","Red",IF(Q20<TODAY(),"Red",IF(Q20<=TODAY()+30,"Amber","Green")))) -> N/A
A21: Annual review completed | B21: ☐ | C21: ☐ | D21: ☐ | E21: ☐ | F21: ☐ | G21: ☐ | H21: ☐ | I21: ☐ | J21: ☐ | K21: ☐ | L21: ☐ | M21: ☐ | N21: ☐ | O21: ☐ | Q21: =IF(P21="","",EDATE(P21,$B$5)) | R21: Registered Manager | S21: =IF(B21="☐","N/A",IF(Q21="","Red",IF(Q21<TODAY(),"Red",IF(Q21<=TODAY()+30,"Amber","Green")))) -> N/A

Sheet Social Media Consent
A1: AS Care - Social Media Consent
A3: Resident Name
A4: Last Reviewed
A5: Review Frequency (months) | B5: Monthly
A6: Next Review Due | B6: =IF(B4="","",EDATE(B4,B5))
A7: Responsible Person | B7: Registered Manager
A8: RAG | B8: =IF(B6="","Red",IF(B6<TODAY(),"Red",IF(B6<=TODAY()+30,"Amber","Green"))) -> Red
A9: Evidence Location | B9: Resident file / this register
A12: Checklist Item | B12: Applicable | C12: Jan | D12: Feb | E12: Mar | F12: Apr | G12: May | H12: Jun | I12: Jul | J12: Aug | K12: Sep | L12: Oct | M12: Nov | N12: Dec | O12: Completed | P12: Last Reviewed | Q12: Next Review Due | R12: Responsible Person | S12: RAG | T12: Evidence / Notes
A13: Facebook consent | B13: ☐ | C13: ☐ | D13: ☐ | E13: ☐ | F13: ☐ | G13: ☐ | H13: ☐ | I13: ☐ | J13: ☐ | K13: ☐ | L13: ☐ | M13: ☐ | N13: ☐ | O13: ☐ | Q13: =IF(P13="","",EDATE(P13,$B$5)) | R13: Registered Manager | S13: =IF(B13="☐","N/A",IF(Q13="","Red",IF(Q13<TODAY(),"Red",IF(Q13<=TODAY()+30,"Amber","Green")))) -> N/A
A14: Website consent | B14: ☐ | C14: ☐ | D14: ☐ | E14: ☐ | F14: ☐ | G14: ☐ | H14: ☐ | I14: ☐ | J14: ☐ | K14: ☐ | L14: ☐ | M14: ☐ | N14: ☐ | O14: ☐ | Q14: =IF(P14="","",EDATE(P14,$B$5)) | R14: Registered Manager | S14: =IF(B14="☐","N/A",IF(Q14="","Red",IF(Q14<TODAY(),"Red",IF(Q14<=TODAY()+30,"Amber","Green")))) -> N/A
A15: Newsletter consent | B15: ☐ | C15: ☐ | D15: ☐ | E15: ☐ | F15: ☐ | G15: ☐ | H15: ☐ | I15: ☐ | J15: ☐ | K15: ☐ | L15: ☐ | M15: ☐ | N15: ☐ | O15: ☐ | Q15: =IF(P15="","",EDATE(P15,$B$5)) | R15: Registered Manager | S15: =IF(B15="☐","N/A",IF(Q15="","Red",IF(Q15<TODAY(),"Red",IF(Q15<=TODAY()+30,"Amber","Green")))) -> N/A
A16: Marketing material consent | B16: ☐ | C16: ☐ | D16: ☐ | E16: ☐ | F16: ☐ | G16: ☐ | H16: ☐ | I16: ☐ | J16: ☐ | K16: ☐ | L16: ☐ | M16: ☐ | N16: ☐ | O16: ☐ | Q16: =IF(P16="","",EDATE(P16,$B$5)) | R16: Registered Manager | S16: =IF(B16="☐","N/A",IF(Q16="","Red",IF(Q16<TODAY(),"Red",IF(Q16<=TODAY()+30,"Amber","Green")))) -> N/A
A17: Group photograph consent | B17: ☐ | C17: ☐ | D17: ☐ | E17: ☐ | F17: ☐ | G17: ☐ | H17: ☐ | I17: ☐ | J17: ☐ | K17: ☐ | L17: ☐ | M17: ☐ | N17: ☐ | O17: ☐ | Q17: =IF(P17="","",EDATE(P17,$B$5)) | R17: Registered Manager | S17: =IF(B17="☐","N/A",IF(Q17="","Red",IF(Q17<TODAY(),"Red",IF(Q17<=TODAY()+30,"Amber","Green")))) -> N/A
A18: Video consent | B18: ☐ | C18: ☐ | D18: ☐ | E18: ☐ | F18: ☐ | G18: ☐ | H18: ☐ | I18: ☐ | J18: ☐ | K18: ☐ | L18: ☐ | M18: ☐ | N18: ☐ | O18: ☐ | Q18: =IF(P18="","",EDATE(P18,$B$5)) | R18: Registered Manager | S18: =IF(B18="☐","N/A",IF(Q18="","Red",IF(Q18<TODAY(),"Red",IF(Q18<=TODAY()+30,"Amber","Green")))) -> N/A
A19: Restrictions recorded | B19: ☐ | C19: ☐ | D19: ☐ | E19: ☐ | F19: ☐ | G19: ☐ | H19: ☐ | I19: ☐ | J19: ☐ | K19: ☐ | L19: ☐ | M19: ☐ | N19: ☐ | O19: ☐ | Q19: =IF(P19="","",EDATE(P19,$B$5)) | R19: Registered Manager | S19: =IF(B19="☐","N/A",IF(Q19="","Red",IF(Q19<TODAY(),"Red",IF(Q19<=TODAY()+30,"Amber","Green")))) -> N/A
A20: Consent withdrawn process explained | B20: ☐ | C20: ☐ | D20: ☐ | E20: ☐ | F20: ☐ | G20: ☐ | H20: ☐ | I20: ☐ | J20: ☐ | K20: ☐ | L20: ☐ | M20: ☐ | N20: ☐ | O20: ☐ | Q20: =IF(P20="","",EDATE(P20,$B$5)) | R20: Registered Manager | S20: =IF(B20="☐","N/A",IF(Q20="","Red",IF(Q20<TODAY(),"Red",IF(Q20<=TODAY()+30,"Amber","Green")))) -> N/A
A21: Annual review completed | B21: ☐ | C21: ☐ | D21: ☐ | E21: ☐ | F21: ☐ | G21: ☐ | H21: ☐ | I21: ☐ | J21: ☐ | K21: ☐ | L21: ☐ | M21: ☐ | N21: ☐ | O21: ☐ | Q21: =IF(P21="","",EDATE(P21,$B$5)) | R21: Registered Manager | S21: =IF(B21="☐","N/A",IF(Q21="","Red",IF(Q21<TODAY(),"Red",IF(Q21<=TODAY()+30,"Amber","Green")))) -> N/A

Sheet Telephone Consent
A1: AS Care - Telephone Consent
A3: Resident Name
A4: Last Reviewed
A5: Review Frequency (months) | B5: 12
A6: Next Review Due | B6: =IF(B4="","",EDATE(B4,B5))
A7: Responsible Person | B7: Registered Manager
A8: RAG | B8: =IF(B6="","Red",IF(B6<TODAY(),"Red",IF(B6<=TODAY()+30,"Amber","Green"))) -> Red
A9: Evidence Location | B9: Resident file / this register
A12: Checklist Item | B12: Applicable | C12: Jan | D12: Feb | E12: Mar | F12: Apr | G12: May | H12: Jun | I12: Jul | J12: Aug | K12: Sep | L12: Oct | M12: Nov | N12: Dec | O12: Completed | P12: Last Reviewed | Q12: Next Review Due | R12: Responsible Person | S12: RAG | T12: Evidence / Notes
A13: Telephone directory consent | B13: ☐ | C13: ☐ | D13: ☐ | E13: ☐ | F13: ☐ | G13: ☐ | H13: ☐ | I13: ☐ | J13: ☐ | K13: ☐ | L13: ☐ | M13: ☐ | N13: ☐ | O13: ☐ | Q13: =IF(P13="","",EDATE(P13,$B$5)) | R13: Registered Manager | S13: =IF(B13="☐","N/A",IF(Q13="","Red",IF(Q13<TODAY(),"Red",IF(Q13<=TODAY()+30,"Amber","Green")))) -> N/A
A14: Family contact sharing consent | B14: ☐ | C14: ☐ | D14: ☐ | E14: ☐ | F14: ☐ | G14: ☐ | H14: ☐ | I14: ☐ | J14: ☐ | K14: ☐ | L14: ☐ | M14: ☐ | N14: ☐ | O14: ☐ | Q14: =IF(P14="","",EDATE(P14,$B$5)) | R14: Registered Manager | S14: =IF(B14="☐","N/A",IF(Q14="","Red",IF(Q14<TODAY(),"Red",IF(Q14<=TODAY()+30,"Amber","Green")))) -> N/A
A15: Professional contact sharing consent | B15: ☐ | C15: ☐ | D15: ☐ | E15: ☐ | F15: ☐ | G15: ☐ | H15: ☐ | I15: ☐ | J15: ☐ | K15: ☐ | L15: ☐ | M15: ☐ | N15: ☐ | O15: ☐ | Q15: =IF(P15="","",EDATE(P15,$B$5)) | R15: Registered Manager | S15: =IF(B15="☐","N/A",IF(Q15="","Red",IF(Q15<TODAY(),"Red",IF(Q15<=TODAY()+30,"Amber","Green")))) -> N/A
A16: Email communication consent | B16: ☐ | C16: ☐ | D16: ☐ | E16: ☐ | F16: ☐ | G16: ☐ | H16: ☐ | I16: ☐ | J16: ☐ | K16: ☐ | L16: ☐ | M16: ☐ | N16: ☐ | O16: ☐ | Q16: =IF(P16="","",EDATE(P16,$B$5)) | R16: Registered Manager | S16: =IF(B16="☐","N/A",IF(Q16="","Red",IF(Q16<TODAY(),"Red",IF(Q16<=TODAY()+30,"Amber","Green")))) -> N/A
A17: Text/WhatsApp communication consent | B17: ☐ | C17: ☐ | D17: ☐ | E17: ☐ | F17: ☐ | G17: ☐ | H17: ☐ | I17: ☐ | J17: ☐ | K17: ☐ | L17: ☐ | M17: ☐ | N17: ☐ | O17: ☐ | Q17: =IF(P17="","",EDATE(P17,$B$5)) | R17: Registered Manager | S17: =IF(B17="☐","N/A",IF(Q17="","Red",IF(Q17<TODAY(),"Red",IF(Q17<=TODAY()+30,"Amber","Green")))) -> N/A
A18: Restrictions recorded | B18: ☐ | C18: ☐ | D18: ☐ | E18: ☐ | F18: ☐ | G18: ☐ | H18: ☐ | I18: ☐ | J18: ☐ | K18: ☐ | L18: ☐ | M18: ☐ | N18: ☐ | O18: ☐ | Q18: =IF(P18="","",EDATE(P18,$B$5)) | R18: Registered Manager | S18: =IF(B18="☐","N/A",IF(Q18="","Red",IF(Q18<TODAY(),"Red",IF(Q18<=TODAY()+30,"Amber","Green")))) -> N/A
A19: Consent reviewed | B19: ☐ | C19: ☐ | D19: ☐ | E19: ☐ | F19: ☐ | G19: ☐ | H19: ☐ | I19: ☐ | J19: ☐ | K19: ☐ | L19: ☐ | M19: ☐ | N19: ☐ | O19: ☐ | Q19: =IF(P19="","",EDATE(P19,$B$5)) | R19: Registered Manager | S19: =IF(B19="☐","N/A",IF(Q19="","Red",IF(Q19<TODAY(),"Red",IF(Q19<=TODAY()+30,"Amber","Green")))) -> N/A
A20: Annual review completed | B20: ☐ | C20: ☐ | D20: ☐ | E20: ☐ | F20: ☐ | G20: ☐ | H20: ☐ | I20: ☐ | J20: ☐ | K20: ☐ | L20: ☐ | M20: ☐ | N20: ☐ | O20: ☐ | Q20: =IF(P20="","",EDATE(P20,$B$5)) | R20: Registered Manager | S20: =IF(B20="☐","N/A",IF(Q20="","Red",IF(Q20<TODAY(),"Red",IF(Q20<=TODAY()+30,"Amber","Green")))) -> N/A

Sheet Resident Expenses Log
A1: Date | B1: Resident Name | C1: Reference | D1: Money In (£) | E1: Money Out (£) | F1: Description/Purpose | G1: Payment Method | H1: Receipt No. | I1: Running Balance (£) | J1: Recorded By | K1: Resident/LPA Signature | L1: Staff Signature | N1: Resident Expenses Summary
I2: =SUM($D$2:D2)-SUM($E$2:E2) -> 0 | N2: Total Money In | O2: =SUM(D2:D41) -> 0
I3: =SUM($D$2:D3)-SUM($E$2:E3) -> 0 | N3: Total Money Out | O3: =SUM(E2:E41) -> 0
I4: =SUM($D$2:D4)-SUM($E$2:E4) -> 0 | N4: Current Balance | O4: =O2-O3 -> 0
I5: =SUM($D$2:D5)-SUM($E$2:E5) -> 0
I6: =SUM($D$2:D6)-SUM($E$2:E6) -> 0
I7: =SUM($D$2:D7)-SUM($E$2:E7) -> 0
I8: =SUM($D$2:D8)-SUM($E$2:E8) -> 0
I9: =SUM($D$2:D9)-SUM($E$2:E9) -> 0
I10: =SUM($D$2:D10)-SUM($E$2:E10) -> 0
I11: =SUM($D$2:D11)-SUM($E$2:E11) -> 0
I12: =SUM($D$2:D12)-SUM($E$2:E12) -> 0
I13: =SUM($D$2:D13)-SUM($E$2:E13) -> 0
I14: =SUM($D$2:D14)-SUM($E$2:E14) -> 0
I15: =SUM($D$2:D15)-SUM($E$2:E15) -> 0
I16: =SUM($D$2:D16)-SUM($E$2:E16) -> 0
... I41: =SUM($D$2:D41)-SUM($E$2:E41) -> 0

Sheet Meaningful Activity Assessment
A1: Resident Meaningful Activity Assessment Tracker
A2: Complete within 72 hours of admission and review monthly or when needs/preferences change.
A3: Resident Name | B3: Admission Date | C3: Assessment Date | D3: Assessor | E3: Life History Complete | F3: Culture/Religion Recorded | G3: Preferences Recorded | H3: Current Abilities Recorded | I3: Activity Plan Complete | J3: Family Input | K3: Next Review Date | L3: RAG Status | M3: Comments/Evidence
L4: =IF(K4="","Not Started",IF(K4<TODAY(),"Red - Overdue",IF(K4<=TODAY()+30,"Amber - Due Soon","Green - Current"))) -> Not Started
L5: =IF(K5="","Not Started",IF(K5<TODAY(),"Red - Overdue",IF(K5<=TODAY()+30,"Amber - Due Soon","Green - Current"))) -> Not Started
L6: =IF(K6="","Not Started",IF(K6<TODAY(),"Red - Overdue",IF(K6<=TODAY()+30,"Amber - Due Soon","Green - Current"))) -> Not Started
L7: =IF(K7="","Not Started",IF(K7<TODAY(),"Red - Overdue",IF(K7<=TODAY()+30,"Amber - Due Soon","Green - Current"))) -> Not Started
L8: =IF(K8="","Not Started",IF(K8<TODAY(),"Red - Overdue",IF(K8<=TODAY()+30,"Amber - Due Soon","Green - Current"))) -> Not Started
L9: =IF(K9="","Not Started",IF(K9<TODAY(),"Red - Overdue",IF(K9<=TODAY()+30,"Amber - Due Soon","Green - Current"))) -> Not Started
L10: =IF(K10="","Not Started",IF(K10<TODAY(),"Red - Overdue",IF(K10<=TODAY()+30,"Amber - Due Soon","Green - Current"))) -> Not Started
L11: =IF(K11="","Not Started",IF(K11<TODAY(),"Red - Overdue",IF(K11<=TODAY()+30,"Amber - Due Soon","Green - Current"))) -> Not Started
L12: =IF(K12="","Not Started",IF(K12<TODAY(),"Red - Overdue",IF(K12<=TODAY()+30,"Amber - Due Soon","Green - Current"))) -> Not Started
L13: =IF(K13="","Not Started",IF(K13<TODAY(),"Red - Overdue",IF(K13<=TODAY()+30,"Amber - Due Soon","Green - Current"))) -> Not Started
L14: =IF(K14="","Not Started",IF(K14<TODAY(),"Red - Overdue",IF(K14<=TODAY()+30,"Amber - Due Soon","Green - Current"))) -> Not Started
L15: =IF(K15="","Not Started",IF(K15<TODAY(),"Red - Overdue",IF(K15<=TODAY()+30,"Amber - Due Soon","Green - Current"))) -> Not Started
... L123: =IF(K123="","Not Started",IF(K123<TODAY(),"Red - Overdue",IF(K123<=TODAY()+30,"Amber - Due Soon","Green - Current"))) -> Not Started

Sheet Life Story Book
A1: Life Story Book Tracker
A2: Records the resident’s background, identity, achievements, memories and important people.
A3: Resident Name | B3: Birthplace/Childhood | C3: Education/Work | D3: Marriage/Family | E3: Proudest Achievements | F3: Favourite Memories | G3: Important People | H3: Favourite Places | I3: Photos/Objects Included | J3: Completed By | K3: Date Completed | L3: Next Review Date | M3: Comments

Sheet This Is Me
A1: “This Is Me” Profile Tracker
A2: A quick person-centred profile for staff to understand the resident’s routine, communication and comfort needs.
A3: Resident Name | B3: Preferred Name | C3: How I Communicate | D3: Morning Routine | E3: Food/Drinks I Like | F3: Food/Drinks I Dislike | G3: Music/TV I Enjoy | H3: Things Important To Me | I3: What Upsets Me | J3: How To Reassure Me | K3: Hobbies/Interests | L3: Personal Goals | M3: Review Date | N3: Comments

Sheet Weekly Activity Planner
A1: Weekly Person-Centred Activity Planner
A2: Plan activities linked to each resident’s life history, culture, preferences and abilities.
A3: Week Commencing | B3: Resident Name | C3: Monday | D3: Tuesday | E3: Wednesday | F3: Thursday | G3: Friday | H3: Saturday | I3: Sunday | J3: One-to-One Included? | K3: Family/Community Link | L3: Staff Initials | M3: Weekly Outcome/Comments

Sheet Daily Activity Outcomes
A1: Daily Activity Outcome Record
A2: Record what was offered/completed and the resident’s emotional wellbeing outcome.
A3: Date | B3: Resident Name | C3: Activity Offered/Completed | D3: Life History Link | E3: One-to-One or Group | F3: Duration | G3: Mood Before | H3: Mood After | I3: Outcome/Evidence | J3: Staff Initials

Sheet Monthly Activity Audit
A1: Monthly Meaningful Activity Audit
A2: Management oversight audit to evidence that meaningful occupation is embedded and reviewed.
A3: Month | B3: Auditor | C3: Residents Audited | D3: Assessments Completed % | E3: Life Story Complete % | F3: This Is Me Complete % | G3: Weekly Planners Completed % | H3: Daily Outcomes Recorded % | I3: Family Input Evidenced? | J3: Photos/Consent Checked? | K3: Overall RAG | L3: Actions Required | M3: Responsible Person | N3: Target Date | O3: Completed Date | P3: Comments

Sheet Activity Evidence Tracker
A1: Activity Evidence Tracker
A2: Use this tab to map evidence for CQC and management review.
A3: Resident Name | B3: Evidence Type | C3: Evidence Location/Folder | D3: Date Added | E3: Linked To Life History? | F3: Consent Checked? | G3: Added By | H3: Review Required? | I3: Comments

Sheet Decisions on MCA, DOLS or BI
A1: Step | B1: Decision / Action | C1: Outcome / Next Step | D1: Evidence Required | E1: Evidence Required
A2: 1 | B2: CCTV operating in communal areas? | C2: If YES → Step 2 | D2: CCTV Policy, DPIA | E2: CCTV Policy
A3: 2 | B3: Resident affected by CCTV? | C3: If YES → Step 3 | D3: Care Plan | E3: Resident location/risk review
A4: 3 | B4: Complete Mental Capacity Assessment (MCA) for CCTV decision. | C4: Has capacity → Step 4 Lacks capacity → Step 5 | D4: MCA Assessment | E4: Mental Capacity Assessment
A5: 4 | B5: Resident HAS capacity. Explain CCTV, GDPR, purpose, access and retention. Seek consent. | C5: Consent given → Record and review. Consent refused → Respect decision unless lawful exception. | D5: Signed Consent Form | E5: CCTV Consent Form
A6: 5 | B6: Resident LACKS capacity. | C6: Hold Best Interest Decision meeting. | D6: MCA Outcome | E6: Best Interest Record
A7: 6 | B7: Best Interest Decision | C7: Consult family/LPA/Deputy/IMCA, consider wishes, least restrictive option. | D7: Best Interest Record | E7: Care Plan, Risk Assessment
A8: 7 | B8: Is resident subject to restrictions amounting to deprivation of liberty? | C8: If YES ensure DoLS/LPS authorisation is in place or requested. | D8: DoLS Authorisation / Application | E8: Audit, DPIA, Access Log
A9: 8 | B9: Update Care Plan & Risk Assessment | C9: Record CCTV rationale, privacy measures and review date. | D9: Care Plan & Risk Assessment
A10: 9 | B10: Governance | C10: Monthly audit, access log, signage, DPIA review, annual policy review. | D10: Audit & Dashboard
A13: Colour Key
A14: Blue | B14: Assessment/Start
A15: Yellow | B15: Capacity & Consent
A16: Green | B16: Best Interest / DoLS
A17: Red | B17: Implementation & Governance

Sheet Family Involvement Flow
A1: Family Involvement in Decisions - CQC Evidence Flowchart
A3: Step | B3: Decision / Action | C3: If YES | D3: If NO / Alternative | E3: Evidence Required | F3: RAG
A4: 1 | B4: Is a care, treatment, risk, activity, safeguarding, finance, end of life or significant decision required? | C4: Go to Step 2 | D4: Record no decision required | E4: Care plan / daily notes | F4: 🟦
A5: 2 | B5: Does the resident have capacity for this specific decision? | C5: Ask resident whether they want family involved | D5: Complete MCA and go to Best Interest pathway | E5: Decision-specific MCA if capacity is unclear | F5: 🟨
A6: 3 | B6: Resident HAS capacity: do they consent to family involvement / information sharing? | C6: Involve family as requested by resident | D6: Respect resident choice unless legal/safeguarding duty applies | E6: Consent to share, communication preference record | F6: 🟩
A7: 4 | B7: Resident LACKS capacity: complete Best Interest process | C7: Consult family, Health & Welfare LPA, Deputy, IMCA where appropriate | D7: Record reason if family cannot/should not be consulted | E7: MCA, Best Interest record, LPA evidence | F7: 🟧
A8: 5 | B8: Is this a significant event or material change? e.g. fall, hospital, deterioration, medication issue, safeguarding, weight loss, pressure damage, refusal of treatment | C8: Notify family/LPA promptly where appropriate | D8: Record rationale if not informed | E8: Family notification record, daily notes | F8: 🟥
A9: 6 | B9: Update documentation after discussion | C9: Care plan, risk assessment, communication log and action plan updated | D9: Escalate to manager if not updated | E9: Care plan, risk assessment, communication log | F9: 🟦
A10: 7 | B10: Set review date | C10: Review at next care plan review or sooner if condition/wishes change | D10: Manager to chase overdue reviews | E10: Review record / dashboard | F10: 🟩
A12: Colour Key | B12: Meaning
A13: Green | B13: Consent/decision evidenced and complete
A14: Amber | B14: Capacity / best interest / family involvement needs assessment
A15: Red | B15: Significant event or urgent escalation required
A16: Blue | B16: Governance / documentation step

Sheet Family Communication Log
A1: Family Communication Log - Evidence of Family / LPA Involvement
A3: Date | B3: Resident | C3: Family / LPA Name | D3: Relationship / Role | E3: Decision / Event Discussed | F3: Resident Capacity? | G3: Resident consent to share? | H3: Reason for contact | I3: Information shared | J3: Family / LPA views | K3: Agreed actions | L3: Owner | M3: Due Date | N3: Completed Date | O3: Status | P3: Manager Oversight

Sheet Family Decision Register
A1: Family Involvement Decision Register - Linked Evidence Tracker
A3: Resident | B3: Decision Type | C3: Decision Date | D3: Capacity Outcome | E3: Family Involved? | F3: LPA / Deputy / IMCA Involved? | G3: Resident Consent Recorded? | H3: Best Interest Required? | I3: Best Interest Completed? | J3: Care Plan Updated? | K3: Risk Assessment Updated? | L3: Communication Log Completed? | M3: Review Due | N3: Current Status | O3: RAG | P3: Manager Comments | Q3: Manager Sign-off
O4: =IF(N4="Complete","Green",IF(N4="Overdue","Red",IF(N4="Escalated","Red",IF(N4="In Progress","Amber",""))))
O5: =IF(N5="Complete","Green",IF(N5="Overdue","Red",IF(N5="Escalated","Red",IF(N5="In Progress","Amber",""))))
O6: =IF(N6="Complete","Green",IF(N6="Overdue","Red",IF(N6="Escalated","Red",IF(N6="In Progress","Amber",""))))
O7: =IF(N7="Complete","Green",IF(N7="Overdue","Red",IF(N7="Escalated","Red",IF(N7="In Progress","Amber",""))))
O8: =IF(N8="Complete","Green",IF(N8="Overdue","Red",IF(N8="Escalated","Red",IF(N8="In Progress","Amber",""))))
O9: =IF(N9="Complete","Green",IF(N9="Overdue","Red",IF(N9="Escalated","Red",IF(N9="In Progress","Amber",""))))
O10: =IF(N10="Complete","Green",IF(N10="Overdue","Red",IF(N10="Escalated","Red",IF(N10="In Progress","Amber",""))))
O11: =IF(N11="Complete","Green",IF(N11="Overdue","Red",IF(N11="Escalated","Red",IF(N11="In Progress","Amber",""))))
O12: =IF(N12="Complete","Green",IF(N12="Overdue","Red",IF(N12="Escalated","Red",IF(N12="In Progress","Amber",""))))
O13: =IF(N13="Complete","Green",IF(N13="Overdue","Red",IF(N13="Escalated","Red",IF(N13="In Progress","Amber",""))))
O14: =IF(N14="Complete","Green",IF(N14="Overdue","Red",IF(N14="Escalated","Red",IF(N14="In Progress","Amber",""))))
O15: =IF(N15="Complete","Green",IF(N15="Overdue","Red",IF(N15="Escalated","Red",IF(N15="In Progress","Amber",""))))
... O103: =IF(N103="Complete","Green",IF(N103="Overdue","Red",IF(N103="Escalated","Red",IF(N103="In Progress","Amber",""))))
